Workbook

Sheet INVENTARIO JULIO 
A3: Inventario Inicial/Final Tiendas | F3: Inventario Inicial/Final Almacenes de Cendis
A4: Almacen | B4: Valor Inicial | C4: Valor Final | F4: Almacen | G4: Valor Inicial | H4: Valor Final
A5: ACB/Existencias | B5: 49023.84 | C5: 39729.41 | F5: CTDD/Existencias | G5: 1245467.6 | H5: 1635382.9 | I5: CENTRO DE DISTRIBUCION (BULTO CERRADO)
A6: ACG/Existencias | B6: 47200.37 | C6: 40562.12 | F6: CENSWM/Existencias | G6: 43153.63 | H6: 45844.31 | I6: SHOW ROOM
A7: ACO/Existencias | B7: 64130.41 | C7: 72396.54 | F7: EVENC/Existencias | G7: 14342.95 | H7: 15056.99 | I7: EVENTOS
A8: ADO/Existencias | B8: 46414.04 | C8: 46940.82 | F8: FARMA/Existencias | G8: 23427.75 | H8: 28833.02 | I8: FARMATODO
A9: ADS - TCY/Existencias | B9: 59025.22 | C9: 54097.42 | F9: GECOM/Existencias | G9: 19.14 | H9: 0
A10: ANT/Existencias | B10: 61641.29 | C10: 51455.89 | F10: ICDD/Existencias | G10: 538868.8 | H10: 416831.92 | I10: INSUMOS
A11: APU/Existencias | B11: 55092.81 | C11: 62230.8 | F11: MIXTO/Existencias | G11: 578017.9 | H11: 595224.93 | I11: ZONA MIXTA
A12: ARO - INT/Existencias | B12: 0 | C12: 0 | F12: MTA/Existencias | G12: 193641.43 | H12: 849946.04 | I12: MATERIA PRIMA
A13: ARO - NAC/Existencias | B13: 0 | C13: 0 | F13: SUM/Existencias | G13: 994.26 | H13: 967.93 | I13: REDES
A14: ATV/Existencias | B14: 40831.93 | C14: 41135.18 | F14: DEVVENEZ/Existencias | G14: 23365.79 | H14: 117251.43 | I14: DEVOLUCIONES
A15: AVM/Existencias | B15: 25361.18 | C15: 29877.56 | F15: PCRTI/Existencias | G15: 65708.4 | H15: 65359.7
A16: BAC/Existencias | B16: 41408.77 | C16: 35083.37 | F16: TI-CENDIS/Existencias | G16: 96.79 | H16: 4616.78
A17: BCC/Existencias | B17: 56729.44 | C17: 48350.95 | F17: PICK/Existencias | G17: 798474.51 | H17: 932148.66 | I17: PICKING VARIEDAD DE MERCANCIA
A18: BCD/Existencias | B18: 35401.29 | C18: 31794.64 | F18: VMC /Existencias | G18: 997.96 | H18: 862.24 | I18: CHUCHERIAS
A19: BCN/Existencias | B19: 53754.66 | C19: 51746.29 | F19: CEN - MYR/Existencias | G19: 176.6 | H19: -320.46
A20: BCO/Existencias | B20: 40650.95 | C20: 45999.82 | F20: Totales | G20: =SUM(G5:G19) -> 3526753.6 | H20: =SUM(H5:H19) -> 4708006.4
A21: BJM/Existencias | B21: 52190.32 | C21: 51828.39
A22: BLS /Existencias | B22: 0 | C22: 38029.82
A23: BNS/Existencias | B23: 89752.63 | C23: 79186.7
A24: BRC/Existencias | B24: 36692.63 | C24: 47018.23 | F24: Venez/Existencias | G24: 13400.92 | H24: -149722.8
A25: BTA/Existencias | B25: 60108.49 | C25: 43181.87
A26: BVC/Existencias | B26: 90014.11 | C26: 66192.63 | F26: Total almacenes cendis | G26: =G24+G20 -> 3540154.5 | H26: =H24+H20 -> 4558283.6
A27: BZC/Existencias | B27: 37568.43 | C27: 34535.52
A28: BZD/Existencias | B28: 54697.45 | C28: 62895.26
A29: BZT/Existencias | B29: 35239.69 | C29: 34550.52
A30: BZU/Existencias | B30: 40397.51 | C30: 38736.61
A31: CAG/Existencias | B31: 39194.46 | C31: 34749.9
A32: CAT/Existencias | B32: 101322.83 | C32: 92309.46
A33: CBM/Existencias | B33: 58012.13 | C33: 70389
A34: CBQ/Existencias | B34: 60140.37 | C34: 63475.85
A35: CBR/Existencias | B35: 44760.36 | C35: 38903.25
A36: CBV/Existencias | B36: 59311.17 | C36: 57708.45
A37: CCA/Existencias | B37: 61838.12 | C37: 44466.35
A38: CCB/Existencias | B38: 45461.46 | C38: 35402.43
... A226: ZAR/Existencias | B226: 55946.11 | C226: 47828.13
A227: Total general | B227: =SUM(B5:B226) -> 10949399 | C227: =SUM(C5:C226) -> 9767525.9

Sheet INV GARANTIAS JULIO
A2: Garantias Inicial/Final Tiendas | E2: Garantias Inicial/Final Almacenes de Cendis
A3: Almacen | B3: Valor Inicial | C3: Valor Final | E3: Almacen | F3: Valor Inicial | G3: Valor Final
A4: ABM-GAR/Existencias | B4: 149.62 | C4: 488.85 | E4: CEN-GAR/Control de calidad | F4: 78.14 | G4: 0
A5: ABM-GAR/Existencias/Existencias | B5: -29.71 | C5: -31.83 | E5: CEN-GAR/Entrada | F5: 756.86 | G5: 0
A6: ACB-GAR/Existencias | B6: 588.07 | C6: 161.21 | E6: CEN-GAR/Existencias | F6: 135534.27 | G6: 204546.68
A7: ACG-GAR/Existencias | B7: 166.78 | C7: 11.85 | E7: CEN-GAR/PosproducciÃ³n | F7: 121.44 | G7: 0
A8: ACO-GAR/Existencias | B8: 781.18 | C8: 397.9 | E8: CENSWM-GAR/Existencias | F8: 0 | G8: 0.25
A9: ADO-GAR/Existencias | B9: 0 | C9: 217.52 | E9: Totales | F9: =SUM(F4:F8) -> 136490.71 | G9: =SUM(G4:G8) -> 204546.93
A10: ADSTCY-GAR/Existencias | B10: 23.09 | C10: 8.32
A11: ANT-GAR/Existencias | B11: 64.1 | C11: 65.1
A12: APU-GAR/Existencias | B12: 532.4 | C12: -69.19
A13: AROINT-GAR/Existencias | B13: -18.34 | C13: 0
A14: ARONAC-GAR/Existencias | B14: -29.75 | C14: 0
A15: ATV-GAR/Existencias | B15: 154.72 | C15: 0
A16: AVM-GAR/Existencias | B16: 126.32 | C16: 102.45
A17: BAC-GAR/Existencias | B17: 0 | C17: 640.31
A18: BCC-GAR/Existencias | B18: 477.82 | C18: 71.7
A19: BCD-GAR/Existencias | B19: 470.33 | C19: 60.23
A20: BCN-GAR/Existencias | B20: 58.93 | C20: 11.96
A21: BCO-GAR/Existencias | B21: 194.94 | C21: 178.56
... A212: ZAR-GAR/Existencias | B212: 253.6 | C212: 622.68
A213: Totales | B213: =SUM(B4:B212) -> 60619.1 | C213: =SUM(C4:C212) -> 51480.3

Sheet EDR JULIO
A1: Centros de Costos | B1: Gastos | C1: Costos | D1: Ingresos | E1: Otros Ingresos | F1: Total de ingresos | G1: Total general
A2: [ ABM ] - AV BOLIVAR DE MATURIN | B2: 391.179 | F2: =SUM(D2,E2) -> 0 | G2: =B2+C2+D2+E2 -> 391.179 | H2: =IFERROR(C2/F2,0%) -> 0
A3: [ ACB ] - AV LIBERTADOR CIUDAD BOLIVAR | B3: 9865.879 | C3: 22717.278 | D3: -42850.541 | E3: -6262.729 | F3: =SUM(D3,E3) -> -49113.27 | G3: =B3+C3+D3+E3 -> -16530.113 | H3: =IFERROR(C3/F3,0%) -> -0.46254868
A4: [ ACG ] - ACHAGUAS | B4: 4713.688 | C4: 29078.434 | D4: -49631.89 | E4: -7309.932 | F4: =SUM(D4,E4) -> -56941.822 | G4: =B4+C4+D4+E4 -> -23149.7 | H4: =IFERROR(C4/F4,0%) -> -0.51066919
A5: [ ACO ] - ANACO | B5: 7403.344 | C5: 60262.727 | D5: -104454 | E5: -14443.039 | F5: =SUM(D5,E5) -> -118897.04 | G5: =B5+C5+D5+E5 -> -51230.972 | H5: =IFERROR(C5/F5,0%) -> -0.50684799
A6: [ ADO ] - ALTAGRACIA DEL ORITUCO | B6: 5414.652 | C6: 41163.746 | D6: -73293.141 | E6: -10855.169 | F6: =SUM(D6,E6) -> -84148.31 | G6: =B6+C6+D6+E6 -> -37569.912 | H6: =IFERROR(C6/F6,0%) -> -0.4891809
A7: [ ADS - BQT ] - AEDOS BARQUISIMETO | B7: -11.033 | F7: =SUM(D7,E7) -> 0 | G7: =B7+C7+D7+E7 -> -11.033 | H7: =IFERROR(C7/F7,0%) -> 0
A8: [ ADS - TCY ] - AEDOS TOCUYITO | B8: 25121.691 | C8: 6022.502 | D8: -17002.863 | E8: -2326.228 | F8: =SUM(D8,E8) -> -19329.091 | G8: =B8+C8+D8+E8 -> 11815.102 | H8: =IFERROR(C8/F8,0%) -> -0.31157709
A9: [ ANT ] - ANTIMANO | B9: 6722.854 | C9: 5543.328 | D9: -10027.621 | E9: -1473.34 | F9: =SUM(D9,E9) -> -11500.961 | G9: =B9+C9+D9+E9 -> 765.221 | H9: =IFERROR(C9/F9,0%) -> -0.48198824
A10: [ APU ] - APURE | B10: 7256.201 | C10: 49343.272 | D10: -81546.616 | E10: -12020.995 | F10: =SUM(D10,E10) -> -93567.611 | G10: =B10+C10+D10+E10 -> -36968.138 | H10: =IFERROR(C10/F10,0%) -> -0.52735419
A11: [ ARO - INT ] - AEROPUERTO INTERNACIONAL | B11: 1807.084 | C11: -181.214 | F11: =SUM(D11,E11) -> 0 | G11: =B11+C11+D11+E11 -> 1625.87 | H11: =IFERROR(C11/F11,0%) -> 0
A12: [ ARO - NAC ] - AEROPUERTO NACIONAL | B12: 2174.264 | C12: 7697.841 | F12: =SUM(D12,E12) -> 0 | G12: =B12+C12+D12+E12 -> 9872.105 | H12: =IFERROR(C12/F12,0%) -> 0
A13: [ ARY ] - AROA YARACUY | B13: 16.62 | C13: -32.068 | F13: =SUM(D13,E13) -> 0 | G13: =B13+C13+D13+E13 -> -15.448 | H13: =IFERROR(C13/F13,0%) -> 0
A14: [ ATV ] - ALTA VISTA | B14: 310.188 | C14: 18339.91 | D14: -35063.775 | E14: -5058.827 | F14: =SUM(D14,E14) -> -40122.602 | G14: =B14+C14+D14+E14 -> -21472.504 | H14: =IFERROR(C14/F14,0%) -> -0.45709673
A15: [ AVM ] - AVENIDA MARIÑO | B15: 4065.688 | C15: 24877.791 | D15: -44264.45 | F15: =SUM(D15,E15) -> -44264.45 | G15: =B15+C15+D15+E15 -> -15320.971 | H15: =IFERROR(C15/F15,0%) -> -0.56202643
A16: [ BAC ] - BUENOS AIRES CANGURO | B16: 5359.375 | C16: 22589.678 | D16: -39774.96 | E16: -5408.154 | F16: =SUM(D16,E16) -> -45183.114 | G16: =B16+C16+D16+E16 -> -17234.061 | H16: =IFERROR(C16/F16,0%) -> -0.49995841
A17: [ BCC ] - BISCUCUY | B17: 8264.593 | C17: 17173.338 | D17: -28714.826 | E17: -4288.169 | F17: =SUM(D17,E17) -> -33002.995 | G17: =B17+C17+D17+E17 -> -7565.064 | H17: =IFERROR(C17/F17,0%) -> -0.52035696
A18: [ BCD ] - BARINAS CC DORADO | B18: 3561.329 | C18: 16467.36 | D18: -28423.281 | E18: -4072.416 | F18: =SUM(D18,E18) -> -32495.697 | G18: =B18+C18+D18+E18 -> -12467.008 | H18: =IFERROR(C18/F18,0%) -> -0.50675509
A19: [ BCN ] - BARCELONA | B19: 7330.502 | C19: 38567.289 | D19: -69454.678 | E19: -9945.594 | F19: =SUM(D19,E19) -> -79400.272 | G19: =B19+C19+D19+E19 -> -33502.481 | H19: =IFERROR(C19/F19,0%) -> -0.48573245
A20: [ BCO ] - BOCONO | B20: 6102.949 | C20: 23941.996 | D20: -42456.901 | E20: -5997.832 | F20: =SUM(D20,E20) -> -48454.733 | G20: =B20+C20+D20+E20 -> -18409.788 | H20: =IFERROR(C20/F20,0%) -> -0.49411058
A21: [ BJM ] - BEJUMA | B21: 6610.181 | C21: 24201.919 | D21: -42637.384 | E21: -6002.81 | F21: =SUM(D21,E21) -> -48640.194 | G21: =B21+C21+D21+E21 -> -17828.094 | H21: =IFERROR(C21/F21,0%) -> -0.49757036
A22: [ BLS ] - BAILADORES | B22: 784.006 | C22: 815.361 | D22: -2366.67 | E22: -341.41 | F22: =SUM(D22,E22) -> -2708.08 | G22: =B22+C22+D22+E22 -> -1108.713 | H22: =IFERROR(C22/F22,0%) -> -0.30108453
A23: [ BNS ] - BARINAS SHOP | B23: 11196.559 | C23: 63765.986 | D23: -104268.82 | E23: -15267.428 | F23: =SUM(D23,E23) -> -119536.24 | G23: =B23+C23+D23+E23 -> -44573.699 | H23: =IFERROR(C23/F23,0%) -> -0.53344479
A24: [ BRC ] - BARRANCAS | B24: 4028.58 | C24: 19262.203 | D24: -33678.031 | E24: -4809.871 | F24: =SUM(D24,E24) -> -38487.902 | G24: =B24+C24+D24+E24 -> -15197.119 | H24: =IFERROR(C24/F24,0%) -> -0.50047423
A25: [ BTA ] - BARUTA | B25: 11531.063 | C25: 32236.414 | D25: -60104.394 | E25: -8934.499 | F25: =SUM(D25,E25) -> -69038.893 | G25: =B25+C25+D25+E25 -> -25271.416 | H25: =IFERROR(C25/F25,0%) -> -0.46693121
A26: [ BVC ] - BAZAR VALENCIA CANGURO | B26: 11074.405 | C26: 69758.571 | D26: -107646.38 | E26: -15914.072 | F26: =SUM(D26,E26) -> -123560.45 | G26: =B26+C26+D26+E26 -> -42727.477 | H26: =IFERROR(C26/F26,0%) -> -0.56457037
A27: [ BZC ] - BAZAR 4 | B27: 4805.209 | C27: 28294.648 | D27: -43041.202 | E27: -5823.708 | F27: =SUM(D27,E27) -> -48864.91 | G27: =B27+C27+D27+E27 -> -15765.053 | H27: =IFERROR(C27/F27,0%) -> -0.57903817
... A44: [ CEN - MYR ] - CENDIS MAYOR | B44: 808.31 | C44: 2363.826 | D44: -3726.185 | E44: -2149.48 | F44: =SUM(D44,E44) -> -5875.665 | G44: =B44+C44+D44+E44 -> -2703.529 | H44: =IFERROR(C44/F44,0%) -> -0.40230782
A45: [ CEN - SWM ] - CENDIS SHOWROOM | C45: 266.303 | D45: -1124.137 | E45: -177.379 | F45: =SUM(D45,E45) -> -1301.516 | G45: =B45+C45+D45+E45 -> -1035.213 | H45: =IFERROR(C45/F45,0%) -> -0.20460985
A46: [ CHA ] - CHACAO | B46: 5047.858 | C46: 19736.182 | D46: -42880.256 | E46: -6232.108 | F46: =SUM(D46,E46) -> -49112.364 | G46: =B46+C46+D46+E46 -> -24328.324 | H46: =IFERROR(C46/F46,0%) -> -0.40185771
A47: [ CHC ] - CHICHIRIVICHE | B47: 3995.675 | C47: 10575.546 | D47: -18154.255 | E47: -2724.352 | F47: =SUM(D47,E47) -> -20878.607 | G47: =B47+C47+D47+E47 -> -6307.386 | H47: =IFERROR(C47/F47,0%) -> -0.50652546
A48: [ CHI ] - CHIVACOA | B48: 4390.999 | C48: 28951.562 | D48: -53224.149 | E48: -7030.76 | F48: =SUM(D48,E48) -> -60254.909 | G48: =B48+C48+D48+E48 -> -26912.348 | H48: =IFERROR(C48/F48,0%) -> -0.4804847
A49: [ CHV ] - CHARALLAVE | B49: 11267.249 | C49: 82692.782 | D49: -138038.53 | E49: -19170.415 | F49: =SUM(D49,E49) -> -157208.94 | G49: =B49+C49+D49+E49 -> -63248.91 | H49: =IFERROR(C49/F49,0%) -> -0.52600559
A50: [ CJP ] - CINCO DE JULIO | B50: 5043.989 | C50: 27746.663 | D50: -49919.49 | E50: -6394.019 | F50: =SUM(D50,E50) -> -56313.509 | G50: =B50+C50+D50+E50 -> -23522.857 | H50: =IFERROR(C50/F50,0%) -> -0.49271771
A51: [ CLB ] - CALABOZO | B51: 7609.76 | C51: 47243.148 | D51: -87100.305 | E51: -12683.361 | F51: =SUM(D51,E51) -> -99783.666 | G51: =B51+C51+D51+E51 -> -44930.758 | H51: =IFERROR(C51/F51,0%) -> -0.47345573
A52: [ CLL ] - CALLAO | B52: 12015.378 | C52: 30474.522 | D52: -47645.74 | E52: -6837.114 | F52: =SUM(D52,E52) -> -54482.854 | G52: =B52+C52+D52+E52 -> -11992.954 | H52: =IFERROR(C52/F52,0%) -> -0.55934151
A53: [ CLP ] - CATIA LIFE PHONE | B53: 15583.996 | C53: 71880.752 | D53: -117329.44 | E53: -17034.954 | F53: =SUM(D53,E53) -> -134364.39 | G53: =B53+C53+D53+E53 -> -46899.647 | H53: =IFERROR(C53/F53,0%) -> -0.53496875
A54: [ CLT ] - COLONIA TOVAR | B54: 16727.687 | C54: 25911.399 | D54: -44452.949 | E54: -6328.682 | F54: =SUM(D54,E54) -> -50781.631 | G54: =B54+C54+D54+E54 -> -8142.545 | H54: =IFERROR(C54/F54,0%) -> -0.51025141
A55: [ CMC ] - CUA | B55: 8269.654 | C55: 48175.151 | D55: -90917.192 | E55: -11156.185 | F55: =SUM(D55,E55) -> -102073.38 | G55: =B55+C55+D55+E55 -> -45628.572 | H55: =IFERROR(C55/F55,0%) -> -0.47196588
A56: [ CMO ] - COMERCIO | B56: 12783.126 | C56: 35442.021 | D56: -60112.355 | E56: -9033.568 | F56: =SUM(D56,E56) -> -69145.923 | G56: =B56+C56+D56+E56 -> -20920.776 | H56: =IFERROR(C56/F56,0%) -> -0.51256849
A57: [ CNA ] - CUMANACOA | B57: 5085.302 | C57: 35552.533 | D57: -61465.546 | E57: -8074.348 | F57: =SUM(D57,E57) -> -69539.894 | G57: =B57+C57+D57+E57 -> -28902.059 | H57: =IFERROR(C57/F57,0%) -> -0.51125377
... A69: [ CTL ] - CARTANAL | B69: 6071.371 | C69: 48145.639 | D69: -85888.407 | E69: -10477.817 | F69: =SUM(D69,E69) -> -96366.224 | G69: =B69+C69+D69+E69 -> -42149.214 | H69: =IFERROR(C69/F69,0%) -> -0.49961114
A70: [ CTM ] - CATIA LA MAR | B70: 6695.99 | C70: 13458.454 | E70: -6.86 | F70: =SUM(D70,E70) -> -6.86 | G70: =B70+C70+D70+E70 -> 20147.584 | H70: =IFERROR(C70/F70,0%) -> -1961.8738
A71: [ CTO ] - CEMENTERIO | B71: 12371.273 | C71: 32697.884 | D71: -61586.48 | E71: -8810.259 | F71: =SUM(D71,E71) -> -70396.739 | G71: =B71+C71+D71+E71 -> -25327.582 | H71: =IFERROR(C71/F71,0%) -> -0.46448009
A72: [ CTS ] - CIUDAD TAMANACO SEGUNDO | B72: 5232.203 | C72: 12047.007 | D72: -29898.696 | E72: -4109.02 | F72: =SUM(D72,E72) -> -34007.716 | G72: =B72+C72+D72+E72 -> -16728.506 | H72: =IFERROR(C72/F72,0%) -> -0.35424334
A73: [ CTT ] - CITY 3 | B73: 12667.763 | C73: 56386.21 | D73: -99227.5 | E73: -14867.419 | F73: =SUM(D73,E73) -> -114094.92 | G73: =B73+C73+D73+E73 -> -45040.946 | H73: =IFERROR(C73/F73,0%) -> -0.49420439
A74: [ CTU ] - CITY 1 | B74: 4103.591 | C74: 11018.409 | D74: -18440.447 | E74: -2786.482 | F74: =SUM(D74,E74) -> -21226.929 | G74: =B74+C74+D74+E74 -> -6104.929 | H74: =IFERROR(C74/F74,0%) -> -0.51907692
A75: [ CUA ] - CUMANA SHOP | B75: 9890.252 | C75: 56365.672 | D75: -100824.4 | E75: -14104.605 | F75: =SUM(D75,E75) -> -114929.01 | G75: =B75+C75+D75+E75 -> -48673.083 | H75: =IFERROR(C75/F75,0%) -> -0.49043904
A76: [ CUG ] - CAUCAGUA | B76: 19480.882 | C76: 31423.223 | D76: -54052.602 | E76: -7952.419 | F76: =SUM(D76,E76) -> -62005.021 | G76: =B76+C76+D76+E76 -> -11100.916 | H76: =IFERROR(C76/F76,0%) -> -0.50678514
A77: [ DCA ] - DUACA | B77: 4080.293 | C77: 19191.459 | D77: -35712.327 | E77: -4883.951 | F77: =SUM(D77,E77) -> -40596.278 | G77: =B77+C77+D77+E77 -> -17324.526 | H77: =IFERROR(C77/F77,0%) -> -0.47273937
A78: [ ECJ ] - EL CUJI | B78: 5310.243 | C78: 16865.696 | D78: -36059.854 | E78: -5022.25 | F78: =SUM(D78,E78) -> -41082.104 | G78: =B78+C78+D78+E78 -> -18906.165 | H78: =IFERROR(C78/F78,0%) -> -0.41053633
A79: [ ECM ] ECOMMERCE | B79: 3148.116 | C79: 90107.962 | D79: -139682.65 | E79: -22020.409 | F79: =SUM(D79,E79) -> -161703.06 | G79: =B79+C79+D79+E79 -> -68446.983 | H79: =IFERROR(C79/F79,0%) -> -0.55724339
A80: [ EJD ] - EJIDO | B80: 4017.063 | C80: 18903.991 | D80: -35193.64 | E80: -4686.238 | F80: =SUM(D80,E80) -> -39879.878 | G80: =B80+C80+D80+E80 -> -16958.824 | H80: =IFERROR(C80/F80,0%) -> -0.47402329
A81: [ ELZ ] - ELORZA | B81: 4548.703 | C81: 15509.833 | D81: -26868.105 | E81: -4062.075 | F81: =SUM(D81,E81) -> -30930.18 | G81: =B81+C81+D81+E81 -> -10871.644 | H81: =IFERROR(C81/F81,0%) -> -0.50144658
A82: [ EMT ] - EL MANTECO | B82: 7739.264 | C82: 14731.398 | D82: -22851.346 | E82: -3241.499 | F82: =SUM(D82,E82) -> -26092.845 | G82: =B82+C82+D82+E82 -> -3622.183 | H82: =IFERROR(C82/F82,0%) -> -0.56457615
... A117: [ MNT ] - MONAY TRUJILLO | B117: 2818.432 | C117: 20249.29 | D117: -37150.006 | E117: -4786.208 | F117: =SUM(D117,E117) -> -41936.214 | G117: =B117+C117+D117+E117 -> -18868.492 | H117: =IFERROR(C117/F117,0%) -> -0.48285928
A118: [ MOC ] - CANGURO MOVIL | B118: 73.85 | F118: =SUM(D118,E118) -> 0 | G118: =B118+C118+D118+E118 -> 73.85 | H118: =IFERROR(C118/F118,0%) -> 0
A119: [ MPC ] - MARKET PLACE CANGURO | B119: 14291.882 | C119: 35849.849 | D119: -56930.516 | E119: -8426.092 | F119: =SUM(D119,E119) -> -65356.608 | G119: =B119+C119+D119+E119 -> -15214.877 | H119: =IFERROR(C119/F119,0%) -> -0.54852677
A120: [ MRN ] - MORON | B120: 4788.696 | C120: 35267.78 | D120: -58628.651 | E120: -8499.623 | F120: =SUM(D120,E120) -> -67128.274 | G120: =B120+C120+D120+E120 -> -27071.798 | H120: =IFERROR(C120/F120,0%) -> -0.52537892
A121: [ MTC ] - MANTECAL | B121: 9717.43 | C121: 20534.973 | D121: -32773.269 | E121: -4748.037 | F121: =SUM(D121,E121) -> -37521.306 | G121: =B121+C121+D121+E121 -> -7268.903 | H121: =IFERROR(C121/F121,0%) -> -0.54728833
A122: [ MTP ] - METROPOLIS | B122: 5898.692 | C122: 28387.059 | D122: -55327.263 | E122: -6758.575 | F122: =SUM(D122,E122) -> -62085.838 | G122: =B122+C122+D122+E122 -> -27800.087 | H122: =IFERROR(C122/F122,0%) -> -0.45722277
A123: [ MUN ] - MATURIN SHOP | B123: 10327.111 | C123: 59392.158 | D123: -113243.08 | E123: -16130.412 | F123: =SUM(D123,E123) -> -129373.49 | G123: =B123+C123+D123+E123 -> -59654.221 | H123: =IFERROR(C123/F123,0%) -> -0.45907518
A124: [ MVT - BVT ] MOVISTAR BELLA VISTA | B124: 646.374 | C124: 1886.187 | D124: -2670.879 | E124: -329.131 | F124: =SUM(D124,E124) -> -3000.01 | G124: =B124+C124+D124+E124 -> -467.449 | H124: =IFERROR(C124/F124,0%) -> -0.6287269
A125: [ MVT - CCT ] - MOVISTAR CIUDAD TAMANACO | B125: 1089.902 | C125: 6852.378 | D125: -9370.888 | E125: -1226.382 | F125: =SUM(D125,E125) -> -10597.27 | G125: =B125+C125+D125+E125 -> -2654.99 | H125: =IFERROR(C125/F125,0%) -> -0.64661729
A126: [ MVT - GRZ ] - MOVISTAR LAS GARZAS | B126: 601.95 | C126: 2019.323 | D126: -3115.56 | E126: -256.975 | F126: =SUM(D126,E126) -> -3372.535 | G126: =B126+C126+D126+E126 -> -751.262 | H126: =IFERROR(C126/F126,0%) -> -0.59875524
A127: [ MVT - LNS ] MOVISTAR LOS LEONES | B127: 467.574 | C127: 2459.648 | D127: -3966.584 | E127: -588.866 | F127: =SUM(D127,E127) -> -4555.45 | G127: =B127+C127+D127+E127 -> -1628.228 | H127: =IFERROR(C127/F127,0%) -> -0.53993524
A128: [ MVT - LVÑ ] MOVISTAR LA VIÑA | B128: 771.758 | C128: 1775.674 | D128: -2389.655 | E128: -328.414 | F128: =SUM(D128,E128) -> -2718.069 | G128: =B128+C128+D128+E128 -> -170.637 | H128: =IFERROR(C128/F128,0%) -> -0.65328511
A129: [ MVT - PCC ] - MOVISTAR PARQUE CENTRAL CANAIMA | B129: 872.455 | C129: 50.455 | F129: =SUM(D129,E129) -> 0 | G129: =B129+C129+D129+E129 -> 922.91 | H129: =IFERROR(C129/F129,0%) -> 0
A130: [ MVT - SCB ] MOVISTAR SAN CRISTÓBAL | B130: 874.746 | C130: 498.013 | D130: -1075.05 | E130: -169.255 | F130: =SUM(D130,E130) -> -1244.305 | G130: =B130+C130+D130+E130 -> 128.454 | H130: =IFERROR(C130/F130,0%) -> -0.40023387
A131: [ MVT- LDC ] MOVISTAR LAS DELICIAS | B131: 336.59 | C131: 1227.4 | D131: -1815.585 | E131: -289.283 | F131: =SUM(D131,E131) -> -2104.868 | G131: =B131+C131+D131+E131 -> -540.878 | H131: =IFERROR(C131/F131,0%) -> -0.58312445
A132: [ NGA ] - NIRGUA | B132: 2685.394 | C132: 23651.61 | D132: -44351.744 | E132: -6361.032 | F132: =SUM(D132,E132) -> -50712.776 | G132: =B132+C132+D132+E132 -> -24375.772 | H132: =IFERROR(C132/F132,0%) -> -0.46638366
A133: [ NGT ] - NAIGUATA | B133: 4863.25 | C133: 18326.455 | D133: -30863.508 | E133: -4521.75 | F133: =SUM(D133,E133) -> -35385.258 | G133: =B133+C133+D133+E133 -> -12195.553 | H133: =IFERROR(C133/F133,0%) -> -0.51791215
A134: [ OCT ] - OCUMARE DEL TUY | B134: 17585.642 | C134: 83107.283 | D134: -138174.9 | E134: -17017.458 | F134: =SUM(D134,E134) -> -155192.36 | G134: =B134+C134+D134+E134 -> -54499.437 | H134: =IFERROR(C134/F134,0%) -> -0.53551143
A135: [ ODA ] - CIUDAD OJEDA | B135: 7948.103 | C135: 52878.371 | D135: -90898.309 | E135: -12556.456 | F135: =SUM(D135,E135) -> -103454.76 | G135: =B135+C135+D135+E135 -> -42628.291 | H135: =IFERROR(C135/F135,0%) -> -0.51112552
A136: [ OPO ] - OSPINO | B136: 6348.238 | C136: 21217.678 | D136: -35316.123 | E136: -4976.576 | F136: =SUM(D136,E136) -> -40292.699 | G136: =B136+C136+D136+E136 -> -12726.783 | H136: =IFERROR(C136/F136,0%) -> -0.52658865
A137: [ ORK ] - ORINOKIA | B137: 6088.646 | C137: 27039.458 | D137: -54368.21 | E137: -7712.982 | F137: =SUM(D137,E137) -> -62081.192 | G137: =B137+C137+D137+E137 -> -28953.088 | H137: =IFERROR(C137/F137,0%) -> -0.43554992
A138: [ PDB ] - PEDRAZA | B138: 4762.469 | C138: 13146.992 | D138: -21987.076 | E138: -3270.712 | F138: =SUM(D138,E138) -> -25257.788 | G138: =B138+C138+D138+E138 -> -7348.327 | H138: =IFERROR(C138/F138,0%) -> -0.52051241
A139: [ PDM ] - PUNTA DE MATA | B139: 5872.642 | C139: 46064.281 | D139: -88462.964 | E139: -12684.888 | F139: =SUM(D139,E139) -> -101147.85 | G139: =B139+C139+D139+E139 -> -49210.929 | H139: =IFERROR(C139/F139,0%) -> -0.45541532
A140: [ PDV - GUO ] - PDVSA GUARAGUO | C140: 183.981 | F140: =SUM(D140,E140) -> 0 | G140: =B140+C140+D140+E140 -> 183.981 | H140: =IFERROR(C140/F140,0%) -> 0
A141: [ PDV - LGN ] - PDVSA LAGUNA | C141: -14.719 | F141: =SUM(D141,E141) -> 0 | G141: =B141+C141+D141+E141 -> -14.719 | H141: =IFERROR(C141/F141,0%) -> 0
A142: [ PDV - MUN ] - PDVSA MATURIN | C142: -5.054 | F142: =SUM(D142,E142) -> 0 | G142: =B142+C142+D142+E142 -> -5.054 | H142: =IFERROR(C142/F142,0%) -> 0
A143: [ PDV - PCD ] - PDVSA PETROCEDEÑO | B143: 117.86 | C143: -53.367 | F143: =SUM(D143,E143) -> 0 | G143: =B143+C143+D143+E143 -> 64.493 | H143: =IFERROR(C143/F143,0%) -> 0
A144: [ PDV - PT ] - PDVSA PETROPIAR | C144: -9.718 | F144: =SUM(D144,E144) -> 0 | G144: =B144+C144+D144+E144 -> -9.718 | H144: =IFERROR(C144/F144,0%) -> 0
A145: [ PDV - STM ] - PDVSA SANTOME | B145: 1.367 | C145: 50.291 | F145: =SUM(D145,E145) -> 0 | G145: =B145+C145+D145+E145 -> 51.658 | H145: =IFERROR(C145/F145,0%) -> 0
A146: [ PFO ] - PUNTO FIJO | B146: 8033.46 | C146: 47496.539 | D146: -82985 | E146: -0.01 | F146: =SUM(D146,E146) -> -82985.01 | G146: =B146+C146+D146+E146 -> -27455.011 | H146: =IFERROR(C146/F146,0%) -> -0.57235083
A147: [ PLN ] - PALO NEGRO | B147: 7653.496 | C147: 22307.845 | D147: -42764.674 | E147: -6243.207 | F147: =SUM(D147,E147) -> -49007.881 | G147: =B147+C147+D147+E147 -> -19046.54 | H147: =IFERROR(C147/F147,0%) -> -0.45518893
A148: [ PLS ] - PUERTO LA CRUZ SHOP | B148: 11613.352 | C148: 43266.658 | D148: -82245.286 | E148: -10612 | F148: =SUM(D148,E148) -> -92857.286 | G148: =B148+C148+D148+E148 -> -37977.276 | H148: =IFERROR(C148/F148,0%) -> -0.46594791
A149: [ PML ] - PLAZA MAYOR LECHERIA | B149: 3551.383 | C149: 15009.564 | D149: -32742.743 | E149: -4367.225 | F149: =SUM(D149,E149) -> -37109.968 | G149: =B149+C149+D149+E149 -> -18549.021 | H149: =IFERROR(C149/F149,0%) -> -0.40446179
A150: [ PPT ] - PROPATRIA | B150: 7815.801 | C150: 25118.36 | D150: -47335.763 | E150: -7158.575 | F150: =SUM(D150,E150) -> -54494.338 | G150: =B150+C150+D150+E150 -> -21560.177 | H150: =IFERROR(C150/F150,0%) -> -0.46093523
A151: [ PRG ] - PARIAGUAN | B151: 5709.48 | C151: 26872.553 | D151: -51791.161 | E151: -7339.364 | F151: =SUM(D151,E151) -> -59130.525 | G151: =B151+C151+D151+E151 -> -26548.492 | H151: =IFERROR(C151/F151,0%) -> -0.4544616
A152: [ PRT ] - PUERTO PIRITU | B152: 5439.069 | C152: 32499.891 | D152: -58310.27 | E152: -7932.323 | F152: =SUM(D152,E152) -> -66242.593 | G152: =B152+C152+D152+E152 -> -28303.633 | H152: =IFERROR(C152/F152,0%) -> -0.49061925
A153: [ PSA ] - ACARIGUA | B153: 16220.757 | C153: 56094.025 | D153: -98945.329 | E153: -13857.919 | F153: =SUM(D153,E153) -> -112803.25 | G153: =B153+C153+D153+E153 -> -40488.466 | H153: =IFERROR(C153/F153,0%) -> -0.49727314
A154: [ PTA ] - PUERTO AYACUCHO | B154: 10647.372 | C154: 29966.566 | D154: -47496.041 | E154: -7123.312 | F154: =SUM(D154,E154) -> -54619.353 | G154: =B154+C154+D154+E154 -> -14005.415 | H154: =IFERROR(C154/F154,0%) -> -0.54864374
A155: [ PTC ] - PUERTO CABELLO | B155: 11155.528 | C155: 67358.516 | D155: -112026.09 | E155: -16810.176 | F155: =SUM(D155,E155) -> -128836.27 | G155: =B155+C155+D155+E155 -> -50322.222 | H155: =IFERROR(C155/F155,0%) -> -0.52282263
A156: [ PTT ] - PETARE 3 | B156: 14047.84 | C156: 65579.53 | D156: -114279.83 | E156: -17056.651 | F156: =SUM(D156,E156) -> -131336.48 | G156: =B156+C156+D156+E156 -> -51709.115 | H156: =IFERROR(C156/F156,0%) -> -0.49932454
A157: [ PTU ] - PETARE 1 | B157: 10405.618 | C157: 65753.803 | D157: -111386.16 | E157: -16774.365 | F157: =SUM(D157,E157) -> -128160.53 | G157: =B157+C157+D157+E157 -> -52001.107 | H157: =IFERROR(C157/F157,0%) -> -0.51305815
... A163: [ SAM - LAR ] - SAMBIL LARA | B163: 8244.951 | C163: 34403.312 | D163: -73056.932 | E163: -9862.617 | F163: =SUM(D163,E163) -> -82919.549 | G163: =B163+C163+D163+E163 -> -40271.286 | H163: =IFERROR(C163/F163,0%) -> -0.41489989
A164: [ SAM - MGT ] - SAMBIL MARGARITA | B164: 5275.453 | C164: 17832.716 | D164: -38981.989 | F164: =SUM(D164,E164) -> -38981.989 | G164: =B164+C164+D164+E164 -> -15873.82 | H164: =IFERROR(C164/F164,0%) -> -0.45746039
A165: [ SAM - PFO ] - SAMBIL PUNTO FIJO | B165: 4035.639 | C165: 24777.493 | D165: -47557.72 | E165: -0.02 | F165: =SUM(D165,E165) -> -47557.74 | G165: =B165+C165+D165+E165 -> -18744.608 | H165: =IFERROR(C165/F165,0%) -> -0.52099812
A166: [ SAM - VLC ] - SAMBIL VALENCIA | B166: 4939.129 | C166: 16655.7 | D166: -30851.017 | E166: -4397.012 | F166: =SUM(D166,E166) -> -35248.029 | G166: =B166+C166+D166+E166 -> -13653.2 | H166: =IFERROR(C166/F166,0%) -> -0.47252855
...

Sheet RSM JULIO
A1: Centro de Costo | B1: Amortizacion | C1: % | D1: Arrendamiento | E1: % | F1: Fletes y Transporte | G1: % | H1: Gastos IT | I1: % | J1: Gastos de Personal | K1: % | L1: Gastos Financieros | M1: % | N1: Honorarios Profesionales | O1: % | P1: Impuestos, Tasas y Contribuciones | Q1: % | R1: Materiales, Mantenimiento y Reparaciones | S1: % | T1: Marketing y Promocion | U1: % | V1: Seguros | W1: % | X1: Servicios | Y1: % | Z1: Varios | AA1: % | AB1: Total Gastos | AC1: % | AD1: Total Costos | AE1: % | AF1: Ingresos | AG1: Otros Ingresos | AH1: Total Ingresos | AI1: Ingreso Bruto | AJ1: % impacto sobre ingresos generales | AK1: Gasto Aplicado por Venta | AL1: Monto Ingresos Bs | AM1: Factor de ingresos en bs | AN1: Gasto Aplicado Factor Ingreso Bs | AO1: Gasto aplicado | AP1: % | AQ1: Total General CC | AR1: Resultado - Gastos Distribuidos | AS1: % resultado en base a ingresos | BE1: NOTAS
A2: [ ABM ] - AV BOLIVAR DE MATURIN | B2: 0 | C2: 0 | D2: 0 | E2: 0 | F2: 0 | G2: 0 | H2: 0 | I2: 0 | J2: 0 | K2: 0 | M2: 0 | O2: 0 | Q2: 0 | R2: 391.179 | S2: 0 | U2: 0 | W2: 0 | Y2: 0 | AA2: 0 | AB2: 391.179 | AC2: 0 | AE2: 0 | AF2: 0 | AG2: 0 | AH2: =SUM(AF2,AG2) -> 0 | AI2: =((AF2+AG2)*-1) -> 0 | AJ2: =AI2/($AI$224) -> 0 | AK2: =AJ2*($G$260+$G$313-$B$406) -> 0 | AL2: 0 | AM2: =AL2/AL$224 -> 0 | AN2: =(AM2*$B$406) -> 0 | AO2: =AN2+AK2 -> 0 | AP2: 0 | AQ2: =AB2+AD2+AH2 -> 391.179 | AR2: =AQ2+AO2 -> 391.179 | AS2: 0 | AU2: RESULTADOS ANTES DE DISTRIBUCION JULIO 2026 | BA2: RESULTADOS DESPUES DE DISTRIBUCION JULIO 2026 | BE2: 1- Porcentaje impacto sobre ingresos generales: Analisis vertical de los ingresos por tienda contra el monto total de ingresos
A3: [ ACB ] - AV LIBERTADOR CIUDAD BOLIVAR | B3: 0 | C3: =$B3/$AI3 -> 0 | D3: 1200 | E3: =$D3/$AI3 -> 0.024433315 | F3: 0 | G3: =$F3/$AI3 -> 0 | H3: 0 | I3: =$H3/$AI3 -> 0 | J3: 3343.958 | K3: =$J3/$AI3 -> 0.068086649 | M3: =$L3/$AI3 -> 0 | O3: =$N3/$AI3 -> 0 | P3: 171.01 | Q3: =$P3/$AI3 -> 0.003481951 | R3: 4800.132 | S3: =$R3/$AI3 -> 0.097735948 | U3: =$T3/$AI3 -> 0 | W3: =$V3/$AI3 -> 0 | X3: 174.2 | Y3: =$X3/$AI3 -> 0.0035469029 | Z3: 176.579 | AA3: =$Z3/$AI3 -> 0.003595342 | AB3: 9865.879 | AC3: =$AB3/AI3 -> 0.20088011 | AD3: 22717.278 | AE3: =$AD3/$AI3 -> 0.46254868 | AF3: -42850.541 | AG3: -6262.729 | AH3: =SUM(AF3,AG3) -> -49113.27 | AI3: =((AF3+AG3)*-1) -> 49113.27 | AJ3: =AI3/($AI$224) -> 0.0037479444 | AK3: =AJ3*($G$260+$G$313-$B$406) -> 6620.085 | AL3: 15353.841 | AM3: =AL3/AL$224 -> 0.0032585803 | AN3: =(AM3*$B$406) -> 4430.3168 | AO3: =AN3+AK3 -> 11050.402 | AP3: =$AO3/$AI3 -> 0.22499829 | AQ3: =AB3+AD3+AH3 -> -16530.113 | AR3: =AQ3+AO3 -> -5479.7111 | AS3: =AR3/AI3 -> -0.11157292 | AU3: Perdida | AV3: 17 tiendas | AW3: 57718.74 | BA3: Perdida | BB3: 30 tiendas | BC3: 101304.26
A4: [ ACG ] - ACHAGUAS | B4: 0 | C4: =$B4/$AI4 -> 0 | D4: 940 | E4: =$D4/$AI4 -> 0.016508077 | F4: 0 | G4: =$F4/$AI4 -> 0 | H4: 0 | I4: =$H4/$AI4 -> 0 | J4: 2821.057 | K4: =$J4/$AI4 -> 0.049542795 | M4: =$L4/$AI4 -> 0 | O4: =$N4/$AI4 -> 0 | P4: 62.92 | Q4: =$P4/$AI4 -> 0.0011049875 | R4: 502.625 | S4: =$R4/$AI4 -> 0.0088269919 | U4: =$T4/$AI4 -> 0 | W4: =$V4/$AI4 -> 0 | X4: 287.09 | Y4: =$X4/$AI4 -> 0.0050418127 | Z4: 99.996 | AA4: =$Z4/$AI4 -> 0.0017561082 | AB4: 4713.688 | AC4: =$AB4/AI4 -> 0.082780772 | AD4: 29078.434 | AE4: =$AD4/$AI4 -> 0.51066919 | AF4: -49631.89 | AG4: -7309.932 | AH4: =SUM(AF4,AG4) -> -56941.822 | AI4: =((AF4+AG4)*-1) -> 56941.822 | AJ4: =AI4/($AI$224) -> 0.0043453588 | AK4: =AJ4*($G$260+$G$313-$B$406) -> 7675.3127 | AL4: 22324.722 | AM4: =AL4/AL$224 -> 0.0047380258 | AN4: =(AM4*$B$406) -> 6441.7488 | AO4: =AN4+AK4 -> 14117.061 | AP4: =$AO4/$AI4 -> 0.24792079 | AQ4: =AB4+AD4+AH4 -> -23149.7 | AR4: =AQ4+AO4 -> -9032.6385 | AS4: =AR4/AI4 -> -0.15862925 | AU4: Ganancias Hasta $10,000 | AV4: 35 tiendas | AW4: -141712.34 | BA4: Ganancias Hasta $10,000 | BB4: 103 tiendas | BC4: -515419.16 | BE4: 2- Gasto aplicado por venta: Se toman los ingresos costos y gastos mas los gastos del corporativo menos el diferencial de cambio
A5: [ ACO ] - ANACO | B5: 0 | C5: =$B5/$AI5 -> 0 | D5: 1700 | E5: =$D5/$AI5 -> 0.014298085 | F5: 0 | G5: =$F5/$AI5 -> 0 | H5: 0 | I5: =$H5/$AI5 -> 0 | J5: 5335.908 | K5: =$J5/$AI5 -> 0.044878391 | M5: =$L5/$AI5 -> 0 | O5: =$N5/$AI5 -> 0 | P5: 104.24 | Q5: =$P5/$AI5 -> 0.00087672492 | R5: 88.044 | S5: =$R5/$AI5 -> 0.00074050622 | U5: =$T5/$AI5 -> 0 | W5: =$V5/$AI5 -> 0 | X5: 123.32 | Y5: =$X5/$AI5 -> 0.0010371999 | Z5: 51.832 | AA5: =$Z5/$AI5 -> 0.00043594019 | AB5: 7403.344 | AC5: =$AB5/AI5 -> 0.062266847 | AD5: 60262.727 | AE5: =$AD5/$AI5 -> 0.50684799 | AF5: -104454 | AG5: -14443.039 | AH5: =SUM(AF5,AG5) -> -118897.04 | AI5: =((AF5+AG5)*-1) -> 118897.04 | AJ5: =AI5/($AI$224) -> 0.0090733015 | AK5: =AJ5*($G$260+$G$313-$B$406) -> 16026.392 | AL5: 42151.387 | AM5: =AL5/AL$224 -> 0.0089458836 | AN5: =(AM5*$B$406) -> 12162.689 | AO5: =AN5+AK5 -> 28189.081 | AP5: =$AO5/$AI5 -> 0.23708816 | AQ5: =AB5+AD5+AH5 -> -51230.972 | AR5: =AQ5+AO5 -> -23041.891 | AS5: =AR5/AI5 -> -0.193797 | AU5: Ganancia Mayor A $10,000 | AV5: 170 tiendas | AW5: -5025592 | BA5: Ganancia Mayor A $10,000 | BB5: 89 tiendas | BC5: -1569561.5
A6: [ ADO ] - ALTAGRACIA DEL ORITUCO | B6: 0 | C6: =$B6/$AI6 -> 0 | D6: 730 | E6: =$D6/$AI6 -> 0.0086751594 | F6: 0 | G6: =$F6/$AI6 -> 0 | H6: 0 | I6: =$H6/$AI6 -> 0 | J6: 4044.558 | K6: =$J6/$AI6 -> 0.048064637 | M6: =$L6/$AI6 -> 0 | O6: =$N6/$AI6 -> 0 | P6: 70.29 | Q6: =$P6/$AI6 -> 0.00083531089 | R6: 292.649 | S6: =$R6/$AI6 -> 0.0034777763 | T6: 1.89 | U6: =$T6/$AI6 -> 2.2460344e-05 | W6: =$V6/$AI6 -> 0 | X6: 281.86 | Y6: =$X6/$AI6 -> 0.0033495622 | Z6: -6.595 | AA6: =$Z6/$AI6 -> -7.8373529e-05 | AB6: 5414.652 | AC6: =$AB6/AI6 -> 0.064346533 | AD6: 41163.746 | AE6: =$AD6/$AI6 -> 0.4891809 | AF6: -73293.141 | AG6: -10855.169 | AH6: =SUM(AF6,AG6) -> -84148.31 | AI6: =((AF6+AG6)*-1) -> 84148.31 | AJ6: =AI6/($AI$224) -> 0.0064215473 | AK6: =AJ6*($G$260+$G$313-$B$406) -> 11342.535 | AL6: 32162.211 | AM6: =AL6/AL$224 -> 0.0068258583 | AN6: =(AM6*$B$406) -> 9280.3345 | AO6: =AN6+AK6 -> 20622.869 | AP6: =$AO6/$AI6 -> 0.24507764 | AQ6: =AB6+AD6+AH6 -> -37569.912 | AR6: =AQ6+AO6 -> -16947.043 | AS6: =AR6/AI6 -> -0.20139493 | AU6: TOTALES | AV6: 222 | AW6: =SUM(AW3:AW5) -> -5109585.6 | BA6: TOTALES | BB6: 222 | BC6: =SUM(BC3:BC5) -> -1983676.4 | BE6: 3- Monto ingresos en bs: Son todos los metodos de pago recibidos en VES (pago movil, biopago, efectivo bs , punto de venta, etc) este dado es suministrado por la Gerencia de Cuentas por Pagar
A7: [ ADS - BQT ] - AEDOS BARQUISIMETO | B7: 0 | C7: 0 | D7: 0 | E7: 0 | F7: 0 | G7: 0 | H7: 0 | I7: 0 | J7: 0 | K7: 0 | M7: 0 | O7: 0 | Q7: 0 | S7: 0 | U7: 0 | W7: 0 | Y7: 0 | Z7: -11.033 | AA7: 0 | AB7: -11.033 | AC7: 0 | AE7: 0 | AF7: 0 | AG7: 0 | AH7: =SUM(AF7,AG7) -> 0 | AI7: =((AF7+AG7)*-1) -> 0 | AJ7: =AI7/($AI$224) -> 0 | AK7: =AJ7*($G$260+$G$313-$B$406) -> 0 | AL7: 0 | AM7: =AL7/AL$224 -> 0 | AN7: =(AM7*$B$406) -> 0 | AO7: =AN7+AK7 -> 0 | AP7: 0 | AQ7: =AB7+AD7+AH7 -> -11.033 | AR7: =AQ7+AO7 -> -11.033 | AS7: 0
A8: [ ADS - TCY ] - AEDOS TOCUYITO | B8: 0 | C8: =$B8/$AI8 -> 0 | D8: 0 | E8: =$D8/$AI8 -> 0 | F8: 30 | G8: =$F8/$AI8 -> 0.0015520647 | H8: 0 | I8: =$H8/$AI8 -> 0 | J8: 924 | K8: =$J8/$AI8 -> 0.047803593 | M8: =$L8/$AI8 -> 0 | O8: =$N8/$AI8 -> 0 | P8: 433.46 | Q8: =$P8/$AI8 -> 0.022425266 | R8: 10854.95 | S8: =$R8/$AI8 -> 0.56158616 | T8: 90 | U8: =$T8/$AI8 -> 0.0046561941 | W8: =$V8/$AI8 -> 0 | X8: 89.1 | Y8: =$X8/$AI8 -> 0.0046096322 | Z8: 12700.181 | AA8: =$Z8/$AI8 -> 0.65705009 | AB8: 25121.691 | AC8: =$AB8/AI8 -> 1.299683 | AD8: 6022.502 | AE8: =$AD8/$AI8 -> 0.31157709 | AF8: -17002.863 | AG8: -2326.228 | AH8: =SUM(AF8,AG8) -> -19329.091 | AI8: =((AF8+AG8)*-1) -> 19329.091 | AJ8: =AI8/($AI$224) -> 0.0014750465 | AK8: =AJ8*($G$260+$G$313-$B$406) -> 2605.4104 | AL8: 14498.62 | AM8: =AL8/AL$224 -> 0.0030770746 | AN8: =(AM8*$B$406) -> 4183.5445 | AO8: =AN8+AK8 -> 6788.9549 | AP8: =$AO8/$AI8 -> 0.35122991 | AQ8: =AB8+AD8+AH8 -> 11815.102 | AR8: =AQ8+AO8 -> 18604.057 | AS8: =AR8/AI8 -> 0.96249001 | AU8: ARRENDAMIENTO | BE8: 4- Factor de Ingresos en bs: El impacto que tiene cada tienda sobre el total del ingreso en bolivares del Período
A9: [ ANT ] - ANTIMANO | B9: 0 | C9: =$B9/$AI9 -> 0 | D9: 1500 | E9: =$D9/$AI9 -> 0.13042388 | F9: 0 | G9: =$F9/$AI9 -> 0 | H9: 0 | I9: =$H9/$AI9 -> 0 | J9: 3892.129 | K9: =$J9/$AI9 -> 0.33841772 | M9: =$L9/$AI9 -> 0 | N9: 228.45 | O9: =$N9/$AI9 -> 0.019863557 | P9: 98.63 | Q9: =$P9/$AI9 -> 0.0085758051 | R9: 877.585 | S9: =$R9/$AI9 -> 0.076305363 | U9: =$T9/$AI9 -> 0 | W9: =$V9/$AI9 -> 0 | X9: 112.89 | Y9: =$X9/$AI9 -> 0.0098157015 | Z9: 13.17 | AA9: =$Z9/$AI9 -> 0.0011451217 | AB9: 6722.854 | AC9: =$AB9/AI9 -> 0.58454715 | AD9: 5543.328 | AE9: =$AD9/$AI9 -> 0.48198824 | AF9: -10027.621 | AG9: -1473.34 | AH9: =SUM(AF9,AG9) -> -11500.961 | AI9: =((AF9+AG9)*-1) -> 11500.961 | AJ9: =AI9/($AI$224) -> 0.00087766427 | AK9: =AJ9*($G$260+$G$313-$B$406) -> 1550.2397 | AL9: 4371.0637 | AM9: =AL9/AL$224 -> 0.00092768068 | AN9: =(AM9*$B$406) -> 1261.2607 | AO9: =AN9+AK9 -> 2811.5004 | AP9: =$AO9/$AI9 -> 0.24445787 | AQ9: =AB9+AD9+AH9 -> 765.221 | AR9: =AQ9+AO9 -> 3576.7214 | AS9: =AR9/AI9 -> 0.31099326 | AU9: Gastos superiores a $2000 | AV9: 30 tiendas | AW9: 87044.62
A10: [ APU ] - APURE | B10: 0 | C10: =$B10/$AI10 -> 0 | D10: 1420 | E10: =$D10/$AI10 -> 0.015176192 | F10: 0 | G10: =$F10/$AI10 -> 0 | H10: 47.2 | I10: =$H10/$AI10 -> 0.00050444806 | J10: 4245.454 | K10: =$J10/$AI10 -> 0.045373115 | M10: =$L10/$AI10 -> 0 | O10: =$N10/$AI10 -> 0 | P10: 119.18 | Q10: =$P10/$AI10 -> 0.0012737314 | R10: 732.844 | S10: =$R10/$AI10 -> 0.0078322402 | U10: =$T10/$AI10 -> 0 | W10: =$V10/$AI10 -> 0 | X10: 229.98 | Y10: =$X10/$AI10 -> 0.0024579018 | Z10: 461.543 | AA10: =$Z10/$AI10 -> 0.0049327219 | AB10: 7256.201 | AC10: =$AB10/AI10 -> 0.07755035 | AD10: 49343.272 | AE10: =$AD10/$AI10 -> 0.52735419 | AF10: -81546.616 | AG10: -12020.995 | AH10: =SUM(AF10,AG10) -> -93567.611 | AI10: =((AF10+AG10)*-1) -> 93567.611 | AJ10: =AI10/($AI$224) -> 0.0071403554 | AK10: =AJ10*($G$260+$G$313-$B$406) -> 12612.183 | AL10: 35382.82 | AM10: =AL10/AL$224 -> 0.0075093754 | AN10: =(AM10*$B$406) -> 10209.634 | AO10: =AN10+AK10 -> 22821.817 | AP10: =$AO10/$AI10 -> 0.24390723 | AQ10: =AB10+AD10+AH10 -> -36968.138 | AR10: =AQ10+AO10 -> -14146.321 | AS10: =AR10/AI10 -> -0.15118822 | AU10: Gastos entre $1001 hasta $2000 | AV10: 69 tiendas | AW10: 102791.81 | BE10: 5- Gasto aplicado a diferencial de cambio: El gasto del diferencial de cambio (perdida por diferencia en cambio) que se aplica sobre el factor de ingresos en bolivares de cada tienda
A11: [ ARO - INT ] - AEROPUERTO INTERNACIONAL | B11: 0 | C11: 0 | D11: 215 | E11: 0 | F11: 0 | G11: 0 | H11: 0 | I11: 0 | J11: 1488.504 | K11: 0 | M11: 0 | O11: 0 | Q11: 0 | S11: 0 | U11: 0 | W11: 0 | X11: 100.23 | Y11: 0 | Z11: 3.35 | AA11: 0 | AB11: 1807.084 | AC11: 0 | AD11: -181.214 | AE11: 0 | AF11: 0 | AG11: 0 | AH11: =SUM(AF11,AG11) -> 0 | AI11: =((AF11+AG11)*-1) -> 0 | AJ11: =AI11/($AI$224) -> 0 | AK11: =AJ11*($G$260+$G$313-$B$406) -> 0 | AL11: 0 | AM11: =AL11/AL$224 -> 0 | AN11: =(AM11*$B$406) -> 0 | AO11: =AN11+AK11 -> 0 | AP11: 0 | AQ11: =AB11+AD11+AH11 -> 1625.87 | AR11: =AQ11+AO11 -> 1625.87 | AS11: 0 | AU11: Gastos entre $0 hasta $1000 | AV11: 123 tiendas | AW11: 52989.12
A12: [ ARO - NAC ] - AEROPUERTO NACIONAL | B12: 0 | C12: 0 | D12: 215 | E12: 0 | F12: 0 | G12: 0 | H12: 0 | I12: 0 | J12: 1477.455 | K12: 0 | M12: 0 | O12: 0 | Q12: 0 | R12: 258.207 | S12: 0 | U12: 0 | W12: 0 | X12: 85.23 | Y12: 0 | Z12: 138.372 | AA12: 0 | AB12: 2174.264 | AC12: 0 | AD12: 7697.841 | AE12: 0 | AF12: 0 | AG12: 0 | AH12: =SUM(AF12,AG12) -> 0 | AI12: =((AF12+AG12)*-1) -> 0 | AJ12: =AI12/($AI$224) -> 0 | AK12: =AJ12*($G$260+$G$313-$B$406) -> 0 | AL12: 0 | AM12: =AL12/AL$224 -> 0 | AN12: =(AM12*$B$406) -> 0 | AO12: =AN12+AK12 -> 0 | AP12: 0 | AQ12: =AB12+AD12+AH12 -> 9872.105 | AR12: =AQ12+AO12 -> 9872.105 | AS12: 0 | AU12: TOTALES | AV12: 222 | AW12: =SUM(AW9:AW11) -> 242825.55 | BE12: 6- Gasto Aplicado : Es el gasto aplicado por venta + el gasto aplicado a diferencia de cambio
A13: [ ARY ] - AROA YARACUY | B13: 0 | C13: 0 | D13: 0 | E13: 0 | F13: 0 | G13: 0 | H13: 0 | I13: 0 | J13: 0 | K13: 0 | M13: 0 | O13: 0 | Q13: 0 | R13: 9.74 | S13: 0 | U13: 0 | W13: 0 | Y13: 0 | Z13: 6.88 | AA13: 0 | AB13: 16.62 | AC13: 0 | AD13: -32.068 | AE13: 0 | AF13: 0 | AG13: 0 | AH13: =SUM(AF13,AG13) -> 0 | AI13: =((AF13+AG13)*-1) -> 0 | AJ13: =AI13/($AI$224) -> 0 | AK13: =AJ13*($G$260+$G$313-$B$406) -> 0 | AL13: 0 | AM13: =AL13/AL$224 -> 0 | AN13: =(AM13*$B$406) -> 0 | AO13: =AN13+AK13 -> 0 | AP13: 0 | AQ13: =AB13+AD13+AH13 -> -15.448 | AR13: =AQ13+AO13 -> -15.448 | AS13: 0
A14: [ ATV ] - ALTA VISTA | B14: -3100 | C14: =$B14/$AI14 -> -0.077263184 | D14: 1100 | E14: =$D14/$AI14 -> 0.027415969 | F14: 0 | G14: =$F14/$AI14 -> 0 | H14: 0 | I14: =$H14/$AI14 -> 0 | J14: 2174.073 | K14: =$J14/$AI14 -> 0.054185743 | M14: =$L14/$AI14 -> 0 | O14: =$N14/$AI14 -> 0 | Q14: =$P14/$AI14 -> 0 | R14: 54.171 | S14: =$R14/$AI14 -> 0.0013501368 | U14: =$T14/$AI14 -> 0 | W14: =$V14/$AI14 -> 0 | X14: 40.7 | Y14: =$X14/$AI14 -> 0.0010143908 | Z14: 41.244 | AA14: =$Z14/$AI14 -> 0.0010279493 | AB14: 310.188 | AC14: =$AB14/AI14 -> 0.0077310041 | AD14: 18339.91 | AE14: =$AD14/$AI14 -> 0.45709673 | AF14: -35063.775 | AG14: -5058.827 | AH14: =SUM(AF14,AG14) -> -40122.602 | AI14: =((AF14+AG14)*-1) -> 40122.602 | AJ14: =AI14/($AI$224) -> 0.0030618462 | AK14: =AJ14*($G$260+$G$313-$B$406) -> 5408.2132 | AL14: 13621.013 | AM14: =AL14/AL$224 -> 0.0028908181 | AN14: =(AM14*$B$406) -> 3930.3129 | AO14: =AN14+AK14 -> 9338.5261 | AP14: =$AO14/$AI14 -> 0.23274976 | AQ14: =AB14+AD14+AH14 -> -21472.504 | AR14: =AQ14+AO14 -> -12133.978 | AS14: =AR14/AI14 -> -0.30242251 | AU14: GASTOS DE PERSONAL | BE14: 7- Resultado de la tienda ( total general + gasto aplicado)
A15: [ AVM ] - AVENIDA MARIÑO | B15: 0 | C15: =$B15/$AI15 -> 0 | D15: 800 | E15: =$D15/$AI15 -> 0.018073194 | F15: 20 | G15: =$F15/$AI15 -> 0.00045182985 | H15: 0 | I15: =$H15/$AI15 -> 0 | J15: 2448.821 | K15: =$J15/$AI15 -> 0.055322522 | M15: =$L15/$AI15 -> 0 | N15: 10.06 | O15: =$N15/$AI15 -> 0.00022727042 | P15: 111.93 | Q15: =$P15/$AI15 -> 0.0025286658 | R15: 444.205 | S15: =$R15/$AI15 -> 0.010035254 | U15: =$T15/$AI15 -> 0 | W15: =$V15/$AI15 -> 0 | X15: 185.98 | Y15: =$X15/$AI15 -> 0.0042015658 | Z15: 44.692 | AA15: =$Z15/$AI15 -> 0.001009659 | AB15: 4065.688 | AC15: =$AB15/AI15 -> 0.091849961 | AD15: 24877.791 | AE15: =$AD15/$AI15 -> 0.56202643 | AF15: -44264.45 | AG15: 0 | AH15: =SUM(AF15,AG15) -> -44264.45 | AI15: =((AF15+AG15)*-1) -> 44264.45 | AJ15: =AI15/($AI$224) -> 0.00337792 | AK15: =AJ15*($G$260+$G$313-$B$406) -> 5966.502 | AL15: 14473.401 | AM15: =AL15/AL$224 -> 0.0030717225 | AN15: =(AM15*$B$406) -> 4176.2678 | AO15: =AN15+AK15 -> 10142.77 | AP15: =$AO15/$AI15 -> 0.22914031 | AQ15: =AB15+AD15+AH15 -> -15320.971 | AR15: =AQ15+AO15 -> -5178.2012 | AS15: =AR15/AI15 -> -0.1169833 | AU15: Gastos superiores a $6000 | AV15: 25 tiendas | AW15: 199615.04
A16: [ BAC ] - BUENOS AIRES CANGURO | B16: 0 | C16: =$B16/$AI16 -> 0 | D16: 1100 | E16: =$D16/$AI16 -> 0.024345378 | F16: 22.5 | G16: =$F16/$AI16 -> 0.00049797365 | H16: 47.2 | I16: =$H16/$AI16 -> 0.001044638 | J16: 3563.221 | K16: =$J16/$AI16 -> 0.078861785 | M16: =$L16/$AI16 -> 0 | O16: =$N16/$AI16 -> 0 | P16: 165.95 | Q16: =$P16/$AI16 -> 0.0036728323 | R16: 117.381 | S16: =$R16/$AI16 -> 0.0025978953 | U16: =$T16/$AI16 -> 0 | W16: =$V16/$AI16 -> 0 | X16: 310.72 | Y16: =$X16/$AI16 -> 0.0068769054 | Z16: 32.403 | AA16: =$Z16/$AI16 -> 0.00071714845 | AB16: 5359.375 | AC16: =$AB16/AI16 -> 0.11861456 | AD16: 22589.678 | AE16: =$AD16/$AI16 -> 0.49995841 | AF16: -39774.96 | AG16: -5408.154 | AH16: =SUM(AF16,AG16) -> -45183.114 | AI16: =((AF16+AG16)*-1) -> 45183.114 | AJ16: =AI16/($AI$224) -> 0.0034480253 | AK16: =AJ16*($G$260+$G$313-$B$406) -> 6090.3307 | AL16: 15150.12 | AM16: =AL16/AL$224 -> 0.0032153439 | AN16: =(AM16*$B$406) -> 4371.5333 | AO16: =AN16+AK16 -> 10461.864 | AP16: =$AO16/$AI16 -> 0.23154367 | AQ16: =AB16+AD16+AH16 -> -17234.061 | AR16: =AQ16+AO16 -> -6772.1969 | AS16: =AR16/AI16 -> -0.14988336 | AU16: Gastos entre $3001 hasta $6000 | AV16: 114 tiendas | AW16: 468218.01 | BE16: OBSERVACION
A17: [ BCC ] - BISCUCUY | B17: 0 | C17: =$B17/$AI17 -> 0 | D17: 600 | E17: =$D17/$AI17 -> 0.018180168 | F17: 0 | G17: =$F17/$AI17 -> 0 | H17: 0 | I17: =$H17/$AI17 -> 0 | J17: 2727.408 | K17: =$J17/$AI17 -> 0.082641227 | M17: =$L17/$AI17 -> 0 | O17: =$N17/$AI17 -> 0 | Q17: =$P17/$AI17 -> 0 | R17: 4273.529 | S17: =$R17/$AI17 -> 0.12948913 | U17: =$T17/$AI17 -> 0 | W17: =$V17/$AI17 -> 0 | X17: 29.47 | Y17: =$X17/$AI17 -> 0.00089294926 | Z17: 634.186 | AA17: =$Z17/$AI17 -> 0.019216014 | AB17: 8264.593 | AC17: =$AB17/AI17 -> 0.25041948 | AD17: 17173.338 | AE17: =$AD17/$AI17 -> 0.52035696 | AF17: -28714.826 | AG17: -4288.169 | AH17: =SUM(AF17,AG17) -> -33002.995 | AI17: =((AF17+AG17)*-1) -> 33002.995 | AJ17: =AI17/($AI$224) -> 0.002518533 | AK17: =AJ17*($G$260+$G$313-$B$406) -> 4448.5458 | AL17: 12384.42 | AM17: =AL17/AL$224 -> 0.0026283732 | AN17: =(AM17*$B$406) -> 3573.4968 | AO17: =AN17+AK17 -> 8022.0427 | AP17: =$AO17/$AI17 -> 0.24307014 | AQ17: =AB17+AD17+AH17 -> -7565.064 | AR17: =AQ17+AO17 -> 456.97867 | AS17: =AR17/AI17 -> 0.013846582 | AU17: Gastos entre $0 hasta $3000 | AV17: 83 tiendas | AW17: 135782.46 | BE17: Los ingresos, costos y gastos del cendis se distribuyen al igual que los gastos del corporativo entre las tiendas en funcion de la venta.
A18: [ BCD ] - BARINAS CC DORADO | B18: 0 | C18: =$B18/$AI18 -> 0 | D18: 350 | E18: =$D18/$AI18 -> 0.010770657 | F18: 0 | G18: =$F18/$AI18 -> 0 | H18: 0 | I18: =$H18/$AI18 -> 0 | J18: 2436.293 | K18: =$J18/$AI18 -> 0.074972788 | M18: =$L18/$AI18 -> 0 | O18: =$N18/$AI18 -> 0 | P18: 57.82 | Q18: =$P18/$AI18 -> 0.0017793125 | R18: 240.771 | S18: =$R18/$AI18 -> 0.0074093195 | U18: =$T18/$AI18 -> 0 | W18: =$V18/$AI18 -> 0 | X18: 345.33 | Y18: =$X18/$AI18 -> 0.010626945 | Z18: 131.115 | AA18: =$Z18/$AI18 -> 0.0040348419 | AB18: 3561.329 | AC18: =$AB18/AI18 -> 0.10959386 | AD18: 16467.36 | AE18: =$AD18/$AI18 -> 0.50675509 | AF18: -28423.281 | AG18: -4072.416 | AH18: =SUM(AF18,AG18) -> -32495.697 | AI18: =((AF18+AG18)*-1) -> 32495.697 | AJ18: =AI18/($AI$224) -> 0.0024798199 | AK18: =AJ18*($G$260+$G$313-$B$406) -> 4380.166 | AL18: 11290.267 | AM18: =AL18/AL$224 -> 0.0023961588 | AN18: =(AM18*$B$406) -> 3257.7815 | AO18: =AN18+AK18 -> 7637.9476 | AP18: =$AO18/$AI18 -> 0.23504489 | AQ18: =AB18+AD18+AH18 -> -12467.008 | AR18: =AQ18+AO18 -> -4829.0604 | AS18: =AR18/AI18 -> -0.14860615 | AU18: TOTALES | AV18: 222 | AW18: =SUM(AW15:AW17) -> 803615.51
A19: [ BCN ] - BARCELONA | B19: 0 | C19: =$B19/$AI19 -> 0 | D19: 2508.33 | E19: =$D19/$AI19 -> 0.03159095 | F19: 0 | G19: =$F19/$AI19 -> 0 | H19: 0 | I19: =$H19/$AI19 -> 0 | J19: 4308.157 | K19: =$J19/$AI19 -> 0.054258718 | M19: =$L19/$AI19 -> 0 | O19: =$N19/$AI19 -> 0 | P19: 357.02 | Q19: =$P19/$AI19 -> 0.0044964581 | R19: 11.99 | S19: =$R19/$AI19 -> 0.00015100704 | U19: =$T19/$AI19 -> 0 | W19: =$V19/$AI19 -> 0 | X19: 109.29 | Y19: =$X19/$AI19 -> 0.0013764436 | Z19: 35.715 | AA19: =$Z19/$AI19 -> 0.00044980954 | AB19: 7330.502 | AC19: =$AB19/AI19 -> 0.092323386 | AD19: 38567.289 | AE19: =$AD19/$AI19 -> 0.48573245 | AF19: -69454.678 | AG19: -9945.594 | AH19: =SUM(AF19,AG19) -> -79400.272 | AI19: =((AF19+AG19)*-1) -> 79400.272 | AJ19: =AI19/($AI$224) -> 0.0060592138 | AK19: =AJ19*($G$260+$G$313-$B$406) -> 10702.536 | AL19: 29744.153 | AM19: =AL19/AL$224 -> 0.0063126685 | AN19: =(AM19*$B$406) -> 8582.6093 | AO19: =AN19+AK19 -> 19285.146 | AP19: =$AO19/$AI19 -> 0.24288513 | AQ19: =AB19+AD19+AH19 -> -33502.481 | AR19: =AQ19+AO19 -> -14217.335 | AS19: =AR19/AI19 -> -0.17905903
A20: [ BCO ] - BOCONO | B20: 0 | C20: =$B20/$AI20 -> 0 | D20: 1030 | E20: =$D20/$AI20 -> 0.021256953 | F20: 66.98 | G20: =$F20/$AI20 -> 0.0013823211 | H20: 0 | I20: =$H20/$AI20 -> 0 | J20: 3584.88 | K20: =$J20/$AI20 -> 0.073984104 | M20: =$L20/$AI20 -> 0 | O20: =$N20/$AI20 -> 0 | P20: 183.06 | Q20: =$P20/$AI20 -> 0.0037779591 | R20: 932.268 | S20: =$R20/$AI20 -> 0.019239978 | U20: =$T20/$AI20 -> 0 | W20: =$V20/$AI20 -> 0 | X20: 273.55 | Y20: =$X20/$AI20 -> 0.0056454753 | Z20: 32.211 | AA20: =$Z20/$AI20 -> 0.00066476478 | AB20: 6102.949 | AC20: =$AB20/AI20 -> 0.12595156 | AD20: 23941.996 | AE20: =$AD20/$AI20 -> 0.49411058 | AF20: -42456.901 | AG20: -5997.832 | AH20: =SUM(AF20,AG20) -> -48454.733 | AI20: =((AF20+AG20)*-1) -> 48454.733 | AJ20: =AI20/($AI$224) -> 0.0036976899 | AK20: =AJ20*($G$260+$G$313-$B$406) -> 6531.3194 | AL20: 22349.9 | AM20: =AL20/AL$224 -> 0.0047433694 | AN20: =(AM20*$B$406) -> 6449.0139 | AO20: =AN20+AK20 -> 12980.333 | AP20: =$AO20/$AI20 -> 0.26788577 | AQ20: =AB20+AD20+AH20 -> -18409.788 | AR20: =AQ20+AO20 -> -5429.4547 | AS20: =AR20/AI20 -> -0.1120521 | AU20: TOTAL DE GASTOS
A21: [ BJM ] - BEJUMA | B21: 0 | C21: =$B21/$AI21 -> 0 | D21: 700 | E21: =$D21/$AI21 -> 0.01439139 | F21: 239.18 | G21: =$F21/$AI21 -> 0.0049173324 | H21: 0 | I21: =$H21/$AI21 -> 0 | J21: 3011.965 | K21: =$J21/$AI21 -> 0.061923376 | M21: =$L21/$AI21 -> 0 | O21: =$N21/$AI21 -> 0 | P21: 59.23 | Q21: =$P21/$AI21 -> 0.0012177172 | R21: 2486.392 | S21: =$R21/$AI21 -> 0.051118053 | U21: =$T21/$AI21 -> 0 | W21: =$V21/$AI21 -> 0 | X21: 157.32 | Y21: =$X21/$AI21 -> 0.0032343621 | Z21: -43.906 | AA21: =$Z21/$AI21 -> -0.0009026691 | AB21: 6610.181 | AC21: =$AB21/AI21 -> 0.13589956 | AD21: 24201.919 | AE21: =$AD21/$AI21 -> 0.49757036 | AF21: -42637.384 | AG21: -6002.81 | AH21: =SUM(AF21,AG21) -> -48640.194 | AI21: =((AF21+AG21)*-1) -> 48640.194 | AJ21: =AI21/($AI$224) -> 0.0037118429 | AK21: =AJ21*($G$260+$G$313-$B$406) -> 6556.3181 | AL21: 17717.493 | AM21: =AL21/AL$224 -> 0.0037602233 | AN21: =(AM21*$B$406) -> 5112.3432 | AO21: =AN21+AK21 -> 11668.661 | AP21: =$AO21/$AI21 -> 0.23989751 | AQ21: =AB21+AD21+AH21 -> -17828.094 | AR21: =AQ21+AO21 -> -6159.4327 | AS21: =AR21/AI21 -> -0.12663257 | AU21: Gastos superiores a $7000 | AV21: 82 tiendas | AW21: 876718.67
A22: [ BLS ] - BAILADORES | B22: 0 | C22: =$B22/$AI22 -> 0 | D22: 400 | E22: =$D22/$AI22 -> 0.14770612 | F22: 0 | G22: =$F22/$AI22 -> 0 | H22: 0 | I22: =$H22/$AI22 -> 0 | J22: 0 | K22: =$J22/$AI22 -> 0 | M22: =$L22/$AI22 -> 0 | N22: 240 | O22: =$N22/$AI22 -> 0.088623674 | P22: 87.56 | Q22: =$P22/$AI22 -> 0.032332871 | R22: 2.315 | S22: =$R22/$AI22 -> 0.00085484919 | U22: =$T22/$AI22 -> 0 | W22: =$V22/$AI22 -> 0 | X22: 53.98 | Y22: =$X22/$AI22 -> 0.019932941 | Z22: 0.151 | AA22: =$Z22/$AI22 -> 5.5759062e-05 | AB22: 784.006 | AC22: =$AB22/AI22 -> 0.28950622 | AD22: 815.361 | AE22: =$AD22/$AI22 -> 0.30108453 | AF22: -2366.67 | AG22: -341.41 | AH22: =SUM(AF22,AG22) -> -2708.08 | AI22: =((AF22+AG22)*-1) -> 2708.08 | AJ22: =AI22/($AI$224) -> 0.00020665969 | AK22: =AJ22*($G$260+$G$313-$B$406) -> 365.02802 | AL22: 1079.4016 | AM22: =AL22/AL$224 -> 0.00022908383 | AN22: =(AM22*$B$406) -> 311.45894 | AO22: =AN22+AK22 -> 676.48697 | AP22: =$AO22/$AI22 -> 0.24980317 | AQ22: =AB22+AD22+AH22 -> -1108.713 | AR22: =AQ22+AO22 -> -432.22603 | AS22: =AR22/AI22 -> -0.15960608 | AU22: Gastos entre $4001 hasta $7000 | AV22: 88 tiendas | AW22: 453550.48
A23: [ BNS ] - BARINAS SHOP | B23: 0 | C23: =$B23/$AI23 -> 0 | D23: 2400 | E23: =$D23/$AI23 -> 0.020077593 | F23: 49.76 | G23: =$F23/$AI23 -> 0.00041627542 | H23: 0 | I23: =$H23/$AI23 -> 0 | J23: 6859.219 | K23: =$J23/$AI23 -> 0.057381918 | M23: =$L23/$AI23 -> 0 | O23: =$N23/$AI23 -> 0 | P23: 200.74 | Q23: =$P23/$AI23 -> 0.0016793233 | R23: 804.023 | S23: =$R23/$AI23 -> 0.0067261859 | U23: =$T23/$AI23 -> 0 | W23: =$V23/$AI23 -> 0 | X23: 231.44 | Y23: =$X23/$AI23 -> 0.0019361492 | Z23: 651.377 | AA23: =$Z23/$AI23 -> 0.0054492008 | AB23: 11196.559 | AC23: =$AB23/AI23 -> 0.093666646 | AD23: 63765.986 | AE23: =$AD23/$AI23 -> 0.53344479 | AF23: -104268.82 | AG23: -15267.428 | AH23: =SUM(AF23,AG23) -> -119536.24 | AI23: =((AF23+AG23)*-1) -> 119536.24 | AJ23: =AI23/($AI$224) -> 0.0091220803 | AK23: =AJ23*($G$260+$G$313-$B$406) -> 16112.552 | AL23: 41233.126 | AM23: =AL23/AL$224 -> 0.0087509989 | AN23: =(AM23*$B$406) -> 11897.727 | AO23: =AN23+AK23 -> 28010.278 | AP23: =$AO23/$AI23 -> 0.23432457 | AQ23: =AB23+AD23+AH23 -> -44573.699 | AR23: =AQ23+AO23 -> -16563.421 | AS23: =AR23/AI23 -> -0.138564 | AU23: Gastos entre $0 hasta $4000 | AV23: 52 tiendas | AW23: 83993.31
A24: [ BRC ] - BARRANCAS | B24: 0 | C24: =$B24/$AI24 -> 0 | D24: 600 | E24: =$D24/$AI24 -> 0.015589314 | F24: 26.87 | G24: =$F24/$AI24 -> 0.00069814146 | H24: 0 | I24: =$H24/$AI24 -> 0 | J24: 2970.428 | K24: =$J24/$AI24 -> 0.077178226 | M24: =$L24/$AI24 -> 0 | O24: =$N24/$AI24 -> 0 | P24: 146.84 | Q24: =$P24/$AI24 -> 0.0038152248 | R24: 85.385 | S24: =$R24/$AI24 -> 0.0022184893 | U24: =$T24/$AI24 -> 0 | W24: =$V24/$AI24 -> 0 | X24: 172.28 | Y24: =$X24/$AI24 -> 0.0044762118 | Z24: 26.777 | AA24: =$Z24/$AI24 -> 0.00069572511 | AB24: 4028.58 | AC24: =$AB24/AI24 -> 0.10467133 | AD24: 19262.203 | AE24: =$AD24/$AI24 -> 0.50047423 | AF24: -33678.031 | AG24: -4809.871 | AH24: =SUM(AF24,AG24) -> -38487.902 | AI24: =((AF24+AG24)*-1) -> 38487.902 | AJ24: =AI24/($AI$224) -> 0.0029370986 | AK24: =AJ24*($G$260+$G$313-$B$406) -> 5187.8685 | AL24: 17686.951 | AM24: =AL24/AL$224 -> 0.0037537413 | AN24: =(AM24*$B$406) -> 5103.5303 | AO24: =AN24+AK24 -> 10291.399 | AP24: =$AO24/$AI24 -> 0.26739308 | AQ24: =AB24+AD24+AH24 -> -15197.119 | AR24: =AQ24+AO24 -> -4905.7202 | AS24: =AR24/AI24 -> -0.12746136 | AU24: TOTALES | AV24: 222 | AW24: =SUM(AW21:AW23) -> 1414262.5
A25: [ BTA ] - BARUTA | B25: 0 | C25: =$B25/$AI25 -> 0 | D25: 1800 | E25: =$D25/$AI25 -> 0.02607226 | F25: 0 | G25: =$F25/$AI25 -> 0 | H25: 0 | I25: =$H25/$AI25 -> 0 | J25: 4635.075 | K25: =$J25/$AI25 -> 0.067137157 | M25: =$L25/$AI25 -> 0 | O25: =$N25/$AI25 -> 0 | P25: 115.02 | Q25: =$P25/$AI25 -> 0.0016660174 | R25: 4133.532 | S25: =$R25/$AI25 -> 0.059872513 | U25: =$T25/$AI25 -> 0 | V25: 425 | W25: =$V25/$AI25 -> 0.0061559504 | X25: 380.17 | Y25: =$X25/$AI25 -> 0.0055066063 | Z25: 42.266 | AA25: =$Z25/$AI25 -> 0.00061220564 | AB25: 11531.063 | AC25: =$AB25/AI25 -> 0.16702271 | AD25: 32236.414 | AE25: =$AD25/$AI25 -> 0.46693121 | AF25: -60104.394 | AG25: -8934.499 | AH25: =SUM(AF25,AG25) -> -69038.893 | AI25: =((AF25+AG25)*-1) -> 69038.893 | AJ25: =AI25/($AI$224) -> 0.0052685136 | AK25: =AJ25*($G$260+$G$313-$B$406) -> 9305.9033 | AL25: 28880.64 | AM25: =AL25/AL$224 -> 0.0061294032 | AN25: =(AM25*$B$406) -> 8333.4446 | AO25: =AN25+AK25 -> 17639.348 | AP25: =$AO25/$AI25 -> 0.25549871 | AQ25: =AB25+AD25+AH25 -> -25271.416 | AR25: =AQ25+AO25 -> -7632.0681 | AS25: =AR25/AI25 -> -0.11054737
A26: [ BVC ] - BAZAR VALENCIA CANGURO | B26: 0 | C26: =$B26/$AI26 -> 0 | D26: 3650 | E26: =$D26/$AI26 -> 0.029540196 | F26: 128.54 | G26: =$F26/$AI26 -> 0.0010403005 | H26: 0 | I26: =$H26/$AI26 -> 0 | J26: 4643.673 | K26: =$J26/$AI26 -> 0.037582195 | M26: =$L26/$AI26 -> 0 | O26: =$N26/$AI26 -> 0 | P26: 185.55 | Q26: =$P26/$AI26 -> 0.0015016941 | R26: 1208.245 | S26: =$R26/$AI26 -> 0.0097785737 | U26: =$T26/$AI26 -> 0 | W26: =$V26/$AI26 -> 0 | X26: 385.9 | Y26: =$X26/$AI26 -> 0.0031231676 | Z26: 872.497 | AA26: =$Z26/$AI26 -> 0.0070612965 | AB26: 11074.405 | AC26: =$AB26/AI26 -> 0.089627423 | AD26: 69758.571 | AE26: =$AD26/$AI26 -> 0.56457037 | AF26: -107646.38 | AG26: -15914.072 | AH26: =SUM(AF26,AG26) -> -123560.45 | AI26: =((AF26+AG26)*-1) -> 123560.45 | AJ26: =AI26/($AI$224) -> 0.0094291768 | AK26: =AJ26*($G$260+$G$313-$B$406) -> 16654.984 | AL26: 28062.578 | AM26: =AL26/AL$224 -> 0.005955784 | AN26: =(AM26*$B$406) -> 8097.3945 | AO26: =AN26+AK26 -> 24752.378 | AP26: =$AO26/$AI26 -> 0.20032606 | AQ26: =AB26+AD26+AH26 -> -42727.477 | AR26: =AQ26+AO26 -> -17975.099 | AS26: =AR26/AI26 -> -0.14547615
A27: [ BZC ] - BAZAR 4 | B27: 0 | C27: =$B27/$AI27 -> 0 | D27: 1200 | E27: =$D27/$AI27 -> 0.024557499 | F27: 0 | G27: =$F27/$AI27 -> 0 | H27: 0 | I27: =$H27/$AI27 -> 0 | J27: 2917.646 | K27: =$J27/$AI27 -> 0.059708408 | M27: =$L27/$AI27 -> 0 | O27: =$N27/$AI27 -> 0 | P27: 129.93 | Q27: =$P27/$AI27 -> 0.0026589633 | R27: 309.567 | S27: =$R27/$AI27 -> 0.0063351595 | U27: =$T27/$AI27 -> 0 | W27: =$V27/$AI27 -> 0 | X27: 184.93 | Y27: =$X27/$AI27 -> 0.0037845153 | Z27: 63.136 | AA27: =$Z27/$AI27 -> 0.0012920519 | AB27: 4805.209 | AC27: =$AB27/AI27 -> 0.098336598 | AD27: 28294.648 | AE27: =$AD27/$AI27 -> 0.57903817 | AF27: -43041.202 | AG27: -5823.708 | AH27: =SUM(AF27,AG27) -> -48864.91 | AI27: =((AF27+AG27)*-1) -> 48864.91 | AJ27: =AI27/($AI$224) -> 0.0037289915 | AK27: =AJ27*($G$260+$G$313-$B$406) -> 6586.608 | AL27: 10395.796 | AM27: =AL27/AL$224 -> 0.0022063232 | AN27: =(AM27*$B$406) -> 2999.6839 | AO27: =AN27+AK27 -> 9586.292 | AP27: =$AO27/$AI27 -> 0.19617947 | AQ27: =AB27+AD27+AH27 -> -15765.053 | AR27: =AQ27+AO27 -> -6178.761 | AS27: =AR27/AI27 -> -0.12644577 | AU27: TIENDAS NUEVAS
A28: [ BZD ] - BAZAR 2 | B28: 0 | C28: =$B28/$AI28 -> 0 | D28: 1200 | E28: =$D28/$AI28 -> 0.010757121 | F28: 0 | G28: =$F28/$AI28 -> 0 | H28: 0 | I28: =$H28/$AI28 -> 0 | J28: 3609.041 | K28: =$J28/$AI28 -> 0.03235241 | M28: =$L28/$AI28 -> 0 | O28: =$N28/$AI28 -> 0 | P28: 171.98 | Q28: =$P28/$AI28 -> 0.0015416748 | R28: 102.433 | S28: =$R28/$AI28 -> 0.00091823683 | T28: 6.57 | U28: =$T28/$AI28 -> 5.8895239e-05 | W28: =$V28/$AI28 -> 0 | X28: 209.17 | Y28: =$X28/$AI28 -> 0.0018750559 | Z28: 122.607 | AA28: =$Z28/$AI28 -> 0.001099082 | AB28: 5421.801 | AC28: =$AB28/AI28 -> 0.048602476 | AD28: 65230.391 | AE28: =$AD28/$AI28 -> 0.58474269 | AF28: -97801.734 | AG28: -13752.275 | AH28: =SUM(AF28,AG28) -> -111554.01 | AI28: =((AF28+AG28)*-1) -> 111554.01 | AJ28: =AI28/($AI$224) -> 0.008512938 | AK28: =AJ28*($G$260+$G$313-$B$406) -> 15036.609 | AL28: 23517.646 | AM28: =AL28/AL$224 -> 0.0049912028 | AN28: =(AM28*$B$406) -> 6785.9644 | AO28: =AN28+AK28 -> 21822.573 | AP28: =$AO28/$AI28 -> 0.19562339 | AQ28: =AB28+AD28+AH28 -> -40901.817 | AR28: =AQ28+AO28 -> -19079.244 | AS28: =AR28/AI28 -> -0.17103145 | AU28: [ ADS - BQT ] - AEDOS BARQUISIMETO
A29: [ BZT ] - BAZAR 3 | B29: 0 | C29: =$B29/$AI29 -> 0 | D29: 1000 | E29: =$D29/$AI29 -> 0.028736 | F29: 0 | G29: =$F29/$AI29 -> 0 | H29: 0 | I29: =$H29/$AI29 -> 0 | J29: 2738.454 | K29: =$J29/$AI29 -> 0.078692215 | M29: =$L29/$AI29 -> 0 | O29: =$N29/$AI29 -> 0 | P29: 114.42 | Q29: =$P29/$AI29 -> 0.0032879732 | R29: 75.61 | S29: =$R29/$AI29 -> 0.002172729 | U29: =$T29/$AI29 -> 0 | W29: =$V29/$AI29 -> 0 | X29: 186 | Y29: =$X29/$AI29 -> 0.0053448961 | Z29: 27.424 | AA29: =$Z29/$AI29 -> 0.00078805608 | AB29: 4141.908 | AC29: =$AB29/AI29 -> 0.11902187 | AD29: 18863.316 | AE29: =$AD29/$AI29 -> 0.54205626 | AF29: -30700.528 | AG29: -4099.026 | AH29: =SUM(AF29,AG29) -> -34799.554 | AI29: =((AF29+AG29)*-1) -> 34799.554 | AJ29: =AI29/($AI$224) -> 0.0026556324 | AK29: =AJ29*($G$260+$G$313-$B$406) -> 4690.708 | AL29: 8313.2578 | AM29: =AL29/AL$224 -> 0.0017643414 | AN29: =(AM29*$B$406) -> 2398.7721 | AO29: =AN29+AK29 -> 7089.48 | AP29: =$AO29/$AI29 -> 0.2037233 | AQ29: =AB29+AD29+AH29 -> -11794.33 | AR29: =AQ29+AO29 -> -4704.85 | AS29: =AR29/AI29 -> -0.13519857 | AU29: [ ARY ] - AROA YARACUY
A30: [ BZU ] - BAZAR 1 | B30: 0 | C30: =$B30/$AI30 -> 0 | D30: 1200 | E30: =$D30/$AI30 -> 0.020241401 | F30: 0 | G30: =$F30/$AI30 -> 0 | H30: 0 | I30: =$H30/$AI30 -> 0 | J30: 2653.566 | K30: =$J30/$AI30 -> 0.04475991 | M30: =$L30/$AI30 -> 0 | O30: =$N30/$AI30 -> 0 | P30: 107.1 | Q30: =$P30/$AI30 -> 0.001806545 | R30: 93.32 | S30: =$R30/$AI30 -> 0.0015741063 | T30: 6.57 | U30: =$T30/$AI30 -> 0.00011082167 | W30: =$V30/$AI30 -> 0 | X30: 186.79 | Y30: =$X30/$AI30 -> 0.0031507427 | Z30: 144.973 | AA30: =$Z30/$AI30 -> 0.0024453805 | AB30: 4392.319 | AC30: =$AB30/AI30 -> 0.074088907 | AD30: 33010.969 | AE30: =$AD30/$AI30 -> 0.55682354 | AF30: -52116.931 | AG30: -7167.504 | AH30: =SUM(AF30,AG30) -> -59284.435 | AI30: =((AF30+AG30)*-1) -> 59284.435 | AJ30: =AI30/($AI$224) -> 0.0045241289 | AK30: =AJ30*($G$260+$G$313-$B$406) -> 7991.0786 | AL30: 14567.642 | AM30: =AL30/AL$224 -> 0.0030917233 | AN30: =(AM30*$B$406) -> 4203.4607 | AO30: =AN30+AK30 -> 12194.539 | AP30: =$AO30/$AI30 -> 0.20569546 | AQ30: =AB30+AD30+AH30 -> -21881.147 | AR30: =AQ30+AO30 -> -9686.6077 | AS30: =AR30/AI30 -> -0.16339209 | AU30: [ BLS ] - BAILADORES
A31: [ CAG ] - CAGUA | B31: 0 | C31: =$B31/$AI31 -> 0 | D31: 700 | E31: =$D31/$AI31 -> 0.0095288515 | F31: 149.51 | G31: =$F31/$AI31 -> 0.0020352266 | H31: 0 | I31: =$H31/$AI31 -> 0 | J31: 3383.434 | K31: =$J31/$AI31 -> 0.046057486 | M31: =$L31/$AI31 -> 0 | O31: =$N31/$AI31 -> 0 | P31: 85.36 | Q31: =$P31/$AI31 -> 0.0011619754 | R31: 1287.054 | S31: =$R31/$AI31 -> 0.017520209 | U31: =$T31/$AI31 -> 0 | W31: =$V31/$AI31 -> 0 | X31: 191.87 | Y31: =$X31/$AI31 -> 0.0026118582 | Z31: 78.073 | AA31: =$Z31/$AI31 -> 0.00106278 | AB31: 5875.301 | AC31: =$AB31/AI31 -> 0.079978387 | AD31: 35349.549 | AE31: =$AD31/$AI31 -> 0.48120086 | AF31: -64164.724 | AG31: -9296.385 | AH31: =SUM(AF31,AG31) -> -73461.109 | AI31: =((AF31+AG31)*-1) -> 73461.109 | AJ31: =AI31/($AI$224) -> 0.0056059829 | AK31: =AJ31*($G$260+$G$313-$B$406) -> 9901.9835 | AL31: 24410.196 | AM31: =AL31/AL$224 -> 0.0051806308 | AN31: =(AM31*$B$406) -> 7043.5079 | AO31: =AN31+AK31 -> 16945.491 | AP31: =$AO31/$AI31 -> 0.23067296 | AQ31: =AB31+AD31+AH31 -> -32236.259 | AR31: =AQ31+AO31 -> -15290.768 | AS31: =AR31/AI31 -> -0.20814779 | AU31: [ TVR ] - TOVAR MERIDA
A32: [ CAT ] - CATIA | B32: 0 | C32: =$B32/$AI32 -> 0 | D32: 2600 | E32: =$D32/$AI32 -> 0.015340892 | F32: 0 | G32: =$F32/$AI32 -> 0 | H32: 0 | I32: =$H32/$AI32 -> 0 | J32: 11218.025 | K32: =$J32/$AI32 -> 0.066190197 | M32: =$L32/$AI32 -> 0 | N32: 228.45 | O32: =$N32/$AI32 -> 0.0013479334 | P32: 150.84 | Q32: =$P32/$AI32 -> 0.00089000776 | R32: 1163.745 | S32: =$R32/$AI32 -> 0.0068664948 | U32: =$T32/$AI32 -> 0 | W32: =$V32/$AI32 -> 0 | X32: 352.564 | Y32: =$X32/$AI32 -> 0.0020802486 | Z32: 171.075 | AA32: =$Z32/$AI32 -> 0.0010094012 | AB32: 15884.699 | AC32: =$AB32/AI32 -> 0.093725175 | AD32: 84387.513 | AE32: =$AD32/$AI32 -> 0.49791528 | AF32: -147246.17 | AG32: -22235.497 | AH32: =SUM(AF32,AG32) -> -169481.67 | AI32: =((AF32+AG32)*-1) -> 169481.67 | AJ32: =AI32/($AI$224) -> 0.012933528 | AK32: =AJ32*($G$260+$G$313-$B$406) -> 22844.805 | AL32: 66747.561 | AM32: =AL32/AL$224 -> 0.014165985 | AN32: =(AM32*$B$406) -> 19259.861 | AO32: =AN32+AK32 -> 42104.665 | AP32: =$AO32/$AI32 -> 0.24843197 | AQ32: =AB32+AD32+AH32 -> -69209.456 | AR32: =AQ32+AO32 -> -27104.791 | AS32: =AR32/AI32 -> -0.15992757 | AU32: [ ABM ] - AV BOLIVAR DE MATURIN
A33: [ CBM ] - CABIMAS | B33: 0 | C33: =$B33/$AI33 -> 0 | D33: 1000 | E33: =$D33/$AI33 -> 0.011708942 | F33: 50.28 | G33: =$F33/$AI33 -> 0.0005887256 | H33: 0 | I33: =$H33/$AI33 -> 0 | J33: 3940.957 | K33: =$J33/$AI33 -> 0.046144437 | M33: =$L33/$AI33 -> 0 | O33: =$N33/$AI33 -> 0 | P33: 183.4 | Q33: =$P33/$AI33 -> 0.00214742 | R33: 2068.952 | S33: =$R33/$AI33 -> 0.024225239 | U33: =$T33/$AI33 -> 0 | W33: =$V33/$AI33 -> 0 | X33: 114.69 | Y33: =$X33/$AI33 -> 0.0013428986 | Z33: 16.534 | AA33: =$Z33/$AI33 -> 0.00019359565 | AB33: 7374.813 | AC33: =$AB33/AI33 -> 0.086351258 | AD33: 43333.13 | AE33: =$AD33/$AI33 -> 0.5073851 | AF33: -74464.669 | AG33: -10940.144 | AH33: =SUM(AF33,AG33) -> -85404.813 | AI33: =((AF33+AG33)*-1) -> 85404.813 | AJ33: =AI33/($AI$224) -> 0.0065174339 | AK33: =AJ33*($G$260+$G$313-$B$406) -> 11511.901 | AL33: 29725.609 | AM33: =AL33/AL$224 -> 0.0063087327 | AN33: =(AM33*$B$406) -> 8577.2583 | AO33: =AN33+AK33 -> 20089.16 | AP33: =$AO33/$AI33 -> 0.23522281 | AQ33: =AB33+AD33+AH33 -> -34696.87 | AR33: =AQ33+AO33 -> -14607.71 | AS33: =AR33/AI33 -> -0.17104083
A34: [ CBQ ] - CHABASQUEN | B34: 0 | C34: =$B34/$AI34 -> 0 | D34: 500 | E34: =$D34/$AI34 -> 0.019421878 | F34: 45.47 | G34: =$F34/$AI34 -> 0.0017662256 | H34: 0 | I34: =$H34/$AI34 -> 0 | J34: 2559.083 | K34: =$J34/$AI34 -> 0.099404397 | M34: =$L34/$AI34 -> 0 | O34: =$N34/$AI34 -> 0 | P34: 22.67 | Q34: =$P34/$AI34 -> 0.00088058796 | R34: 1804.946 | S34: =$R34/$AI34 -> 0.070110883 | U34: =$T34/$AI34 -> 0 | W34: =$V34/$AI34 -> 0 | X34: 93.04 | Y34: =$X34/$AI34 -> 0.0036140231 | Z34: 179.762 | AA34: =$Z34/$AI34 -> 0.0069826314 | AB34: 5204.971 | AC34: =$AB34/AI34 -> 0.20218063 | AD34: 12712.48 | AE34: =$AD34/$AI34 -> 0.49380048 | AF34: -22404.081 | AG34: -3340.082 | AH34: =SUM(AF34,AG34) -> -25744.163 | AI34: =((AF34+AG34)*-1) -> 25744.163 | AJ34: =AI34/($AI$224) -> 0.0019645951 | AK34: =AJ34*($G$260+$G$313-$B$406) -> 3470.112 | AL34: 8589.9372 | AM34: =AL34/AL$224 -> 0.0018230617 | AN34: =(AM34*$B$406) -> 2478.6073 | AO34: =AN34+AK34 -> 5948.7193 | AP34: =$AO34/$AI34 -> 0.2310706 | AQ34: =AB34+AD34+AH34 -> -7826.712 | AR34: =AQ34+AO34 -> -1877.9927 | AS34: =AR34/AI34 -> -0.072948291
A35: [ CBR ] - CABUDARE | B35: 0 | C35: =$B35/$AI35 -> 0 | D35: 600 | E35: =$D35/$AI35 -> 0.014626037 | F35: 70 | G35: =$F35/$AI35 -> 0.001706371 | H35: 0 | I35: =$H35/$AI35 -> 0 | J35: 3951.349 | K35: =$J35/$AI35 -> 0.096320962 | M35: =$L35/$AI35 -> 0 | O35: =$N35/$AI35 -> 0 | P35: 26.68 | Q35: =$P35/$AI35 -> 0.00065037112 | R35: 629.403 | S35: =$R35/$AI35 -> 0.015342786 | U35: =$T35/$AI35 -> 0 | W35: =$V35/$AI35 -> 0 | X35: 45.9 | Y35: =$X35/$AI35 -> 0.0011188918 | Z35: 93.4 | AA35: =$Z35/$AI35 -> 0.0022767864 | AB35: 5416.732 | AC35: =$AB35/AI35 -> 0.13204221 | AD35: 18104.009 | AE35: =$AD35/$AI35 -> 0.44131651 | AF35: -36012.324 | AG35: -5010.408 | AH35: =SUM(AF35,AG35) -> -41022.732 | AI35: =((AF35+AG35)*-1) -> 41022.732 | AJ35: =AI35/($AI$224) -> 0.0031305372 | AK35: =AJ35*($G$260+$G$313-$B$406) -> 5529.5437 | AL35: 15263.332 | AM35: =AL35/AL$224 -> 0.0032393712 | AN35: =(AM35*$B$406) -> 4404.2004 | AO35: =AN35+AK35 -> 9933.7442 | AP35: =$AO35/$AI35 -> 0.24215218 | AQ35: =AB35+AD35+AH35 -> -17501.991 | AR35: =AQ35+AO35 -> -7568.2468 | AS35: =AR35/AI35 -> -0.1844891
A36: [ CBV ] - CIUDAD BOLIVAR | B36: 0 | C36: =$B36/$AI36 -> 0 | D36: 1007 | E36: =$D36/$AI36 -> 0.013376157 | F36: 24.51 | G36: =$F36/$AI36 -> 0.00032557061 | H36: 0 | I36: =$H36/$AI36 -> 0 | J36: 6370.228 | K36: =$J36/$AI36 -> 0.084616852 | M36: =$L36/$AI36 -> 0 | N36: 291.2 | O36: =$N36/$AI36 -> 0.0038680605 | P36: 161.59 | Q36: =$P36/$AI36 -> 0.0021464282 | R36: 1725.395 | S36: =$R36/$AI36 -> 0.022918723 | U36: =$T36/$AI36 -> 0 | W36: =$V36/$AI36 -> 0 | X36: 123.68 | Y36: =$X36/$AI36 -> 0.0016428631 | Z36: 28.608 | AA36: =$Z36/$AI36 -> 0.00038000507 | AB36: 9732.211 | AC36: =$AB36/AI36 -> 0.12927466 | AD36: 36033.337 | AE36: =$AD36/$AI36 -> 0.47863711 | AF36: -65915.319 | AG36: -9367.888 | AH36: =SUM(AF36,AG36) -> -75283.207 | AI36: =((AF36+AG36)*-1) -> 75283.207 | AJ36: =AI36/($AI$224) -> 0.0057450313 | AK36: =AJ36*($G$260+$G$313-$B$406) -> 10147.588 | AL36: 27392.171 | AM36: =AL36/AL$224 -> 0.005813502 | AN36: =(AM36*$B$406) -> 7903.9501 | AO36: =AN36+AK36 -> 18051.538 | AP36: =$AO36/$AI36 -> 0.23978174 | AQ36: =AB36+AD36+AH36 -> -29517.659 | AR36: =AQ36+AO36 -> -11466.121 | AS36: =AR36/AI36 -> -0.15230649
A37: [ CCA ] - CENTRO COMERCIAL AVIADORES | B37: 0 | C37: =$B37/$AI37 -> 0 | D37: 2212.97 | E37: =$D37/$AI37 -> 0.046472405 | F37: 11.43 | G37: =$F37/$AI37 -> 0.00024003018 | H37: 0 | I37: =$H37/$AI37 -> 0 | J37: 3744.306 | K37: =$J37/$AI37 -> 0.078630485 | M37: =$L37/$AI37 -> 0 | N37: 29.14 | O37: =$N37/$AI37 -> 0.00061194046 | P37: 482.9 | Q37: =$P37/$AI37 -> 0.010140908 | R37: 153.692 | S37: =$R37/$AI37 -> 0.0032275344 | U37: =$T37/$AI37 -> 0 | W37: =$V37/$AI37 -> 0 | X37: 976.26 | Y37: =$X37/$AI37 -> 0.020501475 | Z37: 279.311 | AA37: =$Z37/$AI37 -> 0.0058655354 | AB37: 7890.009 | AC37: =$AB37/AI37 -> 0.16569031 | AD37: 20686.388 | AE37: =$AD37/$AI37 -> 0.43441447 | AF37: -41597.093 | AG37: -6021.919 | AH37: =SUM(AF37,AG37) -> -47619.012 | AI37: =((AF37+AG37)*-1) -> 47619.012 | AJ37: =AI37/($AI$224) -> 0.0036339142 | AK37: =AJ37*($G$260+$G$313-$B$406) -> 6418.6707 | AL37: 16151.289 | AM37: =AL37/AL$224 -> 0.0034278242 | AN37: =(AM37*$B$406) -> 4660.4184 | AO37: =AN37+AK37 -> 11079.089 | AP37: =$AO37/$AI37 -> 0.23266105 | AQ37: =AB37+AD37+AH37 -> -19042.615 | AR37: =AQ37+AO37 -> -7963.5259 | AS37: =AR37/AI37 -> -0.16723417
A38: [ CCB ] - CALLE CAMEJO BARINAS | B38: 0 | C38: =$B38/$AI38 -> 0 | D38: 575 | E38: =$D38/$AI38 -> 0.012508857 | F38: 67.5 | G38: =$F38/$AI38 -> 0.0014684311 | H38: 0 | I38: =$H38/$AI38 -> 0 | J38: 2136.507 | K38: =$J38/$AI38 -> 0.046478715 | M38: =$L38/$AI38 -> 0 | O38: =$N38/$AI38 -> 0 | Q38: =$P38/$AI38 -> 0 | R38: 714.853 | S38: =$R38/$AI38 -> 0.015551294 | U38: =$T38/$AI38 -> 0 | W38: =$V38/$AI38 -> 0 | X38: 69.65 | Y38: =$X38/$AI38 -> 0.0015152033 | Z38: 112.768 | AA38: =$Z38/$AI38 -> 0.0024532154 | AB38: 3676.278 | AC38: =$AB38/AI38 -> 0.079975717 | AD38: 25348.269 | AE38: =$AD38/$AI38 -> 0.55143979 | AF38: -40119.566 | AG38: -5847.862 | AH38: =SUM(AF38,AG38) -> -45967.428 | AI38: =((AF38+AG38)*-1) -> 45967.428 | AJ38: =AI38/($AI$224) -> 0.0035078781 | AK38: =AJ38*($G$260+$G$313-$B$406) -> 6196.0501 | AL38: 14810.77 | AM38: =AL38/AL$224 -> 0.0031433229 | AN38: =(AM38*$B$406) -> 4273.6147 | AO38: =AN38+AK38 -> 10469.665 | AP38: =$AO38/$AI38 -> 0.22776268 | AQ38: =AB38+AD38+AH38 -> -16942.881 | AR38: =AQ38+AO38 -> -6473.2162 | AS38: =AR38/AI38 -> -0.14082181
A39: [ CCM ] - CENTRO COMERCIAL METROCENTER | B39: 0 | C39: =$B39/$AI39 -> 0 | D39: 1200 | E39: =$D39/$AI39 -> 0.01808444 | F39: 0 | G39: =$F39/$AI39 -> 0 | H39: 0 | I39: =$H39/$AI39 -> 0 | J39: 2388.414 | K39: =$J39/$AI39 -> 0.035994275 | M39: =$L39/$AI39 -> 0 | O39: =$N39/$AI39 -> 0 | P39: 126.27 | Q39: =$P39/$AI39 -> 0.0019029352 | R39: 731.877 | S39: =$R39/$AI39 -> 0.011029655 | U39: =$T39/$AI39 -> 0 | W39: =$V39/$AI39 -> 0 | X39: 356.43 | Y39: =$X39/$AI39 -> 0.0053715309 | Z39: 516.138 | AA39: =$Z39/$AI39 -> 0.007778389 | AB39: 5319.129 | AC39: =$AB39/AI39 -> 0.080161226 | AD39: 34707.77 | AE39: =$AD39/$AI39 -> 0.52305883 | AF39: -59060.347 | AG39: -7295.038 | AH39: =SUM(AF39,AG39) -> -66355.385 | AI39: =((AF39+AG39)*-1) -> 66355.385 | AJ39: =AI39/($AI$224) -> 0.0050637291 | AK39: =AJ39*($G$260+$G$313-$B$406) -> 8944.1874 | AL39: 27201.271 | AM39: =AL39/AL$224 -> 0.0057729868 | AN39: =(AM39*$B$406) -> 7848.8663 | AO39: =AN39+AK39 -> 16793.054 | AP39: =$AO39/$AI39 -> 0.25307748 | AQ39: =AB39+AD39+AH39 -> -26328.486 | AR39: =AQ39+AO39 -> -9535.4323 | AS39: =AR39/AI39 -> -0.14370246
A40: [ CCO ] - CAICARA DEL ORINOCO | B40: 0 | C40: =$B40/$AI40 -> 0 | D40: 600 | E40: =$D40/$AI40 -> 0.013295816 | F40: 0 | G40: =$F40/$AI40 -> 0 | H40: 0 | I40: =$H40/$AI40 -> 0 | J40: 3274.394 | K40: =$J40/$AI40 -> 0.072559566 | M40: =$L40/$AI40 -> 0 | O40: =$N40/$AI40 -> 0 | P40: 83.51 | Q40: =$P40/$AI40 -> 0.001850556 | R40: 1135.959 | S40: =$R40/$AI40 -> 0.025172503 | U40: =$T40/$AI40 -> 0 | W40: =$V40/$AI40 -> 0 | X40: 69.7 | Y40: =$X40/$AI40 -> 0.0015445306 | Z40: 42.725 | AA40: =$Z40/$AI40 -> 0.00094677288 | AB40: 5206.288 | AC40: =$AB40/AI40 -> 0.11536974 | AD40: 22041.84 | AE40: =$AD40/$AI40 -> 0.48844041 | AF40: -39411.242 | AG40: -5715.737 | AH40: =SUM(AF40,AG40) -> -45126.979 | AI40: =((AF40+AG40)*-1) -> 45126.979 | AJ40: =AI40/($AI$224) -> 0.0034437415 | AK40: =AJ40*($G$260+$G$313-$B$406) -> 6082.7642 | AL40: 17926.354 | AM40: =AL40/AL$224 -> 0.0038045504 | AN40: =(AM40*$B$406) -> 5172.6097 | AO40: =AN40+AK40 -> 11255.374 | AP40: =$AO40/$AI40 -> 0.24941563 | AQ40: =AB40+AD40+AH40 -> -17878.851 | AR40: =AQ40+AO40 -> -6623.4772 | AS40: =AR40/AI40 -> -0.14677422
A41: [ CCT ] - CC CIUDAD TAMANACO | B41: 0 | C41: =$B41/$AI41 -> 0 | D41: 1800 | E41: =$D41/$AI41 -> 0.060494297 | F41: 0 | G41: =$F41/$AI41 -> 0 | H41: 0 | I41: =$H41/$AI41 -> 0 | J41: 2134.246 | K41: =$J41/$AI41 -> 0.071727617 | M41: =$L41/$AI41 -> 0 | O41: =$N41/$AI41 -> 0 | P41: 65.99 | Q41: =$P41/$AI41 -> 0.0022177881 | R41: 36.282 | S41: =$R41/$AI41 -> 0.0012193634 | U41: =$T41/$AI41 -> 0 | W41: =$V41/$AI41 -> 0 | X41: 241.43 | Y41: =$X41/$AI41 -> 0.0081139656 | Z41: 347.357 | AA41: =$Z41/$AI41 -> 0.011673954 | AB41: 4625.305 | AC41: =$AB41/AI41 -> 0.15544699 | AD41: 13100.161 | AE41: =$AD41/$AI41 -> 0.44026946 | AF41: -25910.514 | AG41: -3844.357 | AH41: =SUM(AF41,AG41) -> -29754.871 | AI41: =((AF41+AG41)*-1) -> 29754.871 | AJ41: =AI41/($AI$224) -> 0.0022706613 | AK41: =AJ41*($G$260+$G$313-$B$406) -> 4010.7241 | AL41: 16305.29 | AM41: =AL41/AL$224 -> 0.0034605084 | AN41: =(AM41*$B$406) -> 4704.8552 | AO41: =AN41+AK41 -> 8715.5794 | AP41: =$AO41/$AI41 -> 0.29291269 | AQ41: =AB41+AD41+AH41 -> -12029.405 | AR41: =AQ41+AO41 -> -3313.8256 | AS41: =AR41/AI41 -> -0.11137086
A42: [ CDL ] - LA CANDELARIA | B42: 0 | C42: =$B42/$AI42 -> 0 | D42: 3100 | E42: =$D42/$AI42 -> 0.057756407 | F42: 0 | G42: =$F42/$AI42 -> 0 | H42: 0 | I42: =$H42/$AI42 -> 0 | J42: 4919.659 | K42: =$J42/$AI42 -> 0.091658654 | M42: =$L42/$AI42 -> 0 | O42: =$N42/$AI42 -> 0 | P42: 44.79 | Q42: =$P42/$AI42 -> 0.00083448692 | R42: 1308.567 | S42: =$R42/$AI42 -> 0.024380041 | U42: =$T42/$AI42 -> 0 | W42: =$V42/$AI42 -> 0 | X42: 498.49 | Y42: =$X42/$AI42 -> 0.0092874165 | Z42: 80.06 | AA42: =$Z42/$AI42 -> 0.0014916058 | AB42: 9951.566 | AC42: =$AB42/AI42 -> 0.18540861 | AD42: 24757.958 | AE42: =$AD42/$AI42 -> 0.46126797 | AF42: -46814.934 | AG42: -6858.765 | AH42: =SUM(AF42,AG42) -> -53673.699 | AI42: =((AF42+AG42)*-1) -> 53673.699 | AJ42: =AI42/($AI$224) -> 0.004095961 | AK42: =AJ42*($G$260+$G$313-$B$406) -> 7234.7952 | AL42: 23225.524 | AM42: =AL42/AL$224 -> 0.0049292052 | AN42: =(AM42*$B$406) -> 6701.6735 | AO42: =AN42+AK42 -> 13936.469 | AP42: =$AO42/$AI42 -> 0.25965173 | AQ42: =AB42+AD42+AH42 -> -18964.175 | AR42: =AQ42+AO42 -> -5027.7063 | AS42: =AR42/AI42 -> -0.093671694
A43: [ CDO ] - CEDENO | B43: 0 | C43: =$B43/$AI43 -> 0 | D43: 450 | E43: =$D43/$AI43 -> 0.0075823485 | F43: 72.5 | G43: =$F43/$AI43 -> 0.0012216006 | H43: 0 | I43: =$H43/$AI43 -> 0 | J43: 4393.945 | K43: =$J43/$AI43 -> 0.074036494 | M43: =$L43/$AI43 -> 0 | O43: =$N43/$AI43 -> 0 | P43: 92.75 | Q43: =$P43/$AI43 -> 0.0015628063 | R43: 81.716 | S43: =$R43/$AI43 -> 0.0013768871 | U43: =$T43/$AI43 -> 0 | W43: =$V43/$AI43 -> 0 | X43: 162.11 | Y43: =$X43/$AI43 -> 0.0027314989 | Z43: 12.992 | AA43: =$Z43/$AI43 -> 0.00021891083 | AB43: 5266.013 | AC43: =$AB43/AI43 -> 0.088730546 | AD43: 28645.458 | AE43: =$AD43/$AI43 -> 0.48266632 | AF43: -51880.448 | AG43: -7467.919 | AH43: =SUM(AF43,AG43) -> -59348.367 | AI43: =((AF43+AG43)*-1) -> 59348.367 | AJ43: =AI43/($AI$224) -> 0.0045290077 | AK43: =AJ43*($G$260+$G$313-$B$406) -> 7999.6961 | AL43: 16868.372 | AM43: =AL43/AL$224 -> 0.0035800124 | AN43: =(AM43*$B$406) -> 4867.3311 | AO43: =AN43+AK43 -> 12867.027 | AP43: =$AO43/$AI43 -> 0.21680508 | AQ43: =AB43+AD43+AH43 -> -25436.896 | AR43: =AQ43+AO43 -> -12569.869 | AS43: =AR43/AI43 -> -0.21179806
A44: [ CEN - MYR ] - CENDIS MAYOR | B44: 0 | C44: =$B44/$AI44 -> 0 | D44: 0 | E44: =$D44/$AI44 -> 0 | F44: 0 | G44: =$F44/$AI44 -> 0 | H44: 0 | I44: =$H44/$AI44 -> 0 | J44: 0 | K44: =$J44/$AI44 -> 0 | M44: =$L44/$AI44 -> 0 | O44: =$N44/$AI44 -> 0 | Q44: =$P44/$AI44 -> 0 | R44: 406.73 | S44: =$R44/$AI44 -> 0.069222803 | U44: =$T44/$AI44 -> 0 | W44: =$V44/$AI44 -> 0 | X44: 401.58 | Y44: =$X44/$AI44 -> 0.068346306 | AA44: =$Z44/$AI44 -> 0 | AB44: 808.31 | AC44: =$AB44/AI44 -> 0.13756911 | AD44: 2363.826 | AE44: =$AD44/$AI44 -> 0.40230782 | AF44: -3726.185 | AG44: -2149.48 | AH44: =SUM(AF44,AG44) -> -5875.665 | AI44: =((AF44+AG44)*-1) -> 5875.665 | AJ44: =AI44/($AI$224) -> 0.00044838525 | AK44: =AJ44*($G$260+$G$313-$B$406) -> 791.99373 | AL44: 0 | AM44: =AL44/AL$224 -> 0 | AN44: =(AM44*$B$406) -> 0 | AO44: =AN44+AK44 -> 791.99373 | AP44: =$AO44/$AI44 -> 0.13479219 | AQ44: =AB44+AD44+AH44 -> -2703.529 | AR44: =AQ44+AO44 -> -1911.5353 | AS44: =AR44/AI44 -> -0.32533088
A45: [ CEN - SWM ] - CENDIS SHOWROOM | B45: 0 | C45: =$B45/$AI45 -> 0 | D45: 0 | E45: =$D45/$AI45 -> 0 | F45: 0 | G45: =$F45/$AI45 -> 0 | H45: 0 | I45: =$H45/$AI45 -> 0 | J45: 0 | K45: =$J45/$AI45 -> 0 | M45: =$L45/$AI45 -> 0 | O45: =$N45/$AI45 -> 0 | Q45: =$P45/$AI45 -> 0 | S45: =$R45/$AI45 -> 0 | U45: =$T45/$AI45 -> 0 | W45: =$V45/$AI45 -> 0 | Y45: =$X45/$AI45 -> 0 | AA45: =$Z45/$AI45 -> 0 | AB45: 0 | AC45: =$AB45/AI45 -> 0 | AD45: 266.303 | AE45: =$AD45/$AI45 -> 0.20460985 | AF45: -1124.137 | AG45: -177.379 | AH45: =SUM(AF45,AG45) -> -1301.516 | AI45: =((AF45+AG45)*-1) -> 1301.516 | AJ45: =AI45/($AI$224) -> 9.9321621e-05 | AK45: =AJ45*($G$260+$G$313-$B$406) -> 175.43419 | AL45: 567.95748 | AM45: =AL45/AL$224 -> 0.00012053889 | AN45: =(AM45*$B$406) -> 163.88287 | AO45: =AN45+AK45 -> 339.31706 | AP45: =$AO45/$AI45 -> 0.26070909 | AQ45: =AB45+AD45+AH45 -> -1035.213 | AR45: =AQ45+AO45 -> -695.89594 | AS45: =AR45/AI45 -> -0.53468105
A46: [ CHA ] - CHACAO | B46: 0 | C46: =$B46/$AI46 -> 0 | D46: 2000 | E46: =$D46/$AI46 -> 0.040722943 | F46: 0 | G46: =$F46/$AI46 -> 0 | H46: 0 | I46: =$H46/$AI46 -> 0 | J46: 2412.629 | K46: =$J46/$AI46 -> 0.049124677 | M46: =$L46/$AI46 -> 0 | O46: =$N46/$AI46 -> 0 | P46: 90.87 | Q46: =$P46/$AI46 -> 0.0018502469 | R46: 62.542 | S46: =$R46/$AI46 -> 0.0012734472 | U46: =$T46/$AI46 -> 0 | W46: =$V46/$AI46 -> 0 | X46: 289.01 | Y46: =$X46/$AI46 -> 0.0058846689 | Z46: 192.807 | AA46: =$Z46/$AI46 -> 0.0039258342 | AB46: 5047.858 | AC46: =$AB46/AI46 -> 0.10278182 | AD46: 19736.182 | AE46: =$AD46/$AI46 -> 0.40185771 | AF46: -42880.256 | AG46: -6232.108 | AH46: =SUM(AF46,AG46) -> -49112.364 | AI46: =((AF46+AG46)*-1) -> 49112.364 | AJ46: =AI46/($AI$224) -> 0.0037478752 | AK46: =AJ46*($G$260+$G$313-$B$406) -> 6619.9629 | AL46: 22160.282 | AM46: =AL46/AL$224 -> 0.0047031265 | AN46: =(AM46*$B$406) -> 6394.3002 | AO46: =AN46+AK46 -> 13014.263 | AP46: =$AO46/$AI46 -> 0.26498955 | AQ46: =AB46+AD46+AH46 -> -24328.324 | AR46: =AQ46+AO46 -> -11314.061 | AS46: =AR46/AI46 -> -0.23037093
A47: [ CHC ] - CHICHIRIVICHE | B47: 0 | C47: =$B47/$AI47 -> 0 | D47: 400 | E47: =$D47/$AI47 -> 0.019158366 | F47: 0 | G47: =$F47/$AI47 -> 0 | H47: 0 | I47: =$H47/$AI47 -> 0 | J47: 2691.117 | K47: =$J47/$AI47 -> 0.12889351 | M47: =$L47/$AI47 -> 0 | N47: 167.68 | O47: =$N47/$AI47 -> 0.0080311871 | P47: 108.55 | Q47: =$P47/$AI47 -> 0.0051991016 | R47: 434.317 | S47: =$R47/$AI47 -> 0.02080201 | U47: =$T47/$AI47 -> 0 | W47: =$V47/$AI47 -> 0 | X47: 55.29 | Y47: =$X47/$AI47 -> 0.0026481652 | Z47: 138.721 | AA47: =$Z47/$AI47 -> 0.0066441693 | AB47: 3995.675 | AC47: =$AB47/AI47 -> 0.19137651 | AD47: 10575.546 | AE47: =$AD47/$AI47 -> 0.50652546 | AF47: -18154.255 | AG47: -2724.352 | AH47: =SUM(AF47,AG47) -> -20878.607 | AI47: =((AF47+AG47)*-1) -> 20878.607 | AJ47: =AI47/($AI$224) -> 0.0015932936 | AK47: =AJ47*($G$260+$G$313-$B$406) -> 2814.2731 | AL47: 6894.6023 | AM47: =AL47/AL$224 -> 0.0014632569 | AN47: =(AM47*$B$406) -> 1989.4222 | AO47: =AN47+AK47 -> 4803.6953 | AP47: =$AO47/$AI47 -> 0.23007738 | AQ47: =AB47+AD47+AH47 -> -6307.386 | AR47: =AQ47+AO47 -> -1503.6907 | AS47: =AR47/AI47 -> -0.072020645
A48: [ CHI ] - CHIVACOA | B48: 0 | C48: =$B48/$AI48 -> 0 | D48: 510 | E48: =$D48/$AI48 -> 0.0084640407 | F48: 20 | G48: =$F48/$AI48 -> 0.00033192316 | H48: 0 | I48: =$H48/$AI48 -> 0 | J48: 3473.748 | K48: =$J48/$AI48 -> 0.057650871 | M48: =$L48/$AI48 -> 0 | O48: =$N48/$AI48 -> 0 | P48: 92.18 | Q48: =$P48/$AI48 -> 0.0015298339 | R48: 109.474 | S48: =$R48/$AI48 -> 0.0018168478 | U48: =$T48/$AI48 -> 0 | W48: =$V48/$AI48 -> 0 | X48: 138.49 | Y48: =$X48/$AI48 -> 0.0022984019 | Z48: 47.107 | AA48: =$Z48/$AI48 -> 0.00078179522 | AB48: 4390.999 | AC48: =$AB48/AI48 -> 0.072873714 | AD48: 28951.562 | AE48: =$AD48/$AI48 -> 0.4804847 | AF48: -53224.149 | AG48: -7030.76 | AH48: =SUM(AF48,AG48) -> -60254.909 | AI48: =((AF48+AG48)*-1) -> 60254.909 | AJ48: =AI48/($AI$224) -> 0.004598188 | AK48: =AJ48*($G$260+$G$313-$B$406) -> 8121.8909 | AL48: 21574.338 | AM48: =AL48/AL$224 -> 0.0045787701 | AN48: =(AM48*$B$406) -> 6225.2272 | AO48: =AN48+AK48 -> 14347.118 | AP48: =$AO48/$AI48 -> 0.23810704 | AQ48: =AB48+AD48+AH48 -> -26912.348 | AR48: =AQ48+AO48 -> -12565.23 | AS48: =AR48/AI48 -> -0.20853454
A49: [ CHV ] - CHARALLAVE | B49: 0 | C49: =$B49/$AI49 -> 0 | D49: 2680 | E49: =$D49/$AI49 -> 0.017047376 | F49: 22.13 | G49: =$F49/$AI49 -> 0.00014076808 | H49: 0 | I49: =$H49/$AI49 -> 0 | J49: 4711.372 | K49: =$J49/$AI49 -> 0.029968855 | M49: =$L49/$AI49 -> 0 | O49: =$N49/$AI49 -> 0 | P49: 426.49 | Q49: =$P49/$AI49 -> 0.0027128864 | R49: 3007.258 | S49: =$R49/$AI49 -> 0.019129052 | U49: =$T49/$AI49 -> 0 | W49: =$V49/$AI49 -> 0 | X49: 163.27 | Y49: =$X49/$AI49 -> 0.0010385542 | Z49: 256.729 | AA49: =$Z49/$AI49 -> 0.0016330433 | AB49: 11267.249 | AC49: =$AB49/AI49 -> 0.071670536 | AD49: 82692.782 | AE49: =$AD49/$AI49 -> 0.52600559 | AF49: -138038.53 | AG49: -19170.415 | AH49: =SUM(AF49,AG49) -> -157208.94 | AI49: =((AF49+AG49)*-1) -> 157208.94 | AJ49: =AI49/($AI$224) -> 0.011996969 | AK49: =AJ49*($G$260+$G$313-$B$406) -> 21190.537 | AL49: 52989.882 | AM49: =AL49/AL$224 -> 0.011246162 | AN49: =(AM49*$B$406) -> 15290.113 | AO49: =AN49+AK49 -> 36480.65 | AP49: =$AO49/$AI49 -> 0.232052 | AQ49: =AB49+AD49+AH49 -> -63248.91 | AR49: =AQ49+AO49 -> -26768.26 | AS49: =AR49/AI49 -> -0.17027187
A50: [ CJP ] - CINCO DE JULIO | B50: 0 | C50: =$B50/$AI50 -> 0 | D50: 1200 | E50: =$D50/$AI50 -> 0.021309274 | F50: 0 | G50: =$F50/$AI50 -> 0 | H50: 0 | I50: =$H50/$AI50 -> 0 | J50: 3298.207 | K50: =$J50/$AI50 -> 0.058568664 | M50: =$L50/$AI50 -> 0 | O50: =$N50/$AI50 -> 0 | P50: 88.18 | Q50: =$P50/$AI50 -> 0.0015658765 | R50: 99.373 | S50: =$R50/$AI50 -> 0.0017646387 | U50: =$T50/$AI50 -> 0 | W50: =$V50/$AI50 -> 0 | X50: 300.26 | Y50: =$X50/$AI50 -> 0.0053319355 | Z50: 57.969 | AA50: =$Z50/$AI50 -> 0.0010293978 | AB50: 5043.989 | AC50: =$AB50/AI50 -> 0.089569787 | AD50: 27746.663 | AE50: =$AD50/$AI50 -> 0.49271771 | AF50: -49919.49 | AG50: -6394.019 | AH50: =SUM(AF50,AG50) -> -56313.509 | AI50: =((AF50+AG50)*-1) -> 56313.509 | AJ50: =AI50/($AI$224) -> 0.0042974109 | AK50: =AJ50*($G$260+$G$313-$B$406) -> 7590.621 | AL50: 18650.024 | AM50: =AL50/AL$224 -> 0.0039581366 | AN50: =(AM50*$B$406) -> 5381.4231 | AO50: =AN50+AK50 -> 12972.044 | AP50: =$AO50/$AI50 -> 0.23035404 | AQ50: =AB50+AD50+AH50 -> -23522.857 | AR50: =AQ50+AO50 -> -10550.813 | AS50: =AR50/AI50 -> -0.18735847
A51: [ CLB ] - CALABOZO | B51: 0 | C51: =$B51/$AI51 -> 0 | D51: 1108.01 | E51: =$D51/$AI51 -> 0.011104122 | F51: 0 | G51: =$F51/$AI51 -> 0 | H51: 0 | I51: =$H51/$AI51 -> 0 | J51: 5141.263 | K51: =$J51/$AI51 -> 0.051524094 | M51: =$L51/$AI51 -> 0 | O51: =$N51/$AI51 -> 0 | P51: 77.05 | Q51: =$P51/$AI51 -> 0.00077217047 | R51: 941.142 | S51: =$R51/$AI51 -> 0.0094318242 | U51: =$T51/$AI51 -> 0 | W51: =$V51/$AI51 -> 0 | X51: 194.31 | Y51: =$X51/$AI51 -> 0.0019473127 | Z51: 147.985 | AA51: =$Z51/$AI51 -> 0.0014830584 | AB51: 7609.76 | AC51: =$AB51/AI51 -> 0.076262582 | AD51: 47243.148 | AE51: =$AD51/$AI51 -> 0.47345573 | AF51: -87100.305 | AG51: -12683.361 | AH51: =SUM(AF51,AG51) -> -99783.666 | AI51: =((AF51+AG51)*-1) -> 99783.666 | AJ51: =AI51/($AI$224) -> 0.0076147166 | AK51: =AJ51*($G$260+$G$313-$B$406) -> 13450.058 | AL51: 34385.264 | AM51: =AL51/AL$224 -> 0.0072976619 | AN51: =(AM51*$B$406) -> 9921.7915 | AO51: =AN51+AK51 -> 23371.85 | AP51: =$AO51/$AI51 -> 0.23422521 | AQ51: =AB51+AD51+AH51 -> -44930.758 | AR51: =AQ51+AO51 -> -21558.908 | AS51: =AR51/AI51 -> -0.21605648
A52: [ CLL ] - CALLAO | B52: 0 | C52: =$B52/$AI52 -> 0 | D52: 3500 | E52: =$D52/$AI52 -> 0.064240394 | F52: 0 | G52: =$F52/$AI52 -> 0 | H52: 47.2 | I52: =$H52/$AI52 -> 0.0008663276 | J52: 1571.091 | K52: =$J52/$AI52 -> 0.02883643 | M52: =$L52/$AI52 -> 0 | O52: =$N52/$AI52 -> 0 | P52: 40 | Q52: =$P52/$AI52 -> 0.00073417593 | R52: 6061.761 | S52: =$R52/$AI52 -> 0.11125998 | U52: =$T52/$AI52 -> 0 | W52: =$V52/$AI52 -> 0 | X52: 100 | Y52: =$X52/$AI52 -> 0.0018354398 | Z52: 695.326 | AA52: =$Z52/$AI52 -> 0.01276229 | AB52: 12015.378 | AC52: =$AB52/AI52 -> 0.22053503 | AD52: 30474.522 | AE52: =$AD52/$AI52 -> 0.55934151 | AF52: -47645.74 | AG52: -6837.114 | AH52: =SUM(AF52,AG52) -> -54482.854 | AI52: =((AF52+AG52)*-1) -> 54482.854 | AJ52: =AI52/($AI$224) -> 0.0041577095 | AK52: =AJ52*($G$260+$G$313-$B$406) -> 7343.863 | AL52: 13155.669 | AM52: =AL52/AL$224 -> 0.0027920571 | AN52: =(AM52*$B$406) -> 3796.0389 | AO52: =AN52+AK52 -> 11139.902 | AP52: =$AO52/$AI52 -> 0.2044662 | AQ52: =AB52+AD52+AH52 -> -11992.954 | AR52: =AQ52+AO52 -> -853.05206 | AS52: =AR52/AI52 -> -0.015657257
A53: [ CLP ] - CATIA LIFE PHONE | B53: 0 | C53: =$B53/$AI53 -> 0 | D53: 2000 | E53: =$D53/$AI53 -> 0.014884896 | F53: 0 | G53: =$F53/$AI53 -> 0 | H53: 0 | I53: =$H53/$AI53 -> 0 | J53: 8208.958 | K53: =$J53/$AI53 -> 0.061094742 | M53: =$L53/$AI53 -> 0 | O53: =$N53/$AI53 -> 0 | P53: 183.27 | Q53: =$P53/$AI53 -> 0.0013639774 | R53: 4397.03 | S53: =$R53/$AI53 -> 0.032724666 | U53: =$T53/$AI53 -> 0 | W53: =$V53/$AI53 -> 0 | X53: 118.17 | Y53: =$X53/$AI53 -> 0.00087947406 | Z53: 676.568 | AA53: =$Z53/$AI53 -> 0.005035322 | AB53: 15583.996 | AC53: =$AB53/AI53 -> 0.11598308 | AD53: 71880.752 | AE53: =$AD53/$AI53 -> 0.53496875 | AF53: -117329.44 | AG53: -17034.954 | AH53: =SUM(AF53,AG53) -> -134364.39 | AI53: =((AF53+AG53)*-1) -> 134364.39 | AJ53: =AI53/($AI$224) -> 0.01025365 | AK53: =AJ53*($G$260+$G$313-$B$406) -> 18111.271 | AL53: 56254.537 | AM53: =AL53/AL$224 -> 0.011939027 | AN53: =(AM53*$B$406) -> 16232.122 | AO53: =AN53+AK53 -> 34343.392 | AP53: =$AO53/$AI53 -> 0.2555989 | AQ53: =AB53+AD53+AH53 -> -46899.647 | AR53: =AQ53+AO53 -> -12556.255 | AS53: =AR53/AI53 -> -0.093449272
A54: [ CLT ] - COLONIA TOVAR | B54: -676.166 | C54: =$B54/$AI54 -> -0.013315169 | D54: 2000 | E54: =$D54/$AI54 -> 0.03938432 | F54: 0 | G54: =$F54/$AI54 -> 0 | H54: 0 | I54: =$H54/$AI54 -> 0 | J54: 2443.835 | K54: =$J54/$AI54 -> 0.04812439 | M54: =$L54/$AI54 -> 0 | N54: 120 | O54: =$N54/$AI54 -> 0.0023630592 | P54: 124.14 | Q54: =$P54/$AI54 -> 0.0024445847 | R54: 12321.671 | S54: =$R54/$AI54 -> 0.24264032 | U54: =$T54/$AI54 -> 0 | W54: =$V54/$AI54 -> 0 | X54: 126.76 | Y54: =$X54/$AI54 -> 0.0024961782 | Z54: 267.447 | AA54: =$Z54/$AI54 -> 0.0052666091 | AB54: 16727.687 | AC54: =$AB54/AI54 -> 0.32940429 | AD54: 25911.399 | AE54: =$AD54/$AI54 -> 0.51025141 | AF54: -44452.949 | AG54: -6328.682 | AH54: =SUM(AF54,AG54) -> -50781.631 | AI54: =((AF54+AG54)*-1) -> 50781.631 | AJ54: =AI54/($AI$224) -> 0.0038752608 | AK54: =AJ54*($G$260+$G$313-$B$406) -> 6844.9671 | AL54: 22182.917 | AM54: =AL54/AL$224 -> 0.0047079302 | AN54: =(AM54*$B$406) -> 6400.8313 | AO54: =AN54+AK54 -> 13245.798 | AP54: =$AO54/$AI54 -> 0.26083838 | AQ54: =AB54+AD54+AH54 -> -8142.545 | AR54: =AQ54+AO54 -> 5103.2534 | AS54: =AR54/AI54 -> 0.10049408
A55: [ CMC ] - CUA | B55: 0 | C55: =$B55/$AI55 -> 0 | D55: 1650 | E55: =$D55/$AI55 -> 0.016164842 | F55: 10.22 | G55: =$F55/$AI55 -> 0.00010012405 | H55: 0 | I55: =$H55/$AI55 -> 0 | J55: 5426.315 | K55: =$J55/$AI55 -> 0.053160924 | M55: =$L55/$AI55 -> 0 | N55: 129.52 | O55: =$N55/$AI55 -> 0.0012688911 | P55: 136.61 | Q55: =$P55/$AI55 -> 0.0013383509 | R55: 485.405 | S55: =$R55/$AI55 -> 0.0047554516 | U55: =$T55/$AI55 -> 0 | W55: =$V55/$AI55 -> 0 | X55: 348.94 | Y55: =$X55/$AI55 -> 0.0034185212 | Z55: 82.644 | AA55: =$Z55/$AI55 -> 0.00080965284 | AB55: 8269.654 | AC55: =$AB55/AI55 -> 0.081016757 | AD55: 48175.151 | AE55: =$AD55/$AI55 -> 0.47196588 | AF55: -90917.192 | AG55: -11156.185 | AH55: =SUM(AF55,AG55) -> -102073.38 | AI55: =((AF55+AG55)*-1) -> 102073.38 | AJ55: =AI55/($AI$224) -> 0.0077894496 | AK55: =AJ55*($G$260+$G$313-$B$406) -> 13758.694 | AL55: 36908.133 | AM55: =AL55/AL$224 -> 0.0078330959 | AN55: =(AM55*$B$406) -> 10649.76 | AO55: =AN55+AK55 -> 24408.453 | AP55: =$AO55/$AI55 -> 0.23912654 | AQ55: =AB55+AD55+AH55 -> -45628.572 | AR55: =AQ55+AO55 -> -21220.119 | AS55: =AR55/AI55 -> -0.20789083
A56: [ CMO ] - COMERCIO | B56: 0 | C56: =$B56/$AI56 -> 0 | D56: 0 | E56: =$D56/$AI56 -> 0 | F56: 212.51 | G56: =$F56/$AI56 -> 0.0030733555 | H56: 0 | I56: =$H56/$AI56 -> 0 | J56: 8750.818 | K56: =$J56/$AI56 -> 0.12655581 | M56: =$L56/$AI56 -> 0 | O56: =$N56/$AI56 -> 0 | P56: 79.68 | Q56: =$P56/$AI56 -> 0.0011523456 | R56: 2760.443 | S56: =$R56/$AI56 -> 0.039921992 | U56: =$T56/$AI56 -> 0 | W56: =$V56/$AI56 -> 0 | X56: 950.14 | Y56: =$X56/$AI56 -> 0.013741085 | Z56: 29.535 | AA56: =$Z56/$AI56 -> 0.00042714015 | AB56: 12783.126 | AC56: =$AB56/AI56 -> 0.18487172 | AD56: 35442.021 | AE56: =$AD56/$AI56 -> 0.51256849 | AF56: -60112.355 | AG56: -9033.568 | AH56: =SUM(AF56,AG56) -> -69145.923 | AI56: =((AF56+AG56)*-1) -> 69145.923 | AJ56: =AI56/($AI$224) -> 0.0052766813 | AK56: =AJ56*($G$260+$G$313-$B$406) -> 9320.3301 | AL56: 18294.676 | AM56: =AL56/AL$224 -> 0.0038827203 | AN56: =(AM56*$B$406) -> 5278.8882 | AO56: =AN56+AK56 -> 14599.218 | AP56: =$AO56/$AI56 -> 0.21113636 | AQ56: =AB56+AD56+AH56 -> -20920.776 | AR56: =AQ56+AO56 -> -6321.5576 | AS56: =AR56/AI56 -> -0.091423433
A57: [ CNA ] - CUMANACOA | B57: 0 | C57: =$B57/$AI57 -> 0 | D57: 940 | E57: =$D57/$AI57 -> 0.013517421 | F57: 32.36 | G57: =$F57/$AI57 -> 0.0004653444 | H57: 0 | I57: =$H57/$AI57 -> 0 | J57: 3520.317 | K57: =$J57/$AI57 -> 0.050622985 | M57: =$L57/$AI57 -> 0 | N57: 80 | O57: =$N57/$AI57 -> 0.0011504188 | P57: 201.86 | Q57: =$P57/$AI57 -> 0.0029027942 | R57: 171.784 | S57: =$R57/$AI57 -> 0.0024702942 | U57: =$T57/$AI57 -> 0 | W57: =$V57/$AI57 -> 0 | X57: 92.3 | Y57: =$X57/$AI57 -> 0.0013272957 | Z57: 46.681 | AA57: =$Z57/$AI57 -> 0.00067128374 | AB57: 5085.302 | AC57: =$AB57/AI57 -> 0.073127837 | AD57: 35552.533 | AE57: =$AD57/$AI57 -> 0.51125377 | AF57: -61465.546 | AG57: -8074.348 | AH57: =SUM(AF57,AG57) -> -69539.894 | AI57: =((AF57+AG57)*-1) -> 69539.894 | AJ57: =AI57/($AI$224) -> 0.0053067461 | AK57: =AJ57*($G$260+$G$313-$B$406) -> 9373.4343 | AL57: 27408.169 | AM57: =AL57/AL$224 -> 0.0058168973 | AN57: =(AM57*$B$406) -> 7908.5663 | AO57: =AN57+AK57 -> 17282.001 | AP57: =$AO57/$AI57 -> 0.24851923 | AQ57: =AB57+AD57+AH57 -> -28902.059 | AR57: =AQ57+AO57 -> -11620.058 | AS57: =AR57/AI57 -> -0.16709917
A58: [ COD ] - COSMOS SHOP | B58: 0 | C58: =$B58/$AI58 -> 0 | D58: 0 | E58: =$D58/$AI58 -> 0 | F58: 14.95 | G58: =$F58/$AI58 -> 9.6229266e-05 | H58: 0 | I58: =$H58/$AI58 -> 0 | J58: 17860.266 | K58: =$J58/$AI58 -> 0.11496189 | M58: =$L58/$AI58 -> 0 | O58: =$N58/$AI58 -> 0 | P58: 680.05 | Q58: =$P58/$AI58 -> 0.0043773052 | R58: 950.41 | S58: =$R58/$AI58 -> 0.0061175422 | U58: =$T58/$AI58 -> 0 | W58: =$V58/$AI58 -> 0 | X58: 934.84 | Y58: =$X58/$AI58 -> 0.0060173222 | Z58: 794.221 | AA58: =$Z58/$AI58 -> 0.0051121942 | AB58: 21234.737 | AC58: =$AB58/AI58 -> 0.13668248 | AD58: 72373.637 | AE58: =$AD58/$AI58 -> 0.4658503 | AF58: -138029.42 | AG58: -17328.719 | AH58: =SUM(AF58,AG58) -> -155358.14 | AI58: =((AF58+AG58)*-1) -> 155358.14 | AJ58: =AI58/($AI$224) -> 0.01185573 | AK58: =AJ58*($G$260+$G$313-$B$406) -> 20941.064 | AL58: 58393.584 | AM58: =AL58/AL$224 -> 0.012393002 | AN58: =(AM58*$B$406) -> 16849.339 | AO58: =AN58+AK58 -> 37790.403 | AP58: =$AO58/$AI58 -> 0.243247 | AQ58: =AB58+AD58+AH58 -> -61749.769 | AR58: =AQ58+AO58 -> -23959.366 | AS58: =AR58/AI58 -> -0.15422022
A59: [ COE ] - SAN CARLOS | B59: 0 | C59: =$B59/$AI59 -> 0 | D59: 1500 | E59: =$D59/$AI59 -> 0.011705575 | F59: 399.81 | G59: =$F59/$AI59 -> 0.0031200039 | H59: 0 | I59: =$H59/$AI59 -> 0 | J59: 5734.116 | K59: =$J59/$AI59 -> 0.044747416 | M59: =$L59/$AI59 -> 0 | O59: =$N59/$AI59 -> 0 | P59: 95.58 | Q59: =$P59/$AI59 -> 0.00074587922 | R59: 455.501 | S59: =$R59/$AI59 -> 0.0035546007 | U59: =$T59/$AI59 -> 0 | W59: =$V59/$AI59 -> 0 | X59: 271.4 | Y59: =$X59/$AI59 -> 0.0021179287 | Z59: 288.391 | AA59: =$Z59/$AI59 -> 0.0022505216 | AB59: 8744.798 | AC59: =$AB59/AI59 -> 0.068241924 | AD59: 66640.882 | AE59: =$AD59/$AI59 -> 0.52004655 | AF59: -112198.21 | AG59: -15945.859 | AH59: =SUM(AF59,AG59) -> -128144.07 | AI59: =((AF59+AG59)*-1) -> 128144.07 | AJ59: =AI59/($AI$224) -> 0.009778963 | AK59: =AJ59*($G$260+$G$313-$B$406) -> 17272.819 | AL59: 55876.535 | AM59: =AL59/AL$224 -> 0.011858803 | AN59: =(AM59*$B$406) -> 16123.05 | AO59: =AN59+AK59 -> 33395.869 | AP59: =$AO59/$AI59 -> 0.2606119 | AQ59: =AB59+AD59+AH59 -> -52758.391 | AR59: =AQ59+AO59 -> -19362.522 | AS59: =AR59/AI59 -> -0.15109963
A60: [ COR ] - CORO | B60: 0 | C60: =$B60/$AI60 -> 0 | D60: 500 | E60: =$D60/$AI60 -> 0.0032928399 | F60: 15 | G60: =$F60/$AI60 -> 9.8785196e-05 | H60: 0 | I60: =$H60/$AI60 -> 0 | J60: 4918.521 | K60: =$J60/$AI60 -> 0.032391804 | M60: =$L60/$AI60 -> 0 | N60: 16.1 | O60: =$N60/$AI60 -> 0.00010602944 | P60: 855.8 | Q60: =$P60/$AI60 -> 0.0056360247 | R60: 112.051 | S60: =$R60/$AI60 -> 0.000737932 | U60: =$T60/$AI60 -> 0 | W60: =$V60/$AI60 -> 0 | X60: 253.2 | Y60: =$X60/$AI60 -> 0.0016674941 | Z60: 104.182 | AA60: =$Z60/$AI60 -> 0.00068610929 | AB60: 6774.854 | AC60: =$AB60/AI60 -> 0.044617019 | AD60: 92403.5 | AE60: =$AD60/$AI60 -> 0.60853986 | AF60: -135755.57 | AG60: -16089.04 | AH60: =SUM(AF60,AG60) -> -151844.61 | AI60: =((AF60+AG60)*-1) -> 151844.61 | AJ60: =AI60/($AI$224) -> 0.011587605 | AK60: =AJ60*($G$260+$G$313-$B$406) -> 20467.467 | AL60: 49508.298 | AM60: =AL60/AL$224 -> 0.010507257 | AN60: =(AM60*$B$406) -> 14285.509 | AO60: =AN60+AK60 -> 34752.977 | AP60: =$AO60/$AI60 -> 0.22887198 | AQ60: =AB60+AD60+AH60 -> -52666.26 | AR60: =AQ60+AO60 -> -17913.283 | AS60: =AR60/AI60 -> -0.11797115
A61: [ CPN ] - CARUPANO | B61: 0 | C61: =$B61/$AI61 -> 0 | D61: 1700 | E61: =$D61/$AI61 -> 0.011341633 | F61: 0 | G61: =$F61/$AI61 -> 0 | H61: 0 | I61: =$H61/$AI61 -> 0 | J61: 5507.774 | K61: =$J61/$AI61 -> 0.036745384 | M61: =$L61/$AI61 -> 0 | O61: =$N61/$AI61 -> 0 | P61: 331.92 | Q61: =$P61/$AI61 -> 0.0022144205 | R61: 16.923 | S61: =$R61/$AI61 -> 0.00011290262 | U61: =$T61/$AI61 -> 0 | W61: =$V61/$AI61 -> 0 | X61: 277.93 | Y61: =$X61/$AI61 -> 0.0018542236 | Z61: 49.828 | AA61: =$Z61/$AI61 -> 0.00033242994 | AB61: 7884.375 | AC61: =$AB61/AI61 -> 0.052600993 | AD61: 84520.888 | AE61: =$AD61/$AI61 -> 0.56388524 | AF61: -133036.48 | AG61: -16853.753 | AH61: =SUM(AF61,AG61) -> -149890.23 | AI61: =((AF61+AG61)*-1) -> 149890.23 | AJ61: =AI61/($AI$224) -> 0.011438461 | AK61: =AJ61*($G$260+$G$313-$B$406) -> 20204.032 | AL61: 50936.7 | AM61: =AL61/AL$224 -> 0.01081041 | AN61: =(AM61*$B$406) -> 14697.672 | AO61: =AN61+AK61 -> 34901.703 | AP61: =$AO61/$AI61 -> 0.23284842 | AQ61: =AB61+AD61+AH61 -> -57484.967 | AR61: =AQ61+AO61 -> -22583.264 | AS61: =AR61/AI61 -> -0.15066535
A62: [ CRN ] - CLARINES | B62: 0 | C62: =$B62/$AI62 -> 0 | D62: 700 | E62: =$D62/$AI62 -> 0.019701648 | F62: 0 | G62: =$F62/$AI62 -> 0 | H62: 0 | I62: =$H62/$AI62 -> 0 | J62: 3558.126 | K62: =$J62/$AI62 -> 0.10014421 | M62: =$L62/$AI62 -> 0 | O62: =$N62/$AI62 -> 0 | P62: 43.61 | Q62: =$P62/$AI62 -> 0.0012274127 | R62: 227.978 | S62: =$R62/$AI62 -> 0.0064164891 | U62: =$T62/$AI62 -> 0 | W62: =$V62/$AI62 -> 0 | X62: 80 | Y62: =$X62/$AI62 -> 0.002251617 | Z62: 146.855 | AA62: =$Z62/$AI62 -> 0.0041332651 | AB62: 4756.569 | AC62: =$AB62/AI62 -> 0.13387464 | AD62: 17531.842 | AE62: =$AD62/$AI62 -> 0.49343741 | AF62: -31157.852 | AG62: -4372.17 | AH62: =SUM(AF62,AG62) -> -35530.022 | AI62: =((AF62+AG62)*-1) -> 35530.022 | AJ62: =AI62/($AI$224) -> 0.0027113761 | AK62: =AJ62*($G$260+$G$313-$B$406) -> 4789.1693 | AL62: 14105.73 | AM62: =AL62/AL$224 -> 0.0029936907 | AN62: =(AM62*$B$406) -> 4070.177 | AO62: =AN62+AK62 -> 8859.3463 | AP62: =$AO62/$AI62 -> 0.24934818 | AQ62: =AB62+AD62+AH62 -> -13241.611 | AR62: =AQ62+AO62 -> -4382.2647 | AS62: =AR62/AI62 -> -0.12333977
A63: [ CRP ] - CARIPE | B63: 0 | C63: =$B63/$AI63 -> 0 | D63: 600 | E63: =$D63/$AI63 -> 0.0085456147 | F63: 25 | G63: =$F63/$AI63 -> 0.00035606728 | H63: 0 | I63: =$H63/$AI63 -> 0 | J63: 3115.807 | K63: =$J63/$AI63 -> 0.044377477 | M63: =$L63/$AI63 -> 0 | O63: =$N63/$AI63 -> 0 | P63: 41 | Q63: =$P63/$AI63 -> 0.00058395034 | R63: 37.937 | S63: =$R63/$AI63 -> 0.00054032498 | U63: =$T63/$AI63 -> 0 | W63: =$V63/$AI63 -> 0 | X63: 116.88 | Y63: =$X63/$AI63 -> 0.0016646857 | Z63: 35.986 | AA63: =$Z63/$AI63 -> 0.00051253748 | AB63: 3972.61 | AC63: =$AB63/AI63 -> 0.056580657 | AD63: 32713.817 | AE63: =$AD63/$AI63 -> 0.46593279 | AF63: -61382.255 | AG63: -8829.195 | AH63: =SUM(AF63,AG63) -> -70211.45 | AI63: =((AF63+AG63)*-1) -> 70211.45 | AJ63: =AI63/($AI$224) -> 0.0053579941 | AK63: =AJ63*($G$260+$G$313-$B$406) -> 9463.9548 | AL63: 27229.345 | AM63: =AL63/AL$224 -> 0.0057789451 | AN63: =(AM63*$B$406) -> 7856.9671 | AO63: =AN63+AK63 -> 17320.922 | AP63: =$AO63/$AI63 -> 0.24669654 | AQ63: =AB63+AD63+AH63 -> -33525.023 | AR63: =AQ63+AO63 -> -16204.101 | AS63: =AR63/AI63 -> -0.23079001
A64: [ CRR ] - CARORA | B64: 0 | C64: =$B64/$AI64 -> 0 | D64: 1489.92 | E64: =$D64/$AI64 -> 0.013307953 | F64: 0 | G64: =$F64/$AI64 -> 0 | H64: 0 | I64: =$H64/$AI64 -> 0 | J64: 3827.012 | K64: =$J64/$AI64 -> 0.03418284 | M64: =$L64/$AI64 -> 0 | N64: 24.77 | O64: =$N64/$AI64 -> 0.00022124544 | P64: 613.49 | Q64: =$P64/$AI64 -> 0.0054796877 | R64: 96.063 | S64: =$R64/$AI64 -> 0.00085803394 | T64: 47.37 | U64: =$T64/$AI64 -> 0.00042310846 | W64: =$V64/$AI64 -> 0 | X64: 338.57 | Y64: =$X64/$AI64 -> 0.0030241045 | Z64: 370.834 | AA64: =$Z64/$AI64 -> 0.0033122863 | AB64: 6808.029 | AC64: =$AB64/AI64 -> 0.06080926 | AD64: 57872.628 | AE64: =$AD64/$AI64 -> 0.51691784 | AF64: -98508.114 | AG64: -13448.996 | AH64: =SUM(AF64,AG64) -> -111957.11 | AI64: =((AF64+AG64)*-1) -> 111957.11 | AJ64: =AI64/($AI$224) -> 0.0085436995 | AK64: =AJ64*($G$260+$G$313-$B$406) -> 15090.944 | AL64: 36927.909 | AM64: =AL64/AL$224 -> 0.007837293 | AN64: =(AM64*$B$406) -> 10655.466 | AO64: =AN64+AK64 -> 25746.41 | AP64: =$AO64/$AI64 -> 0.22996672 | AQ64: =AB64+AD64+AH64 -> -47276.453 | AR64: =AQ64+AO64 -> -21530.043 | AS64: =AR64/AI64 -> -0.19230617
A65: [ CRT ] - CARIPITO | B65: 0 | C65: =$B65/$AI65 -> 0 | D65: 500 | E65: =$D65/$AI65 -> 0.0086813682 | F65: 0 | G65: =$F65/$AI65 -> 0 | H65: 0 | I65: =$H65/$AI65 -> 0 | J65: 3141.562 | K65: =$J65/$AI65 -> 0.054546113 | M65: =$L65/$AI65 -> 0 | O65: =$N65/$AI65 -> 0 | P65: 111.74 | Q65: =$P65/$AI65 -> 0.0019401122 | R65: 420.242 | S65: =$R65/$AI65 -> 0.0072965511 | U65: =$T65/$AI65 -> 0 | W65: =$V65/$AI65 -> 0 | X65: 52.76 | Y65: =$X65/$AI65 -> 0.00091605798 | Z65: 19.553 | AA65: =$Z65/$AI65 -> 0.00033949359 | AB65: 4245.857 | AC65: =$AB65/AI65 -> 0.073719696 | AD65: 27743.761 | AE65: =$AD65/$AI65 -> 0.48170761 | AF65: -50311.75 | AG65: -7282.858 | AH65: =SUM(AF65,AG65) -> -57594.608 | AI65: =((AF65+AG65)*-1) -> 57594.608 | AJ65: =AI65/($AI$224) -> 0.0043951744 | AK65: =AJ65*($G$260+$G$313-$B$406) -> 7763.3031 | AL65: 21052.699 | AM65: =AL65/AL$224 -> 0.0044680616 | AN65: =(AM65*$B$406) -> 6074.7094 | AO65: =AN65+AK65 -> 13838.013 | AP65: =$AO65/$AI65 -> 0.24026577 | AQ65: =AB65+AD65+AH65 -> -25604.99 | AR65: =AQ65+AO65 -> -11766.977 | AS65: =AR65/AI65 -> -0.20430693
A66: [ CSZ ] - CAJA SECA ZULIA | B66: 0 | C66: =$B66/$AI66 -> 0 | D66: 550 | E66: =$D66/$AI66 -> 0.013537251 | F66: 254.79 | G66: =$F66/$AI66 -> 0.006271193 | H66: 0 | I66: =$H66/$AI66 -> 0 | J66: 3581.56 | K66: =$J66/$AI66 -> 0.088153594 | M66: =$L66/$AI66 -> 0 | O66: =$N66/$AI66 -> 0 | P66: 95.5 | Q66: =$P66/$AI66 -> 0.002350559 | R66: 1310.586 | S66: =$R66/$AI66 -> 0.032257694 | U66: =$T66/$AI66 -> 0 | W66: =$V66/$AI66 -> 0 | X66: 217.25 | Y66: =$X66/$AI66 -> 0.0053472141 | Z66: 355.014 | AA66: =$Z66/$AI66 -> 0.0087380247 | AB66: 6364.7 | AC66: =$AB66/AI66 -> 0.15665553 | AD66: 20296.178 | AE66: =$AD66/$AI66 -> 0.49955355 | AF66: -35916.42 | AG66: -4712.213 | AH66: =SUM(AF66,AG66) -> -40628.633 | AI66: =((AF66+AG66)*-1) -> 40628.633 | AJ66: =AI66/($AI$224) -> 0.0031004626 | AK66: =AJ66*($G$260+$G$313-$B$406) -> 5476.4223 | AL66: 17511.119 | AM66: =AL66/AL$224 -> 0.0037164241 | AN66: =(AM66*$B$406) -> 5052.7945 | AO66: =AN66+AK66 -> 10529.217 | AP66: =$AO66/$AI66 -> 0.25915754 | AQ66: =AB66+AD66+AH66 -> -13967.755 | AR66: =AQ66+AO66 -> -3438.5383 | AS66: =AR66/AI66 -> -0.084633373
A67: [ CTA ] - CANTAURA | B67: 0 | C67: =$B67/$AI67 -> 0 | D67: 377.97 | E67: =$D67/$AI67 -> 0.0075142836 | F67: 0 | G67: =$F67/$AI67 -> 0 | H67: 0 | I67: =$H67/$AI67 -> 0 | J67: 3222.941 | K67: =$J67/$AI67 -> 0.064074114 | M67: =$L67/$AI67 -> 0 | O67: =$N67/$AI67 -> 0 | P67: 64.03 | Q67: =$P67/$AI67 -> 0.0012729571 | R67: 553.338 | S67: =$R67/$AI67 -> 0.011000711 | U67: =$T67/$AI67 -> 0 | W67: =$V67/$AI67 -> 0 | X67: 77.02 | Y67: =$X67/$AI67 -> 0.0015312065 | Z67: 110.872 | AA67: =$Z67/$AI67 -> 0.0022042058 | AB67: 4406.171 | AC67: =$AB67/AI67 -> 0.087597478 | AD67: 24390.819 | AE67: =$AD67/$AI67 -> 0.48490497 | AF67: -44162.941 | AG67: -6137.263 | AH67: =SUM(AF67,AG67) -> -50300.204 | AI67: =((AF67+AG67)*-1) -> 50300.204 | AJ67: =AI67/($AI$224) -> 0.003838522 | AK67: =AJ67*($G$260+$G$313-$B$406) -> 6780.0745 | AL67: 18723.707 | AM67: =AL67/AL$224 -> 0.0039737743 | AN67: =(AM67*$B$406) -> 5402.6839 | AO67: =AN67+AK67 -> 12182.758 | AP67: =$AO67/$AI67 -> 0.24220097 | AQ67: =AB67+AD67+AH67 -> -21503.214 | AR67: =AQ67+AO67 -> -9320.4556 | AS67: =AR67/AI67 -> -0.18529658
A68: [ CTD ] - CITY 2 | B68: 0 | C68: =$B68/$AI68 -> 0 | D68: 1177.25 | E68: =$D68/$AI68 -> 0.041765186 | F68: 0 | G68: =$F68/$AI68 -> 0 | H68: 0 | I68: =$H68/$AI68 -> 0 | J68: 1385.428 | K68: =$J68/$AI68 -> 0.049150697 | M68: =$L68/$AI68 -> 0 | O68: =$N68/$AI68 -> 0 | P68: 65.79 | Q68: =$P68/$AI68 -> 0.0023340256 | R68: 1.846 | S68: =$R68/$AI68 -> 6.5490366e-05 | U68: =$T68/$AI68 -> 0 | W68: =$V68/$AI68 -> 0 | X68: 482.84 | Y68: =$X68/$AI68 -> 0.017129669 | Z68: 392.909 | AA68: =$Z68/$AI68 -> 0.013939195 | AB68: 3506.063 | AC68: =$AB68/AI68 -> 0.12438426 | AD68: 15333.599 | AE68: =$AD68/$AI68 -> 0.54398863 | AF68: -24526.552 | AG68: -3660.8 | AH68: =SUM(AF68,AG68) -> -28187.352 | AI68: =((AF68+AG68)*-1) -> 28187.352 | AJ68: =AI68/($AI$224) -> 0.0021510404 | AK68: =AJ68*($G$260+$G$313-$B$406) -> 3799.4348 | AL68: 8375.3104 | AM68: =AL68/AL$224 -> 0.0017775109 | AN68: =(AM68*$B$406) -> 2416.6772 | AO68: =AN68+AK68 -> 6216.112 | AP68: =$AO68/$AI68 -> 0.22052841 | AQ68: =AB68+AD68+AH68 -> -9347.69 | AR68: =AQ68+AO68 -> -3131.578 | AS68: =AR68/AI68 -> -0.11109869
A69: [ CTL ] - CARTANAL | B69: 0 | C69: =$B69/$AI69 -> 0 | D69: 1200 | E69: =$D69/$AI69 -> 0.012452496 | F69: 0 | G69: =$F69/$AI69 -> 0 | H69: 47.2 | I69: =$H69/$AI69 -> 0.00048979817 | J69: 3885.608 | K69: =$J69/$AI69 -> 0.040321264 | M69: =$L69/$AI69 -> 0 | O69: =$N69/$AI69 -> 0 | P69: 102.74 | Q69: =$P69/$AI69 -> 0.0010661412 | R69: 626.581 | S69: =$R69/$AI69 -> 0.0065020811 | U69: =$T69/$AI69 -> 0 | W69: =$V69/$AI69 -> 0 | X69: 132.189 | Y69: =$X69/$AI69 -> 0.0013717358 | Z69: 77.053 | AA69: =$Z69/$AI69 -> 0.00079958513 | AB69: 6071.371 | AC69: =$AB69/AI69 -> 0.063003102 | AD69: 48145.639 | AE69: =$AD69/$AI69 -> 0.49961114 | AF69: -85888.407 | AG69: -10477.817 | AH69: =SUM(AF69,AG69) -> -96366.224 | AI69: =((AF69+AG69)*-1) -> 96366.224 | AJ69: =AI69/($AI$224) -> 0.0073539239 | AK69: =AJ69*($G$260+$G$313-$B$406) -> 12989.414 | AL69: 32014.716 | AM69: =AL69/AL$224 -> 0.0067945551 | AN69: =(AM69*$B$406) -> 9237.7751 | AO69: =AN69+AK69 -> 22227.189 | AP69: =$AO69/$AI69 -> 0.23065332 | AQ69: =AB69+AD69+AH69 -> -42149.214 | AR69: =AQ69+AO69 -> -19922.025 | AS69: =AR69/AI69 -> -0.20673244
A70: [ CTM ] - CATIA LA MAR | B70: 0 | C70: =$B70/$AI70 -> 0 | D70: 2000 | E70: =$D70/$AI70 -> 291.54519 | F70: 0 | G70: =$F70/$AI70 -> 0 | H70: 0 | I70: =$H70/$AI70 -> 0 | J70: 3915.898 | K70: =$J70/$AI70 -> 570.83061 | M70: =$L70/$AI70 -> 0 | O70: =$N70/$AI70 -> 0 | P70: 174.59 | Q70: =$P70/$AI70 -> 25.450437 | R70: 464.833 | S70: =$R70/$AI70 -> 67.759913 | U70: =$T70/$AI70 -> 0 | W70: =$V70/$AI70 -> 0 | X70: 82.88 | Y70: =$X70/$AI70 -> 12.081633 | Z70: 57.789 | AA70: =$Z70/$AI70 -> 8.4240525 | AB70: 6695.99 | AC70: =$AB70/AI70 -> 976.09184 | AD70: 13458.454 | AE70: =$AD70/$AI70 -> 1961.8738 | AF70: 0 | AG70: -6.86 | AH70: =SUM(AF70,AG70) -> -6.86 | AI70: =((AF70+AG70)*-1) -> 6.86 | AJ70: =AI70/($AI$224) -> 5.2350207e-07 | AK70: =AJ70*($G$260+$G$313-$B$406) -> 0.9246744 | AL70: 0 | AM70: =AL70/AL$224 -> 0 | AN70: =(AM70*$B$406) -> 0 | AO70: =AN70+AK70 -> 0.9246744 | AP70: =$AO70/$AI70 -> 0.13479219 | AQ70: =AB70+AD70+AH70 -> 20147.584 | AR70: =AQ70+AO70 -> 20148.509 | AS70: =AR70/AI70 -> 2937.1004
A71: [ CTO ] - CEMENTERIO | B71: 0 | C71: =$B71/$AI71 -> 0 | D71: 2700 | E71: =$D71/$AI71 -> 0.038354049 | F71: 0 | G71: =$F71/$AI71 -> 0 | H71: 0 | I71: =$H71/$AI71 -> 0 | J71: 7705.468 | K71: =$J71/$AI71 -> 0.10945774 | M71: =$L71/$AI71 -> 0 | O71: =$N71/$AI71 -> 0 | P71: 301.16 | Q71: =$P71/$AI71 -> 0.0042780391 | R71: 1193.291 | S71: =$R71/$AI71 -> 0.016950941 | U71: =$T71/$AI71 -> 0 | W71: =$V71/$AI71 -> 0 | X71: 440.74 | Y71: =$X71/$AI71 -> 0.0062608014 | Z71: 30.614 | AA71: =$Z71/$AI71 -> 0.0004348781 | AB71: 12371.273 | AC71: =$AB71/AI71 -> 0.17573645 | AD71: 32697.884 | AE71: =$AD71/$AI71 -> 0.46448009 | AF71: -61586.48 | AG71: -8810.259 | AH71: =SUM(AF71,AG71) -> -70396.739 | AI71: =((AF71+AG71)*-1) -> 70396.739 | AJ71: =AI71/($AI$224) -> 0.0053721339 | AK71: =AJ71*($G$260+$G$313-$B$406) -> 9488.9303 | AL71: 28498.374 | AM71: =AL71/AL$224 -> 0.006048274 | AN71: =(AM71*$B$406) -> 8223.1426 | AO71: =AN71+AK71 -> 17712.073 | AP71: =$AO71/$AI71 -> 0.2516036 | AQ71: =AB71+AD71+AH71 -> -25327.582 | AR71: =AQ71+AO71 -> -7615.509 | AS71: =AR71/AI71 -> -0.10817986
A72: [ CTS ] - CIUDAD TAMANACO SEGUNDO | B72: 0 | C72: =$B72/$AI72 -> 0 | D72: 176 | E72: =$D72/$AI72 -> 0.0051752961 | F72: 0 | G72: =$F72/$AI72 -> 0 | H72: 0 | I72: =$H72/$AI72 -> 0 | J72: 3721.049 | K72: =$J72/$AI72 -> 0.10941779 | M72: =$L72/$AI72 -> 0 | O72: =$N72/$AI72 -> 0 | Q72: =$P72/$AI72 -> 0 | R72: 411.854 | S72: =$R72/$AI72 -> 0.012110605 | U72: =$T72/$AI72 -> 0 | W72: =$V72/$AI72 -> 0 | X72: 839.39 | Y72: =$X72/$AI72 -> 0.02468234 | Z72: 83.91 | AA72: =$Z72/$AI72 -> 0.0024673812 | AB72: 5232.203 | AC72: =$AB72/AI72 -> 0.15385341 | AD72: 12047.007 | AE72: =$AD72/$AI72 -> 0.35424334 | AF72: -29898.696 | AG72: -4109.02 | AH72: =SUM(AF72,AG72) -> -34007.716 | AI72: =((AF72+AG72)*-1) -> 34007.716 | AJ72: =AI72/($AI$224) -> 0.0025952055 | AK72: =AJ72*($G$260+$G$313-$B$406) -> 4583.9744 | AL72: 16893.655 | AM72: =AL72/AL$224 -> 0.0035853784 | AN72: =(AM72*$B$406) -> 4874.6266 | AO72: =AN72+AK72 -> 9458.601 | AP72: =$AO72/$AI72 -> 0.27813103 | AQ72: =AB72+AD72+AH72 -> -16728.506 | AR72: =AQ72+AO72 -> -7269.905 | AS72: =AR72/AI72 -> -0.21377222
A73: [ CTT ] - CITY 3 | B73: 0 | C73: =$B73/$AI73 -> 0 | D73: 4290 | E73: =$D73/$AI73 -> 0.037600272 | F73: 0 | G73: =$F73/$AI73 -> 0 | H73: 0 | I73: =$H73/$AI73 -> 0 | J73: 5807.166 | K73: =$J73/$AI73 -> 0.050897674 | M73: =$L73/$AI73 -> 0 | O73: =$N73/$AI73 -> 0 | P73: 163.15 | Q73: =$P73/$AI73 -> 0.0014299497 | R73: 207.494 | S73: =$R73/$AI73 -> 0.0018186086 | U73: =$T73/$AI73 -> 0 | W73: =$V73/$AI73 -> 0 | X73: 2109.63 | Y73: =$X73/$AI73 -> 0.018490131 | Z73: 90.323 | AA73: =$Z73/$AI73 -> 0.00079164787 | AB73: 12667.763 | AC73: =$AB73/AI73 -> 0.11102828 | AD73: 56386.21 | AE73: =$AD73/$AI73 -> 0.49420439 | AF73: -99227.5 | AG73: -14867.419 | AH73: =SUM(AF73,AG73) -> -114094.92 | AI73: =((AF73+AG73)*-1) -> 114094.92 | AJ73: =AI73/($AI$224) -> 0.0087068406 | AK73: =AJ73*($G$260+$G$313-$B$406) -> 15379.104 | AL73: 41472.56 | AM73: =AL73/AL$224 -> 0.0088018146 | AN73: =(AM73*$B$406) -> 11966.815 | AO73: =AN73+AK73 -> 27345.919 | AP73: =$AO73/$AI73 -> 0.23967692 | AQ73: =AB73+AD73+AH73 -> -45040.946 | AR73: =AQ73+AO73 -> -17695.027 | AS73: =AR73/AI73 -> -0.15509041
A74: [ CTU ] - CITY 1 | B74: 0 | C74: =$B74/$AI74 -> 0 | D74: 1458 | E74: =$D74/$AI74 -> 0.068686337 | F74: 0 | G74: =$F74/$AI74 -> 0 | H74: 0 | I74: =$H74/$AI74 -> 0 | J74: 1242.912 | K74: =$J74/$AI74 -> 0.058553548 | M74: =$L74/$AI74 -> 0 | N74: 228.45 | O74: =$N74/$AI74 -> 0.010762273 | P74: 41.15 | Q74: =$P74/$AI74 -> 0.0019385753 | R74: 501.835 | S74: =$R74/$AI74 -> 0.023641432 | T74: 4.12 | U74: =$T74/$AI74 -> 0.00019409308 | W74: =$V74/$AI74 -> 0 | X74: 319.96 | Y74: =$X74/$AI74 -> 0.015073306 | Z74: 307.164 | AA74: =$Z74/$AI74 -> 0.014470487 | AB74: 4103.591 | AC74: =$AB74/AI74 -> 0.19332005 | AD74: 11018.409 | AE74: =$AD74/$AI74 -> 0.51907692 | AF74: -18440.447 | AG74: -2786.482 | AH74: =SUM(AF74,AG74) -> -21226.929 | AI74: =((AF74+AG74)*-1) -> 21226.929 | AJ74: =AI74/($AI$224) -> 0.0016198748 | AK74: =AJ74*($G$260+$G$313-$B$406) -> 2861.2242 | AL74: 8097.1871 | AM74: =AL74/AL$224 -> 0.0017184842 | AN74: =(AM74*$B$406) -> 2336.4253 | AO74: =AN74+AK74 -> 5197.6495 | AP74: =$AO74/$AI74 -> 0.24486111 | AQ74: =AB74+AD74+AH74 -> -6104.929 | AR74: =AQ74+AO74 -> -907.2795 | AS74: =AR74/AI74 -> -0.042741911
A75: [ CUA ] - CUMANA SHOP | B75: 0 | C75: =$B75/$AI75 -> 0 | D75: 1900 | E75: =$D75/$AI75 -> 0.016531945 | F75: 0 | G75: =$F75/$AI75 -> 0 | H75: 0 | I75: =$H75/$AI75 -> 0 | J75: 7271.946 | K75: =$J75/$AI75 -> 0.063273374 | M75: =$L75/$AI75 -> 0 | O75: =$N75/$AI75 -> 0 | P75: 160.99 | Q75: =$P75/$AI75 -> 0.0014007778 | R75: 325.047 | S75: =$R75/$AI75 -> 0.0028282416 | U75: =$T75/$AI75 -> 0 | W75: =$V75/$AI75 -> 0 | X75: 163.68 | Y75: =$X75/$AI75 -> 0.0014241835 | Z75: 68.589 | AA75: =$Z75/$AI75 -> 0.00059679451 | AB75: 9890.252 | AC75: =$AB75/AI75 -> 0.086055316 | AD75: 56365.672 | AE75: =$AD75/$AI75 -> 0.49043904 | AF75: -100824.4 | AG75: -14104.605 | AH75: =SUM(AF75,AG75) -> -114929.01 | AI75: =((AF75+AG75)*-1) -> 114929.01 | AJ75: =AI75/($AI$224) -> 0.0087704917 | AK75: =AJ75*($G$260+$G$313-$B$406) -> 15491.532 | AL75: 44863.167 | AM75: =AL75/AL$224 -> 0.0095214108 | AN75: =(AM75*$B$406) -> 12945.167 | AO75: =AN75+AK75 -> 28436.699 | AP75: =$AO75/$AI75 -> 0.24742839 | AQ75: =AB75+AD75+AH75 -> -48673.083 | AR75: =AQ75+AO75 -> -20236.384 | AS75: =AR75/AI75 -> -0.17607725
A76: [ CUG ] - CAUCAGUA | B76: 0 | C76: =$B76/$AI76 -> 0 | D76: 2900 | E76: =$D76/$AI76 -> 0.046770406 | F76: 15 | G76: =$F76/$AI76 -> 0.00024191589 | H76: 0 | I76: =$H76/$AI76 -> 0 | J76: 3378.157 | K76: =$J76/$AI76 -> 0.054481991 | M76: =$L76/$AI76 -> 0 | O76: =$N76/$AI76 -> 0 | P76: 990.56 | Q76: =$P76/$AI76 -> 0.01597548 | R76: 11981.79 | S76: =$R76/$AI76 -> 0.19323903 | U76: =$T76/$AI76 -> 0 | W76: =$V76/$AI76 -> 0 | X76: 130.41 | Y76: =$X76/$AI76 -> 0.0021032168 | Z76: 84.965 | AA76: =$Z76/$AI76 -> 0.0013702923 | AB76: 19480.882 | AC76: =$AB76/AI76 -> 0.31418233 | AD76: 31423.223 | AE76: =$AD76/$AI76 -> 0.50678514 | AF76: -54052.602 | AG76: -7952.419 | AH76: =SUM(AF76,AG76) -> -62005.021 | AI76: =((AF76+AG76)*-1) -> 62005.021 | AJ76: =AI76/($AI$224) -> 0.004731743 | AK76: =AJ76*($G$260+$G$313-$B$406) -> 8357.7923 | AL76: 19624.176 | AM76: =AL76/AL$224 -> 0.004164883 | AN76: =(AM76*$B$406) -> 5662.5125 | AO76: =AN76+AK76 -> 14020.305 | AP76: =$AO76/$AI76 -> 0.22611564 | AQ76: =AB76+AD76+AH76 -> -11100.916 | AR76: =AQ76+AO76 -> 2919.3888 | AS76: =AR76/AI76 -> 0.047083103
A77: [ DCA ] - DUACA | B77: 0 | C77: =$B77/$AI77 -> 0 | D77: 500 | E77: =$D77/$AI77 -> 0.0123164 | F77: 37.25 | G77: =$F77/$AI77 -> 0.0009175718 | H77: 0 | I77: =$H77/$AI77 -> 0 | J77: 3205.048 | K77: =$J77/$AI77 -> 0.078949307 | M77: =$L77/$AI77 -> 0 | O77: =$N77/$AI77 -> 0 | P77: 68.1 | Q77: =$P77/$AI77 -> 0.0016774937 | R77: 54.362 | S77: =$R77/$AI77 -> 0.0013390883 | U77: =$T77/$AI77 -> 0 | W77: =$V77/$AI77 -> 0 | X77: 140.35 | Y77: =$X77/$AI77 -> 0.0034572135 | Z77: 75.183 | AA77: =$Z77/$AI77 -> 0.0018519678 | AB77: 4080.293 | AC77: =$AB77/AI77 -> 0.10050904 | AD77: 19191.459 | AE77: =$AD77/$AI77 -> 0.47273937 | AF77: -35712.327 | AG77: -4883.951 | AH77: =SUM(AF77,AG77) -> -40596.278 | AI77: =((AF77+AG77)*-1) -> 40596.278 | AJ77: =AI77/($AI$224) -> 0.0030979935 | AK77: =AJ77*($G$260+$G$313-$B$406) -> 5472.0611 | AL77: 16414.118 | AM77: =AL77/AL$224 -> 0.0034836051 | AN77: =(AM77*$B$406) -> 4736.2573 | AO77: =AN77+AK77 -> 10208.318 | AP77: =$AO77/$AI77 -> 0.25145946 | AQ77: =AB77+AD77+AH77 -> -17324.526 | AR77: =AQ77+AO77 -> -7116.2077 | AS77: =AR77/AI77 -> -0.17529212
A78: [ ECJ ] - EL CUJI | B78: 0 | C78: =$B78/$AI78 -> 0 | D78: 350 | E78: =$D78/$AI78 -> 0.0085195247 | F78: 91 | G78: =$F78/$AI78 -> 0.0022150764 | H78: 0 | I78: =$H78/$AI78 -> 0 | J78: 3907.052 | K78: =$J78/$AI78 -> 0.095103503 | M78: =$L78/$AI78 -> 0 | O78: =$N78/$AI78 -> 0 | Q78: =$P78/$AI78 -> 0 | R78: 816.088 | S78: =$R78/$AI78 -> 0.019864805 | U78: =$T78/$AI78 -> 0 | W78: =$V78/$AI78 -> 0 | X78: 103 | Y78: =$X78/$AI78 -> 0.0025071744 | Z78: 43.103 | AA78: =$Z78/$AI78 -> 0.0010491916 | AB78: 5310.243 | AC78: =$AB78/AI78 -> 0.12925928 | AD78: 16865.696 | AE78: =$AD78/$AI78 -> 0.41053633 | AF78: -36059.854 | AG78: -5022.25 | AH78: =SUM(AF78,AG78) -> -41082.104 | AI78: =((AF78+AG78)*-1) -> 41082.104 | AJ78: =AI78/($AI$224) -> 0.003135068 | AK78: =AJ78*($G$260+$G$313-$B$406) -> 5537.5466 | AL78: 16536.36 | AM78: =AL78/AL$224 -> 0.0035095487 | AN78: =(AM78*$B$406) -> 4771.5298 | AO78: =AN78+AK78 -> 10309.076 | AP78: =$AO78/$AI78 -> 0.25093837 | AQ78: =AB78+AD78+AH78 -> -18906.165 | AR78: =AQ78+AO78 -> -8597.0886 | AS78: =AR78/AI78 -> -0.20926602
A79: [ ECM ] ECOMMERCE | B79: 0 | C79: =$B79/$AI79 -> 0 | D79: 0 | E79: =$D79/$AI79 -> 0 | F79: 0 | G79: =$F79/$AI79 -> 0 | H79: 0 | I79: =$H79/$AI79 -> 0 | J79: 2902.122 | K79: =$J79/$AI79 -> 0.01794723 | M79: =$L79/$AI79 -> 0 | O79: =$N79/$AI79 -> 0 | Q79: =$P79/$AI79 -> 0 | R79: 116.678 | S79: =$R79/$AI79 -> 0.00072155715 | T79: 0.063 | U79: =$T79/$AI79 -> 3.8960301e-07 | W79: =$V79/$AI79 -> 0 | X79: 44.591 | Y79: =$X79/$AI79 -> 0.00027575854 | Z79: 84.662 | AA79: =$Z79/$AI79 -> 0.00052356461 | AB79: 3148.116 | AC79: =$AB79/AI79 -> 0.0194685 | AD79: 90107.962 | AE79: =$AD79/$AI79 -> 0.55724339 | AF79: -139682.65 | AG79: -22020.409 | AH79: =SUM(AF79,AG79) -> -161703.06 | AI79: =((AF79+AG79)*-1) -> 161703.06 | AJ79: =AI79/($AI$224) -> 0.012339925 | AK79: =AJ79*($G$260+$G$313-$B$406) -> 21796.309 | AL79: 50962.396 | AM79: =AL79/AL$224 -> 0.010815864 | AN79: =(AM79*$B$406) -> 14705.086 | AO79: =AN79+AK79 -> 36501.395 | AP79: =$AO79/$AI79 -> 0.22573101 | AQ79: =AB79+AD79+AH79 -> -68446.983 | AR79: =AQ79+AO79 -> -31945.588 | AS79: =AR79/AI79 -> -0.1975571
A80: [ EJD ] - EJIDO | B80: 0 | C80: =$B80/$AI80 -> 0 | D80: 450 | E80: =$D80/$AI80 -> 0.011283886 | F80: 32.01 | G80: =$F80/$AI80 -> 0.00080266043 | H80: 0 | I80: =$H80/$AI80 -> 0 | J80: 3193.717 | K80: =$J80/$AI80 -> 0.08008342 | M80: =$L80/$AI80 -> 0 | O80: =$N80/$AI80 -> 0 | P80: 10 | Q80: =$P80/$AI80 -> 0.00025075302 | R80: 201.073 | S80: =$R80/$AI80 -> 0.0050419663 | U80: =$T80/$AI80 -> 0 | W80: =$V80/$AI80 -> 0 | X80: 77.09 | Y80: =$X80/$AI80 -> 0.0019330551 | Z80: 53.173 | AA80: =$Z80/$AI80 -> 0.0013333291 | AB80: 4017.063 | AC80: =$AB80/AI80 -> 0.10072907 | AD80: 18903.991 | AE80: =$AD80/$AI80 -> 0.47402329 | AF80: -35193.64 | AG80: -4686.238 | AH80: =SUM(AF80,AG80) -> -39879.878 | AI80: =((AF80+AG80)*-1) -> 39879.878 | AJ80: =AI80/($AI$224) -> 0.0030433234 | AK80: =AJ80*($G$260+$G$313-$B$406) -> 5375.4959 | AL80: 15768.793 | AM80: =AL80/AL$224 -> 0.0033466463 | AN80: =(AM80*$B$406) -> 4550.0501 | AO80: =AN80+AK80 -> 9925.546 | AP80: =$AO80/$AI80 -> 0.24888607 | AQ80: =AB80+AD80+AH80 -> -16958.824 | AR80: =AQ80+AO80 -> -7033.278 | AS80: =AR80/AI80 -> -0.17636157
A81: [ ELZ ] - ELORZA | B81: 0 | C81: =$B81/$AI81 -> 0 | D81: 460 | E81: =$D81/$AI81 -> 0.014872206 | F81: 37.62 | G81: =$F81/$AI81 -> 0.0012162878 | H81: 0 | I81: =$H81/$AI81 -> 0 | J81: 2509.597 | K81: =$J81/$AI81 -> 0.081137484 | M81: =$L81/$AI81 -> 0 | O81: =$N81/$AI81 -> 0 | Q81: =$P81/$AI81 -> 0 | R81: 1223.404 | S81: =$R81/$AI81 -> 0.03955373 | U81: =$T81/$AI81 -> 0 | W81: =$V81/$AI81 -> 0 | X81: 59.13 | Y81: =$X81/$AI81 -> 0.0019117251 | Z81: 258.952 | AA81: =$Z81/$AI81 -> 0.0083721466 | AB81: 4548.703 | AC81: =$AB81/AI81 -> 0.14706358 | AD81: 15509.833 | AE81: =$AD81/$AI81 -> 0.50144658 | AF81: -26868.105 | AG81: -4062.075 | AH81: =SUM(AF81,AG81) -> -30930.18 | AI81: =((AF81+AG81)*-1) -> 30930.18 | AJ81: =AI81/($AI$224) -> 0.0023603518 | AK81: =AJ81*($G$260+$G$313-$B$406) -> 4169.1466 | AL81: 8527.4539 | AM81: =AL81/AL$224 -> 0.0018098007 | AN81: =(AM81*$B$406) -> 2460.5779 | AO81: =AN81+AK81 -> 6629.7244 | AP81: =$AO81/$AI81 -> 0.21434484 | AQ81: =AB81+AD81+AH81 -> -10871.644 | AR81: =AQ81+AO81 -> -4241.9196 | AS81: =AR81/AI81 -> -0.137145
A82: [ EMT ] - EL MANTECO | B82: 0 | C82: =$B82/$AI82 -> 0 | D82: 3655 | E82: =$D82/$AI82 -> 0.14007671 | F82: 201.23 | G82: =$F82/$AI82 -> 0.0077120759 | H82: 0 | I82: =$H82/$AI82 -> 0 | J82: 2271.534 | K82: =$J82/$AI82 -> 0.087055819 | M82: =$L82/$AI82 -> 0 | O82: =$N82/$AI82 -> 0 | P82: 66.96 | Q82: =$P82/$AI82 -> 0.0025662207 | R82: 1123.496 | S82: =$R82/$AI82 -> 0.043057627 | U82: =$T82/$AI82 -> 0 | W82: =$V82/$AI82 -> 0 | X82: 222.16 | Y82: =$X82/$AI82 -> 0.0085142115 | Z82: 198.884 | AA82: =$Z82/$AI82 -> 0.0076221662 | AB82: 7739.264 | AC82: =$AB82/AI82 -> 0.29660484 | AD82: 14731.398 | AE82: =$AD82/$AI82 -> 0.56457615 | AF82: -22851.346 | AG82: -3241.499 | AH82: =SUM(AF82,AG82) -> -26092.845 | AI82: =((AF82+AG82)*-1) -> 26092.845 | AJ82: =AI82/($AI$224) -> 0.0019912038 | AK82: =AJ82*($G$260+$G$313-$B$406) -> 3517.1116 | AL82: 4813.8627 | AM82: =AL82/AL$224 -> 0.0010216569 | AN82: =(AM82*$B$406) -> 1389.0294 | AO82: =AN82+AK82 -> 4906.141 | AP82: =$AO82/$AI82 -> 0.1880263 | AQ82: =AB82+AD82+AH82 -> -3622.183 | AR82: =AQ82+AO82 -> 1283.958 | AS82: =AR82/AI82 -> 0.049207283
A83: [ FAM ] - FLOR AMARILLO | B83: 0 | C83: =$B83/$AI83 -> 0 | D83: 490 | E83: =$D83/$AI83 -> 0.01074988 | F83: 25 | G83: =$F83/$AI83 -> 0.00054846328 | H83: 0 | I83: =$H83/$AI83 -> 0 | J83: 2910.955 | K83: =$J83/$AI83 -> 0.063862077 | M83: =$L83/$AI83 -> 0 | O83: =$N83/$AI83 -> 0 | P83: 45.77 | Q83: =$P83/$AI83 -> 0.0010041266 | R83: 1414.103 | S83: =$R83/$AI83 -> 0.031023343 | U83: =$T83/$AI83 -> 0 | W83: =$V83/$AI83 -> 0 | X83: 100.89 | Y83: =$X83/$AI83 -> 0.0022133784 | Z83: 120.95 | AA83: =$Z83/$AI83 -> 0.0026534653 | AB83: 5107.668 | AC83: =$AB83/AI83 -> 0.11205473 | AD83: 21656.617 | AE83: =$AD83/$AI83 -> 0.47511437 | AF83: -39482.782 | AG83: -6099.121 | AH83: =SUM(AF83,AG83) -> -45581.903 | AI83: =((AF83+AG83)*-1) -> 45581.903 | AJ83: =AI83/($AI$224) -> 0.0034784578 | AK83: =AJ83*($G$260+$G$313-$B$406) -> 6144.0844 | AL83: 14069.196 | AM83: =AL83/AL$224 -> 0.002985937 | AN83: =(AM83*$B$406) -> 4059.6351 | AO83: =AN83+AK83 -> 10203.719 | AP83: =$AO83/$AI83 -> 0.22385462 | AQ83: =AB83+AD83+AH83 -> -18817.618 | AR83: =AQ83+AO83 -> -8613.8985 | AS83: =AR83/AI83 -> -0.18897628
A84: [ FMD ] - FREEMARKET 2 | B84: 0 | C84: =$B84/$AI84 -> 0 | D84: 700 | E84: =$D84/$AI84 -> 0.01283744 | F84: 0 | G84: =$F84/$AI84 -> 0 | H84: 0 | I84: =$H84/$AI84 -> 0 | J84: 2102.087 | K84: =$J84/$AI84 -> 0.038550595 | M84: =$L84/$AI84 -> 0 | O84: =$N84/$AI84 -> 0 | P84: 103.73 | Q84: =$P84/$AI84 -> 0.0019023253 | R84: 3080.605 | S84: =$R84/$AI84 -> 0.056495833 | U84: =$T84/$AI84 -> 0 | W84: =$V84/$AI84 -> 0 | X84: 90.97 | Y84: =$X84/$AI84 -> 0.0016683171 | Z84: 190.846 | AA84: =$Z84/$AI84 -> 0.0034999631 | AB84: 6268.238 | AC84: =$AB84/AI84 -> 0.11495447 | AD84: 31638.087 | AE84: =$AD84/$AI84 -> 0.58021722 | AF84: -47588.815 | AG84: -6939.189 | AH84: =SUM(AF84,AG84) -> -54528.004 | AI84: =((AF84+AG84)*-1) -> 54528.004 | AJ84: =AI84/($AI$224) -> 0.0041611549 | AK84: =AJ84*($G$260+$G$313-$B$406) -> 7349.9489 | AL84: 10417.476 | AM84: =AL84/AL$224 -> 0.0022109243 | AN84: =(AM84*$B$406) -> 3005.9395 | AO84: =AN84+AK84 -> 10355.888 | AP84: =$AO84/$AI84 -> 0.18991871 | AQ84: =AB84+AD84+AH84 -> -16621.679 | AR84: =AQ84+AO84 -> -6265.7906 | AS84: =AR84/AI84 -> -0.11490959
A85: [ FOR - CHV ] - FORUM CHARALLAVE | B85: 0 | C85: =$B85/$AI85 -> 0 | D85: 416.64 | E85: =$D85/$AI85 -> 0.017669536 | F85: 0 | G85: =$F85/$AI85 -> 0 | H85: 0 | I85: =$H85/$AI85 -> 0 | J85: 955.163 | K85: =$J85/$AI85 -> 0.040508082 | M85: =$L85/$AI85 -> 0 | O85: =$N85/$AI85 -> 0 | P85: 137.83 | Q85: =$P85/$AI85 -> 0.0058453154 | R85: 340.144 | S85: =$R85/$AI85 -> 0.014425372 | U85: =$T85/$AI85 -> 0 | W85: =$V85/$AI85 -> 0 | Y85: =$X85/$AI85 -> 0 | Z85: 81.114 | AA85: =$Z85/$AI85 -> 0.0034400124 | AB85: 1930.891 | AC85: =$AB85/AI85 -> 0.081888318 | AD85: 11012.561 | AE85: =$AD85/$AI85 -> 0.46703832 | AF85: -20570.965 | AG85: -3008.601 | AH85: =SUM(AF85,AG85) -> -23579.566 | AI85: =((AF85+AG85)*-1) -> 23579.566 | AJ85: =AI85/($AI$224) -> 0.0017994099 | AK85: =AJ85*($G$260+$G$313-$B$406) -> 3178.3412 | AL85: 7306.2744 | AM85: =AL85/AL$224 -> 0.001550627 | AN85: =(AM85*$B$406) -> 2108.2092 | AO85: =AN85+AK85 -> 5286.5505 | AP85: =$AO85/$AI85 -> 0.2242005 | AQ85: =AB85+AD85+AH85 -> -10636.114 | AR85: =AQ85+AO85 -> -5349.5635 | AS85: =AR85/AI85 -> -0.22687286
A86: [ FOR - GTE ] - FORUM GUATIRE | B86: 0 | C86: =$B86/$AI86 -> 0 | D86: 680.53 | E86: =$D86/$AI86 -> 0.016596487 | F86: 0 | G86: =$F86/$AI86 -> 0 | H86: 0 | I86: =$H86/$AI86 -> 0 | J86: 1412.941 | K86: =$J86/$AI86 -> 0.034458226 | M86: =$L86/$AI86 -> 0 | O86: =$N86/$AI86 -> 0 | P86: 114.29 | Q86: =$P86/$AI86 -> 0.0027872577 | R86: 580.676 | S86: =$R86/$AI86 -> 0.014161288 | U86: =$T86/$AI86 -> 0 | W86: =$V86/$AI86 -> 0 | Y86: =$X86/$AI86 -> 0 | Z86: 327.096 | AA86: =$Z86/$AI86 -> 0.0079770833 | AB86: 3115.533 | AC86: =$AB86/AI86 -> 0.075980343 | AD86: 19652.865 | AE86: =$AD86/$AI86 -> 0.47928602 | AF86: -35936.385 | AG86: -5068.076 | AH86: =SUM(AF86,AG86) -> -41004.461 | AI86: =((AF86+AG86)*-1) -> 41004.461 | AJ86: =AI86/($AI$224) -> 0.0031291429 | AK86: =AJ86*($G$260+$G$313-$B$406) -> 5527.0809 | AL86: 12018.982 | AM86: =AL86/AL$224 -> 0.0025508156 | AN86: =(AM86*$B$406) -> 3468.0507 | AO86: =AN86+AK86 -> 8995.1316 | AP86: =$AO86/$AI86 -> 0.21936958 | AQ86: =AB86+AD86+AH86 -> -18236.063 | AR86: =AQ86+AO86 -> -9240.9314 | AS86: =AR86/AI86 -> -0.22536405
A87: [ FOR - ISF ] - FORUM IPSFA | B87: 0 | C87: =$B87/$AI87 -> 0 | D87: 692.11 | E87: =$D87/$AI87 -> 0.023039398 | F87: 0 | G87: =$F87/$AI87 -> 0 | H87: 0 | I87: =$H87/$AI87 -> 0 | J87: 2721.907 | K87: =$J87/$AI87 -> 0.09060857 | M87: =$L87/$AI87 -> 0 | O87: =$N87/$AI87 -> 0 | P87: 65.69 | Q87: =$P87/$AI87 -> 0.0021867305 | S87: =$R87/$AI87 -> 0 | U87: =$T87/$AI87 -> 0 | W87: =$V87/$AI87 -> 0 | Y87: =$X87/$AI87 -> 0 | Z87: 0.359 | AA87: =$Z87/$AI87 -> 1.195062e-05 | AB87: 3480.066 | AC87: =$AB87/AI87 -> 0.11584665 | AD87: 13109.82 | AE87: =$AD87/$AI87 -> 0.43640802 | AF87: -26083.149 | AG87: -3957.133 | AH87: =SUM(AF87,AG87) -> -30040.282 | AI87: =((AF87+AG87)*-1) -> 30040.282 | AJ87: =AI87/($AI$224) -> 0.0022924417 | AK87: =AJ87*($G$260+$G$313-$B$406) -> 4049.1953 | AL87: 12486.084 | AM87: =AL87/AL$224 -> 0.0026499496 | AN87: =(AM87*$B$406) -> 3602.8317 | AO87: =AN87+AK87 -> 7652.027 | AP87: =$AO87/$AI87 -> 0.25472554 | AQ87: =AB87+AD87+AH87 -> -13450.396 | AR87: =AQ87+AO87 -> -5798.369 | AS87: =AR87/AI87 -> -0.19301979
A88: [ FOR - PRS ] - FORUM PARAISO | B88: 0 | C88: =$B88/$AI88 -> 0 | D88: 361.78 | E88: =$D88/$AI88 -> 0.018820563 | F88: 0 | G88: =$F88/$AI88 -> 0 | H88: 0 | I88: =$H88/$AI88 -> 0 | J88: 1536.897 | K88: =$J88/$AI88 -> 0.079952641 | M88: =$L88/$AI88 -> 0 | O88: =$N88/$AI88 -> 0 | P88: 29.07 | Q88: =$P88/$AI88 -> 0.001512283 | R88: 19.106 | S88: =$R88/$AI88 -> 0.00099393464 | U88: =$T88/$AI88 -> 0 | W88: =$V88/$AI88 -> 0 | X88: 72.18 | Y88: =$X88/$AI88 -> 0.0037549567 | Z88: 18.008 | AA88: =$Z88/$AI88 -> 0.00093681435 | AB88: 2037.041 | AC88: =$AB88/AI88 -> 0.10597119 | AD88: 9208.094 | AE88: =$AD88/$AI88 -> 0.47902458 | AF88: -16729.882 | AG88: -2492.71 | AH88: =SUM(AF88,AG88) -> -19222.592 | AI88: =((AF88+AG88)*-1) -> 19222.592 | AJ88: =AI88/($AI$224) -> 0.0014669193 | AK88: =AJ88*($G$260+$G$313-$B$406) -> 2591.0552 | AL88: 6447.6285 | AM88: =AL88/AL$224 -> 0.0013683947 | AN88: =(AM88*$B$406) -> 1860.4489 | AO88: =AN88+AK88 -> 4451.5041 | AP88: =$AO88/$AI88 -> 0.23157668 | AQ88: =AB88+AD88+AH88 -> -7977.457 | AR88: =AQ88+AO88 -> -3525.9529 | AS88: =AR88/AI88 -> -0.18342755
A89: [ FOR - PZV ] - FORUM PLAZA VENEZUELA | B89: 0 | C89: =$B89/$AI89 -> 0 | D89: 392.31 | E89: =$D89/$AI89 -> 0.041073057 | F89: 0 | G89: =$F89/$AI89 -> 0 | H89: 0 | I89: =$H89/$AI89 -> 0 | J89: 1913.43 | K89: =$J89/$AI89 -> 0.20032734 | M89: =$L89/$AI89 -> 0 | O89: =$N89/$AI89 -> 0 | P89: 25.15 | Q89: =$P89/$AI89 -> 0.0026330896 | R89: 0.5 | S89: =$R89/$AI89 -> 5.2347706e-05 | U89: =$T89/$AI89 -> 0 | W89: =$V89/$AI89 -> 0 | X89: 88.36 | Y89: =$X89/$AI89 -> 0.0092508865 | Z89: 39.558 | AA89: =$Z89/$AI89 -> 0.0041415411 | AB89: 2459.308 | AC89: =$AB89/AI89 -> 0.25747826 | AD89: 4388.088 | AE89: =$AD89/$AI89 -> 0.45941268 | AF89: -8347.328 | AG89: -1204.189 | AH89: =SUM(AF89,AG89) -> -9551.517 | AI89: =((AF89+AG89)*-1) -> 9551.517 | AJ89: =AI89/($AI$224) -> 0.0007288978 | AK89: =AJ89*($G$260+$G$313-$B$406) -> 1287.4699 | AL89: 2953.9045 | AM89: =AL89/AL$224 -> 0.00062691379 | AN89: =(AM89*$B$406) -> 852.34258 | AO89: =AN89+AK89 -> 2139.8124 | AP89: =$AO89/$AI89 -> 0.22402854 | AQ89: =AB89+AD89+AH89 -> -2704.121 | AR89: =AQ89+AO89 -> -564.30856 | AS89: =AR89/AI89 -> -0.059080517
A90: [ FRM ] - FREEMARKET | B90: 0 | C90: =$B90/$AI90 -> 0 | D90: 1200 | E90: =$D90/$AI90 -> 0.015653282 | F90: 0 | G90: =$F90/$AI90 -> 0 | H90: 0 | I90: =$H90/$AI90 -> 0 | J90: 3803.723 | K90: =$J90/$AI90 -> 0.04961729 | M90: =$L90/$AI90 -> 0 | O90: =$N90/$AI90 -> 0 | P90: 118.47 | Q90: =$P90/$AI90 -> 0.0015453703 | R90: 55.132 | S90: =$R90/$AI90 -> 0.00071916395 | U90: =$T90/$AI90 -> 0 | W90: =$V90/$AI90 -> 0 | X90: 61.57 | Y90: =$X90/$AI90 -> 0.00080314381 | Z90: 110.301 | AA90: =$Z90/$AI90 -> 0.0014388105 | AB90: 5349.196 | AC90: =$AB90/AI90 -> 0.069777061 | AD90: 38585.936 | AE90: =$AD90/$AI90 -> 0.50333044 | AF90: -66825.559 | AG90: -9835.681 | AH90: =SUM(AF90,AG90) -> -76661.24 | AI90: =((AF90+AG90)*-1) -> 76661.24 | AJ90: =AI90/($AI$224) -> 0.0058501921 | AK90: =AJ90*($G$260+$G$313-$B$406) -> 10333.336 | AL90: 23390.018 | AM90: =AL90/AL$224 -> 0.0049641162 | AN90: =(AM90*$B$406) -> 6749.1379 | AO90: =AN90+AK90 -> 17082.474 | AP90: =$AO90/$AI90 -> 0.22283065 | AQ90: =AB90+AD90+AH90 -> -32726.108 | AR90: =AQ90+AO90 -> -15643.634 | AS90: =AR90/AI90 -> -0.20406184
A91: [ GCA ] - GUACARA | B91: 0 | C91: =$B91/$AI91 -> 0 | D91: 1400 | E91: =$D91/$AI91 -> 0.0098197179 | F91: 0 | G91: =$F91/$AI91 -> 0 | H91: 0 | I91: =$H91/$AI91 -> 0 | J91: 6365.121 | K91: =$J91/$AI91 -> 0.044645495 | M91: =$L91/$AI91 -> 0 | O91: =$N91/$AI91 -> 0 | P91: 430.35 | Q91: =$P91/$AI91 -> 0.0030185111 | R91: 1521.542 | S91: =$R91/$AI91 -> 0.010672224 | U91: =$T91/$AI91 -> 0 | W91: =$V91/$AI91 -> 0 | X91: 119.39 | Y91: =$X91/$AI91 -> 0.00083741151 | Z91: 256.29 | AA91: =$Z91/$AI91 -> 0.0017976396 | AB91: 10092.693 | AC91: =$AB91/AI91 -> 0.070790999 | AD91: 75540.246 | AE91: =$AD91/$AI91 -> 0.52984565 | AF91: -124744.21 | AG91: -17826.075 | AH91: =SUM(AF91,AG91) -> -142570.29 | AI91: =((AF91+AG91)*-1) -> 142570.29 | AJ91: =AI91/($AI$224) -> 0.01087986 | AK91: =AJ91*($G$260+$G$313-$B$406) -> 19217.361 | AL91: 42546.14 | AM91: =AL91/AL$224 -> 0.0090296629 | AN91: =(AM91*$B$406) -> 12276.594 | AO91: =AN91+AK91 -> 31493.955 | AP91: =$AO91/$AI91 -> 0.22090125 | AQ91: =AB91+AD91+AH91 -> -56937.348 | AR91: =AQ91+AO91 -> -25443.393 | AS91: =AR91/AI91 -> -0.1784621
A92: [ GIA ] - GUIRIA | B92: 0 | C92: =$B92/$AI92 -> 0 | D92: 400 | E92: =$D92/$AI92 -> 0.01019378 | F92: 67.63 | G92: =$F92/$AI92 -> 0.0017235134 | H92: 0 | I92: =$H92/$AI92 -> 0 | J92: 2172.272 | K92: =$J92/$AI92 -> 0.055359158 | M92: =$L92/$AI92 -> 0 | O92: =$N92/$AI92 -> 0 | P92: 88.16 | Q92: =$P92/$AI92 -> 0.0022467092 | R92: 50.615 | S92: =$R92/$AI92 -> 0.0012898955 | U92: =$T92/$AI92 -> 0 | W92: =$V92/$AI92 -> 0 | X92: 196.73 | Y92: =$X92/$AI92 -> 0.0050135559 | Z92: 40.235 | AA92: =$Z92/$AI92 -> 0.0010253669 | AB92: 3015.642 | AC92: =$AB92/AI92 -> 0.076851979 | AD92: 19191.916 | AE92: =$AD92/$AI92 -> 0.48909543 | AF92: -34689.675 | AG92: -4549.939 | AH92: =SUM(AF92,AG92) -> -39239.614 | AI92: =((AF92+AG92)*-1) -> 39239.614 | AJ92: =AI92/($AI$224) -> 0.0029944634 | AK92: =AJ92*($G$260+$G$313-$B$406) -> 5289.1934 | AL92: 17354.7 | AM92: =AL92/AL$224 -> 0.003683227 | AN92: =(AM92*$B$406) -> 5007.6601 | AO92: =AN92+AK92 -> 10296.853 | AP92: =$AO92/$AI92 -> 0.26240965 | AQ92: =AB92+AD92+AH92 -> -17032.056 | AR92: =AQ92+AO92 -> -6735.2025 | AS92: =AR92/AI92 -> -0.17164294
A93: [ GNO ] - GUANARITO | B93: 0 | C93: =$B93/$AI93 -> 0 | D93: 1000 | E93: =$D93/$AI93 -> 0.032603065 | F93: 74.41 | G93: =$F93/$AI93 -> 0.0024259941 | H93: 0 | I93: =$H93/$AI93 -> 0 | J93: 2621.24 | K93: =$J93/$AI93 -> 0.085460458 | M93: =$L93/$AI93 -> 0 | O93: =$N93/$AI93 -> 0 | P93: 90.76 | Q93: =$P93/$AI93 -> 0.0029590542 | R93: 306.653 | S93: =$R93/$AI93 -> 0.0099978277 | U93: =$T93/$AI93 -> 0 | W93: =$V93/$AI93 -> 0 | X93: 238.32 | Y93: =$X93/$AI93 -> 0.0077699624 | Z93: 215.956 | AA93: =$Z93/$AI93 -> 0.0070408275 | AB93: 4547.339 | AC93: =$AB93/AI93 -> 0.14825719 | AD93: 16390.728 | AE93: =$AD93/$AI93 -> 0.53438797 | AF93: -26779.65 | AG93: -3892.313 | AH93: =SUM(AF93,AG93) -> -30671.963 | AI93: =((AF93+AG93)*-1) -> 30671.963 | AJ93: =AI93/($AI$224) -> 0.0023406467 | AK93: =AJ93*($G$260+$G$313-$B$406) -> 4134.3409 | AL93: 10449.199 | AM93: =AL93/AL$224 -> 0.0022176571 | AN93: =(AM93*$B$406) -> 3015.0933 | AO93: =AN93+AK93 -> 7149.4342 | AP93: =$AO93/$AI93 -> 0.23309347 | AQ93: =AB93+AD93+AH93 -> -9733.896 | AR93: =AQ93+AO93 -> -2584.4618 | AS93: =AR93/AI93 -> -0.084261375
A94: [ GNR ] - GUANARE | B94: 0 | C94: =$B94/$AI94 -> 0 | D94: 1100 | E94: =$D94/$AI94 -> 0.012041574 | F94: 0 | G94: =$F94/$AI94 -> 0 | H94: 0 | I94: =$H94/$AI94 -> 0 | J94: 7043.147 | K94: =$J94/$AI94 -> 0.077100523 | M94: =$L94/$AI94 -> 0 | O94: =$N94/$AI94 -> 0 | P94: 81.03 | Q94: =$P94/$AI94 -> 0.00088702613 | R94: 1321.29 | S94: =$R94/$AI94 -> 0.01446401 | U94: =$T94/$AI94 -> 0 | W94: =$V94/$AI94 -> 0 | X94: 95.01 | Y94: =$X94/$AI94 -> 0.0010400636 | Z94: 586.171 | AA94: =$Z94/$AI94 -> 0.0064167468 | AB94: 10226.648 | AC94: =$AB94/AI94 -> 0.11194994 | AD94: 47792.078 | AE94: =$AD94/$AI94 -> 0.5231744 | AF94: -79755.776 | AG94: -11594.408 | AH94: =SUM(AF94,AG94) -> -91350.184 | AI94: =((AF94+AG94)*-1) -> 91350.184 | AJ94: =AI94/($AI$224) -> 0.0069711385 | AK94: =AJ94*($G$260+$G$313-$B$406) -> 12313.291 | AL94: 30386.45 | AM94: =AL94/AL$224 -> 0.0064489846 | AN94: =(AM94*$B$406) -> 8767.9426 | AO94: =AN94+AK94 -> 21081.234 | AP94: =$AO94/$AI94 -> 0.23077385 | AQ94: =AB94+AD94+AH94 -> -33331.458 | AR94: =AQ94+AO94 -> -12250.224 | AS94: =AR94/AI94 -> -0.1341018
A95: [ GNT ] - GUANTA | B95: 0 | C95: =$B95/$AI95 -> 0 | D95: 400 | E95: =$D95/$AI95 -> 0.013489485 | F95: 12.25 | G95: =$F95/$AI95 -> 0.00041311549 | H95: 0 | I95: =$H95/$AI95 -> 0 | J95: 2414.5 | K95: =$J95/$AI95 -> 0.081425906 | M95: =$L95/$AI95 -> 0 | O95: =$N95/$AI95 -> 0 | P95: 80.02 | Q95: =$P95/$AI95 -> 0.0026985715 | R95: 8.44 | S95: =$R95/$AI95 -> 0.00028462814 | U95: =$T95/$AI95 -> 0 | W95: =$V95/$AI95 -> 0 | X95: 155.63 | Y95: =$X95/$AI95 -> 0.0052484215 | Z95: 46.779 | AA95: =$Z95/$AI95 -> 0.0015775616 | AB95: 3117.619 | AC95: =$AB95/AI95 -> 0.10513769 | AD95: 13106.496 | AE95: =$AD95/$AI95 -> 0.44199972 | AF95: -26230.502 | AG95: -3422.223 | AH95: =SUM(AF95,AG95) -> -29652.725 | AI95: =((AF95+AG95)*-1) -> 29652.725 | AJ95: =AI95/($AI$224) -> 0.0022628663 | AK95: =AJ95*($G$260+$G$313-$B$406) -> 3996.9556 | AL95: 10528.27 | AM95: =AL95/AL$224 -> 0.0022344383 | AN95: =(AM95*$B$406) -> 3037.9088 | AO95: =AN95+AK95 -> 7034.8644 | AP95: =$AO95/$AI95 -> 0.23724175 | AQ95: =AB95+AD95+AH95 -> -13428.61 | AR95: =AQ95+AO95 -> -6393.7456 | AS95: =AR95/AI95 -> -0.21562084
A96: [ GPT ] - GUASIPATI | B96: 0 | C96: =$B96/$AI96 -> 0 | D96: 2300 | E96: =$D96/$AI96 -> 0.04978368 | F96: 266.86 | G96: =$F96/$AI96 -> 0.0057762056 | H96: 0 | I96: =$H96/$AI96 -> 0 | J96: 2045.111 | K96: =$J96/$AI96 -> 0.044266588 | M96: =$L96/$AI96 -> 0 | O96: =$N96/$AI96 -> 0 | P96: 78.33 | Q96: =$P96/$AI96 -> 0.001695459 | R96: 349.684 | S96: =$R96/$AI96 -> 0.0075689376 | U96: =$T96/$AI96 -> 0 | W96: =$V96/$AI96 -> 0 | X96: 173.74 | Y96: =$X96/$AI96 -> 0.0037606159 | Z96: 84.236 | AA96: =$Z96/$AI96 -> 0.0018232948 | AB96: 5297.961 | AC96: =$AB96/AI96 -> 0.11467478 | AD96: 24547.797 | AE96: =$AD96/$AI96 -> 0.53133899 | AF96: -40440.562 | AG96: -5759.317 | AH96: =SUM(AF96,AG96) -> -46199.879 | AI96: =((AF96+AG96)*-1) -> 46199.879 | AJ96: =AI96/($AI$224) -> 0.0035256169 | AK96: =AJ96*($G$260+$G$313-$B$406) -> 6227.3827 | AL96: 12485.153 | AM96: =AL96/AL$224 -> 0.002649752 | AN96: =(AM96*$B$406) -> 3602.5631 | AO96: =AN96+AK96 -> 9829.9458 | AP96: =$AO96/$AI96 -> 0.21276995 | AQ96: =AB96+AD96+AH96 -> -16354.121 | AR96: =AQ96+AO96 -> -6524.1752 | AS96: =AR96/AI96 -> -0.14121628
A97: [ GRA ] - GUARENAS | B97: 0 | C97: =$B97/$AI97 -> 0 | D97: 3200 | E97: =$D97/$AI97 -> 0.022328484 | F97: 8 | G97: =$F97/$AI97 -> 5.5821209e-05 | H97: 0 | I97: =$H97/$AI97 -> 0 | J97: 5482.304 | K97: =$J97/$AI97 -> 0.038253605 | M97: =$L97/$AI97 -> 0 | N97: 129.52 | O97: =$N97/$AI97 -> 0.00090374538 | P97: 126.7 | Q97: =$P97/$AI97 -> 0.0008840684 | R97: 21959.283 | S97: =$R97/$AI97 -> 0.15322422 | U97: =$T97/$AI97 -> 0 | W97: =$V97/$AI97 -> 0 | X97: 143.068 | Y97: =$X97/$AI97 -> 0.0009982786 | Z97: 185.714 | AA97: =$Z97/$AI97 -> 0.0012958475 | AB97: 31234.589 | AC97: =$AB97/AI97 -> 0.21794407 | AD97: 69897.668 | AE97: =$AD97/$AI97 -> 0.48772155 | AF97: -124965.86 | AG97: -18348.838 | AH97: =SUM(AF97,AG97) -> -143314.7 | AI97: =((AF97+AG97)*-1) -> 143314.7 | AJ97: =AI97/($AI$224) -> 0.010936668 | AK97: =AJ97*($G$260+$G$313-$B$406) -> 19317.702 | AL97: 43893.713 | AM97: =AL97/AL$224 -> 0.0093156612 | AN97: =(AM97*$B$406) -> 12665.433 | AO97: =AN97+AK97 -> 31983.135 | AP97: =$AO97/$AI97 -> 0.22316716 | AQ97: =AB97+AD97+AH97 -> -42182.445 | AR97: =AQ97+AO97 -> -10199.31 | AS97: =AR97/AI97 -> -0.071167226
A98: [ GTE ] - GUATIRE | B98: 0 | C98: =$B98/$AI98 -> 0 | D98: 660 | E98: =$D98/$AI98 -> 0.0062737359 | F98: 0 | G98: =$F98/$AI98 -> 0 | H98: 0 | I98: =$H98/$AI98 -> 0 | J98: 3995.888 | K98: =$J98/$AI98 -> 0.037983554 | M98: =$L98/$AI98 -> 0 | O98: =$N98/$AI98 -> 0 | P98: 410.49 | Q98: =$P98/$AI98 -> 0.0039019785 | R98: 1593.883 | S98: =$R98/$AI98 -> 0.015150911 | U98: =$T98/$AI98 -> 0 | W98: =$V98/$AI98 -> 0 | X98: 46.62 | Y98: =$X98/$AI98 -> 0.00044315389 | Z98: 514.926 | AA98: =$Z98/$AI98 -> 0.0048947117 | AB98: 7221.807 | AC98: =$AB98/AI98 -> 0.068648045 | AD98: 52479.521 | AE98: =$AD98/$AI98 -> 0.49885251 | AF98: -91658.194 | AG98: -13542.282 | AH98: =SUM(AF98,AG98) -> -105200.48 | AI98: =((AF98+AG98)*-1) -> 105200.48 | AJ98: =AI98/($AI$224) -> 0.0080280856 | AK98: =AJ98*($G$260+$G$313-$B$406) -> 14180.202 | AL98: 37555.026 | AM98: =AL98/AL$224 -> 0.0079703875 | AN98: =(AM98*$B$406) -> 10836.419 | AO98: =AN98+AK98 -> 25016.621 | AP98: =$AO98/$AI98 -> 0.23779951 | AQ98: =AB98+AD98+AH98 -> -45499.148 | AR98: =AQ98+AO98 -> -20482.527 | AS98: =AR98/AI98 -> -0.19469994
A99: [ GTN ] - GATO NEGRO | B99: 0 | C99: =$B99/$AI99 -> 0 | D99: 2100 | E99: =$D99/$AI99 -> 0.034256776 | F99: 0 | G99: =$F99/$AI99 -> 0 | H99: -1.724 | I99: =$H99/$AI99 -> -2.8123182e-05 | J99: 3062.546 | K99: =$J99/$AI99 -> 0.049958548 | M99: =$L99/$AI99 -> 0 | O99: =$N99/$AI99 -> 0 | P99: 69.32 | Q99: =$P99/$AI99 -> 0.0011307999 | R99: 2273.435 | S99: =$R99/$AI99 -> 0.037085978 | U99: =$T99/$AI99 -> 0 | W99: =$V99/$AI99 -> 0 | X99: 94.01 | Y99: =$X99/$AI99 -> 0.0015335617 | Z99: 296.837 | AA99: =$Z99/$AI99 -> 0.0048422279 | AB99: 7894.424 | AC99: =$AB99/AI99 -> 0.12877977 | AD99: 25816.781 | AE99: =$AD99/$AI99 -> 0.4211427 | AF99: -53756.559 | AG99: -7545.182 | AH99: =SUM(AF99,AG99) -> -61301.741 | AI99: =((AF99+AG99)*-1) -> 61301.741 | AJ99: =AI99/($AI$224) -> 0.0046780741 | AK99: =AJ99*($G$260+$G$313-$B$406) -> 8262.9957 | AL99: 28771.732 | AM99: =AL99/AL$224 -> 0.0061062894 | AN99: =(AM99*$B$406) -> 8302.0194 | AO99: =AN99+AK99 -> 16565.015 | AP99: =$AO99/$AI99 -> 0.27022096 | AQ99: =AB99+AD99+AH99 -> -27590.536 | AR99: =AQ99+AO99 -> -11025.521 | AS99: =AR99/AI99 -> -0.17985657
A100: [ HGT ] - HIGUEROTE | B100: 0 | C100: =$B100/$AI100 -> 0 | D100: 1600 | E100: =$D100/$AI100 -> 0.013630411 | F100: 0 | G100: =$F100/$AI100 -> 0 | H100: 0 | I100: =$H100/$AI100 -> 0 | J100: 4609.584 | K100: =$J100/$AI100 -> 0.039269079 | M100: =$L100/$AI100 -> 0 | O100: =$N100/$AI100 -> 0 | P100: 412.88 | Q100: =$P100/$AI100 -> 0.0035173276 | R100: 291.29 | S100: =$R100/$AI100 -> 0.0024815016 | U100: =$T100/$AI100 -> 0 | W100: =$V100/$AI100 -> 0 | X100: 80 | Y100: =$X100/$AI100 -> 0.00068152057 | Z100: 250.047 | AA100: =$Z100/$AI100 -> 0.0021301522 | AB100: 7243.801 | AC100: =$AB100/AI100 -> 0.061709992 | AD100: 63244.213 | AE100: =$AD100/$AI100 -> 0.5387779 | AF100: -102091.49 | AG100: -15293.082 | AH100: =SUM(AF100,AG100) -> -117384.57 | AI100: =((AF100+AG100)*-1) -> 117384.57 | AJ100: =AI100/($AI$224) -> 0.0089578814 | AK100: =AJ100*($G$260+$G$313-$B$406) -> 15822.523 | AL100: 38771.712 | AM100: =AL100/AL$224 -> 0.0082286075 | AN100: =(AM100*$B$406) -> 11187.491 | AO100: =AN100+AK100 -> 27010.014 | AP100: =$AO100/$AI100 -> 0.2300985 | AQ100: =AB100+AD100+AH100 -> -46896.558 | AR100: =AQ100+AO100 -> -19886.544 | AS100: =AR100/AI100 -> -0.16941361
...

Sheet Sr. Wilson 4
B4: Total general | C4: Centro de Costo | D4: Total Ingresos | E4: Total Costos | F4: Total Gastos | G4: Monto Ingresos Bs | H4: Factor de ingresos en bs | I4: Gasto Aplicado por Venta | J4: % impacto sobre ingresos generales | K4: Gasto aplicado | L4: Gasto Aplicado Factor Ingreso Bs | M4: Total General CC | N4: Resultado - Gastos Distribuidos
A5: Tienda | C5: [ ABM ] - AV BOLIVAR DE MATURIN | D5: [ ACB ] - AV LIBERTADOR CIUDAD BOLIVAR | E5: [ ACG ] - ACHAGUAS | F5: [ ACO ] - ANACO | G5: [ ADO ] - ALTAGRACIA DEL ORITUCO | H5: [ ADS - BQT ] - AEDOS BARQUISIMETO | I5: [ ADS - TCY ] - AEDOS TOCUYITO | J5: [ ANT ] - ANTIMANO | K5: [ APU ] - APURE | L5: [ ARO - INT ] - AEROPUERTO INTERNACIONAL | M5: [ ARO - NAC ] - AEROPUERTO NACIONAL | N5: [ ARY ] - AROA YARACUY | O5: [ ATV ] - ALTA VISTA | P5: [ AVM ] - AVENIDA MARIÑO | Q5: [ BAC ] - BUENOS AIRES CANGURO | R5: [ BCC ] - BISCUCUY | S5: [ BCD ] - BARINAS CC DORADO | T5: [ BCN ] - BARCELONA | U5: [ BCO ] - BOCONO | V5: [ BJM ] - BEJUMA | W5: [ BLS ] - BAILADORES | X5: [ BNS ] - BARINAS SHOP | Y5: [ BRC ] - BARRANCAS | Z5: [ BTA ] - BARUTA | AA5: [ BVC ] - BAZAR VALENCIA CANGURO | AB5: [ BZC ] - BAZAR 4 | AC5: [ BZD ] - BAZAR 2 | AD5: [ BZT ] - BAZAR 3 | AE5: [ BZU ] - BAZAR 1 | AF5: [ CAG ] - CAGUA | AG5: [ CAT ] - CATIA | AH5: [ CBM ] - CABIMAS | AI5: [ CBQ ] - CHABASQUEN | AJ5: [ CBR ] - CABUDARE | AK5: [ CBV ] - CIUDAD BOLIVAR | AL5: [ CCA ] - CENTRO COMERCIAL AVIADORES | AM5: [ CCB ] - CALLE CAMEJO BARINAS | AN5: [ CCM ] - CENTRO COMERCIAL METROCENTER | AO5: [ CCO ] - CAICARA DEL ORINOCO | AP5: [ CCT ] - CC CIUDAD TAMANACO | AQ5: [ CDL ] - LA CANDELARIA | AR5: [ CDO ] - CEDENO | AS5: [ CEN - MYR ] - CENDIS MAYOR | AT5: [ CEN - SWM ] - CENDIS SHOWROOM | AU5: [ CHA ] - CHACAO | AV5: [ CHC ] - CHICHIRIVICHE | AW5: [ CHI ] - CHIVACOA | AX5: [ CHV ] - CHARALLAVE | AY5: [ CJP ] - CINCO DE JULIO | AZ5: [ CLB ] - CALABOZO | BA5: [ CLL ] - CALLAO | BB5: [ CLP ] - CATIA LIFE PHONE | BC5: [ CLT ] - COLONIA TOVAR | BD5: [ CMC ] - CUA | BE5: [ CMO ] - COMERCIO | BF5: [ CNA ] - CUMANACOA | BG5: [ COD ] - COSMOS SHOP | BH5: [ COE ] - SAN CARLOS | BI5: [ COR ] - CORO | BJ5: [ CPN ] - CARUPANO | BK5: [ CRN ] - CLARINES | BL5: [ CRP ] - CARIPE | BM5: [ CRR ] - CARORA | BN5: [ CRT ] - CARIPITO | BO5: [ CSZ ] - CAJA SECA ZULIA | BP5: [ CTA ] - CANTAURA | BQ5: [ CTD ] - CITY 2 | BR5: [ CTL ] - CARTANAL | BS5: [ CTM ] - CATIA LA MAR | BT5: [ CTO ] - CEMENTERIO | BU5: [ CTS ] - CIUDAD TAMANACO SEGUNDO | BV5: [ CTT ] - CITY 3 | BW5: [ CTU ] - CITY 1 | BX5: [ CUA ] - CUMANA SHOP | BY5: [ CUG ] - CAUCAGUA | BZ5: [ DCA ] - DUACA | CA5: [ ECJ ] - EL CUJI | CB5: [ ECM ] ECOMMERCE | CC5: [ EJD ] - EJIDO | CD5: [ ELZ ] - ELORZA | CE5: [ EMT ] - EL MANTECO | CF5: [ FAM ] - FLOR AMARILLO | CG5: [ FMD ] - FREEMARKET 2 | CH5: [ FOR - CHV ] - FORUM CHARALLAVE | CI5: [ FOR - GTE ] - FORUM GUATIRE | CJ5: [ FOR - ISF ] - FORUM IPSFA | CK5: [ FOR - PRS ] - FORUM PARAISO | CL5: [ FOR - PZV ] - FORUM PLAZA VENEZUELA | CM5: [ FRM ] - FREEMARKET | CN5: [ GCA ] - GUACARA | CO5: [ GIA ] - GUIRIA | CP5: [ GNO ] - GUANARITO | CQ5: [ GNR ] - GUANARE | CR5: [ GNT ] - GUANTA | CS5: [ GPT ] - GUASIPATI | CT5: [ GRA ] - GUARENAS | CU5: [ GTE ] - GUATIRE | CV5: [ GTN ] - GATO NEGRO | CW5: [ HGT ] - HIGUEROTE | CX5: [ IGD ] - CALLE IGUALDAD | CY5: [ LBD ] - LA BANDERA | CZ5: [ LCH ] - LECHERIA | DA5: [ LLN ] - LLANERO | DB5: [ LMU ] - LA MARRON 1 | DC5: [ LPG ] - LA PARAGUA | DD5: [ MCQ ] - MACHIQUES | DE5: [ MCY ] - MARACAY | DF5: [ MDB ] - MINAS DE BARUTA | DG5: [ MEC ] - MARACAY ESTACION CENTRAL | DH5: [ MGT ] - MARGARITA SHOP | DI5: [ MGZ ] - MENE GRANDE ZULIA | DJ5: [ MID ] - MERIDA SHOP | DK5: [ MJN ] - MOJAN | DL5: [ MKD ] - MACROCENTRO 2 SHOP | DM5: [ MKU ] - MACROCENTRO 1 | DN5: [ MNT ] - MONAY TRUJILLO | DO5: [ MOC ] - CANGURO MOVIL | DP5: [ MPC ] - MARKET PLACE CANGURO | DQ5: [ MRN ] - MORON | DR5: [ MTC ] - MANTECAL | DS5: [ MTP ] - METROPOLIS | DT5: [ MUN ] - MATURIN SHOP | DU5: [ MVT - BVT ] MOVISTAR BELLA VISTA | DV5: [ MVT - CCT ] - MOVISTAR CIUDAD TAMANACO | DW5: [ MVT - GRZ ] - MOVISTAR LAS GARZAS | DX5: [ MVT - LNS ] MOVISTAR LOS LEONES | DY5: [ MVT - LVÑ ] MOVISTAR LA VIÑA | DZ5: [ MVT - PCC ] - MOVISTAR PARQUE CENTRAL CANAIMA | EA5: [ MVT - SCB ] MOVISTAR SAN CRISTÓBAL | EB5: [ MVT- LDC ] MOVISTAR LAS DELICIAS | EC5: [ NGA ] - NIRGUA | ED5: [ NGT ] - NAIGUATA | EE5: [ OCT ] - OCUMARE DEL TUY | EF5: [ ODA ] - CIUDAD OJEDA | EG5: [ OPO ] - OSPINO | EH5: [ ORK ] - ORINOKIA | EI5: [ PDB ] - PEDRAZA | EJ5: [ PDM ] - PUNTA DE MATA | EK5: [ PDV - GCA ] - PDVSA GUACARA | EL5: [ PDV - GUO ] - PDVSA GUARAGUO | EM5: [ PDV - LCP ] - PDVSA LA CAMPIÑA | EN5: [ PDV - LGN ] - PDVSA LAGUNA | EO5: [ PDV - MUN ] - PDVSA MATURIN | EP5: [ PDV - PCD ] - PDVSA PETROCEDEÑO | EQ5: [ PDV - PT ] - PDVSA PETROPIAR | ER5: [ PDV - STM ] - PDVSA SANTOME | ES5: [ PFO ] - PUNTO FIJO | ET5: [ PLN ] - PALO NEGRO | EU5: [ PLS ] - PUERTO LA CRUZ SHOP | EV5: [ PML ] - PLAZA MAYOR LECHERIA | EW5: [ PPT ] - PROPATRIA | EX5: [ PRG ] - PARIAGUAN | EY5: [ PRT ] - PUERTO PIRITU | EZ5: [ PSA ] - ACARIGUA | FA5: [ PTA ] - PUERTO AYACUCHO | FB5: [ PTC ] - PUERTO CABELLO | FC5: [ PTT ] - PETARE 3 | FD5: [ PTU ] - PETARE 1 | FE5: [ QBR ] - QUIBOR | FF5: [ QTC ] - QUINTA CRESPO | FG5: [ RCO ] - RIO CHICO | FH5: [ SAM - CDL ] - SAMBIL CANDELARIA | FI5: [ SAM - CHA ] - SAMBIL CHACAO | FJ5: [ SAM - LAR ] - SAMBIL LARA | FK5: [ SAM - MGT ] - SAMBIL MARGARITA | FL5: [ SAM - PFO ] - SAMBIL PUNTO FIJO | FM5: [ SAM - VLC ] - SAMBIL VALENCIA | FN5: [ SAM - ZUL ] - SAMBIL ZULIA | FO5: [ SBB ] - SANTA BARBARA | FP5: [ SBC ] - SABANA CITY | FQ5: [ SBO ] - EL SOMBRERO | FR5: [ SBZ ] - SANTA BARBARA DE ZULIA | FS5: [ SCM ] - SAN CASIMIRO | FT5: [ SCP ] - SOCOPO | FU5: [ SEU ] - SANTA ELENA DE UAIREN | FV5: [ SFX ] - SAN FELIX | FW5: [ SGO ] - SABANA GRANDE OUTLET | FX5: [ SJM ] - SAN JUAN DE LOS MORROS | FY5: [ SMT ] - SABANA MENDOZA | FZ5: [ SMZ ] - SIERRA MAESTRA | GA5: [ SNR ] - SANARE | GB5: [ SNT ] - SABANETA | GC5: [ SRO ] - SAN RAFAEL DE ONOTO | GD5: [ STL ] - SANTA LUCIA | GE5: [ STR ] - SANTA RITA ARAGUA | GF5: [ STT ] - SANTA TERESA DEL TUY | GG5: [ TBD ] - TEMBLADOR | GH5: [ TCC ] - TUCACAS | GI5: [ TCD ] - TUCUPIDO | GJ5: [ TCO ] - TOCUYO | GK5: [ TCP ] - TUCUPITA | GL5: [ TCY ] - TOCUYITO | GM5: [ TED ] - LOS TEQUES DOS | GN5: [ TEQ ] - LOS TEQUES SHOP | GO5: [ TGO ] - EL TIGRITO | GP5: [ TGR ] - TIGRE SHOP | GQ5: [ THA ] - TACHIRA | GR5: [ TJL ] - TRUJILLO | GS5: [ TLG ] - TERMINAL LA GUAIRA | GT5: [ TMO ] - TURMERO | GU5: [ TMR ] - TUMEREMO | GV5: [ TPV ] - TERMINAL PLAZA VENEZUELA | GW5: [ TQO ] - TINAQUILLO | GX5: [ TQT ] - LOS TEQUES TRES | GY5: [ TRN ] - TUREN | GZ5: [ TRU ] - VALERA SHOP | HA5: [ TVR ] - TOVAR MERIDA | HB5: [ UNR ] - UNARE | HC5: [ UPT ] - UPATA | HD5: [ URD ] - URDANETA SHOP | HE5: [ URF ] - URDANETA FIX | HF5: [ VAR ] - LA GUAIRA | HG5: [ VDC ] - VILLA DE CURA | HH5: [ VDP ] - VALLE DE LA PASCUA | HI5: [ VGA ] - LA VEGA | HJ5: [ VIG ] - VIGIA | HK5: [ VLL ] - EL VALLE | HL5: [ VMC ] - VENDING MACHINE CENDIS | HM5: [ VTA ] - LA VICTORIA | HN5: [ YAR ] - SAN FELIPE | HO5: [ YTG ] - YARITAGUA | HP5: [ ZAR ] - ZARAZA | HQ5: TOTAL TIENDAS | HR5: Total general
A6: Ingresos | B6: -13104635 | C6: 0 | D6: -49113.27 | E6: -56941.822 | F6: -118897.04 | G6: -84148.31 | H6: 0 | I6: -19329.091 | J6: -11500.961 | K6: -93567.611 | L6: 0 | M6: 0 | N6: 0 | O6: -40122.602 | P6: -44264.45 | Q6: -45183.114 | R6: -33002.995 | S6: -32495.697 | T6: -79400.272 | U6: -48454.733 | V6: -48640.194 | W6: -2708.08 | X6: -119536.24 | Y6: -38487.902 | Z6: -69038.893 | AA6: -123560.45 | AB6: -48864.91 | AC6: -111554.01 | AD6: -34799.554 | AE6: -59284.435 | AF6: -73461.109 | AG6: -169481.67 | AH6: -85404.813 | AI6: -25744.163 | AJ6: -41022.732 | AK6: -75283.207 | AL6: -47619.012 | AM6: -45967.428 | AN6: -66355.385 | AO6: -45126.979 | AP6: -29754.871 | AQ6: -53673.699 | AR6: -59348.367 | AS6: -5875.665 | AT6: -1301.516 | AU6: -49112.364 | AV6: -20878.607 | AW6: -60254.909 | AX6: -157208.94 | AY6: -56313.509 | AZ6: -99783.666 | BA6: -54482.854 | BB6: -134364.39 | BC6: -50781.631 | BD6: -102073.38 | BE6: -69145.923 | BF6: -69539.894 | BG6: -155358.14 | BH6: -128144.07 | BI6: -151844.61 | BJ6: -149890.23 | BK6: -35530.022 | BL6: -70211.45 | BM6: -111957.11 | BN6: -57594.608 | BO6: -40628.633 | BP6: -50300.204 | BQ6: -28187.352 | BR6: -96366.224 | BS6: -6.86 | BT6: -70396.739 | BU6: -34007.716 | BV6: -114094.92 | BW6: -21226.929 | BX6: -114929.01 | BY6: -62005.021 | BZ6: -40596.278 | CA6: -41082.104 | CB6: -161703.06 | CC6: -39879.878 | CD6: -30930.18 | CE6: -26092.845 | CF6: -45581.903 | CG6: -54528.004 | CH6: -23579.566 | CI6: -41004.461 | CJ6: -30040.282 | CK6: -19222.592 | CL6: -9551.517 | CM6: -76661.24 | CN6: -142570.29 | CO6: -39239.614 | CP6: -30671.963 | CQ6: -91350.184 | CR6: -29652.725 | CS6: -46199.879 | CT6: -143314.7 | CU6: -105200.48 | CV6: -61301.741 | CW6: -117384.57 | CX6: -40636.54 | CY6: -29765.953 | CZ6: -40292.367 | DA6: -31797.513 | DB6: -57206.434 | DC6: -25098.575 | DD6: -23046.213 | DE6: -78368.86 | DF6: -37549.59 | DG6: -31821.147 | DH6: -59533.32 | DI6: -42590.564 | DJ6: -78148.168 | DK6: -43578.559 | DL6: -100690.25 | DM6: -30352.01 | DN6: -41936.214 | DO6: 0 | DP6: -65356.608 | DQ6: -67128.274 | DR6: -37521.306 | DS6: -62085.838 | DT6: -129373.49 | DU6: -3000.01 | DV6: -10597.27 | DW6: -3372.535 | DX6: -4555.45 | DY6: -2718.069 | DZ6: 0 | EA6: -1244.305 | EB6: -2104.868 | EC6: -50712.776 | ED6: -35385.258 | EE6: -155192.36 | EF6: -103454.76 | EG6: -40292.699 | EH6: -62081.192 | EI6: -25257.788 | EJ6: -101147.85 | EK6: 0 | EL6: 0 | EM6: 0 | EN6: 0 | EO6: 0 | EP6: 0 | EQ6: 0 | ER6: 0 | ES6: -82985.01 | ET6: -49007.881 | EU6: -92857.286 | EV6: -37109.968 | EW6: -54494.338 | EX6: -59130.525 | EY6: -66242.593 | EZ6: -112803.25 | FA6: -54619.353 | FB6: -128836.27 | FC6: -131336.48 | FD6: -128160.53 | FE6: -31119.546 | FF6: -29192.04 | FG6: -110422.5 | FH6: -101408.83 | FI6: -69216.712 | FJ6: -82919.549 | FK6: -38981.989 | FL6: -47557.74 | FM6: -35248.029 | FN6: -38331.434 | FO6: -27432.326 | FP6: -116418.42 | FQ6: -82342.434 | FR6: 0 | FS6: -39284.23 | FT6: -20415.727 | FU6: -60935.637 | FV6: -84399.55 | FW6: -57885.144 | FX6: -104563.46 | FY6: -41225.837 | FZ6: -33010.325 | GA6: -27242.861 | GB6: -41388.573 | GC6: -39501.284 | GD6: -54203.226 | GE6: -65878.804 | GF6: -134277.99 | GG6: -69029.558 | GH6: -33425.374 | GI6: -43760.445 | GJ6: -50439.567 | GK6: -127079.17 | GL6: -65210.983 | GM6: -222852.1 | GN6: -101839 | GO6: -78055.547 | GP6: -77181.331 | GQ6: -34937.812 | GR6: -29900.853 | GS6: 0 | GT6: -95041.142 | GU6: -41968.787 | GV6: -33340.744 | GW6: -77568.847 | GX6: -140141.55 | GY6: -71465.28 | GZ6: -66709.025 | HA6: 0 | HB6: -48943.321 | HC6: -78047.974 | HD6: -54235.848 | HE6: -37145.087 | HF6: -292432.48 | HG6: -43567.824 | HH6: -81078.286 | HI6: -50622.908 | HJ6: -42393.78 | HK6: -97748.103 | HL6: -16.379 | HM6: -87088.044 | HN6: -135055.36 | HO6: -47201.749 | HP6: -78871.005 | HQ6: -13104055
A7: Costo Mercancia | B7: 6580207.1 | D7: 22717.278 | E7: 29078.434 | F7: 60262.727 | G7: 41163.746 | I7: 6022.502 | J7: 5543.328 | K7: 49343.272 | O7: 18339.91 | P7: 24877.791 | Q7: 22589.678 | R7: 17173.338 | S7: 16467.36 | T7: 38567.289 | U7: 23941.996 | V7: 24201.919 | W7: 815.361 | X7: 63765.986 | Y7: 19262.203 | Z7: 32236.414 | AA7: 69758.571 | AB7: 28294.648 | AC7: 65230.391 | AD7: 18863.316 | AE7: 33010.969 | AF7: 35349.549 | AG7: 84387.513 | AH7: 43333.13 | AI7: 12712.48 | AJ7: 18104.009 | AK7: 36033.337 | AL7: 20686.388 | AM7: 25348.269 | AN7: 34707.77 | AO7: 22041.84 | AP7: 13100.161 | AQ7: 24757.958 | AR7: 28645.458 | AS7: 2363.826 | AT7: 266.303 | AU7: 19736.182 | AV7: 10575.546 | AW7: 28951.562 | AX7: 82692.782 | AY7: 27746.663 | AZ7: 47243.148 | BA7: 30474.522 | BB7: 71880.752 | BC7: 25911.399 | BD7: 48175.151 | BE7: 35442.021 | BF7: 35552.533 | BG7: 72373.637 | BH7: 66640.882 | BI7: 92403.5 | BJ7: 84520.888 | BK7: 17531.842 | BL7: 32713.817 | BM7: 57872.628 | BN7: 27743.761 | BO7: 20296.178 | BP7: 24390.819 | BQ7: 15333.599 | BR7: 48145.639 | BS7: 13458.454 | BT7: 32697.884 | BU7: 12047.007 | BV7: 56386.21 | BW7: 11018.409 | BX7: 56365.672 | BY7: 31423.223 | BZ7: 19191.459 | CA7: 16865.696 | CB7: 90107.962 | CC7: 18903.991 | CD7: 15509.833 | CE7: 14731.398 | CF7: 21656.617 | CG7: 31638.087 | CH7: 11012.561 | CI7: 19652.865 | CJ7: 13109.82 | CK7: 9208.094 | CL7: 4388.088 | CM7: 38585.936 | CN7: 75540.246 | CO7: 19191.916 | CP7: 16390.728 | CQ7: 47792.078 | CR7: 13106.496 | CS7: 24547.797 | CT7: 69897.668 | CU7: 52479.521 | CV7: 25816.781 | CW7: 63244.213 | CX7: 20221.863 | CY7: 13236.725 | CZ7: 15647.03 | DA7: 11652.525 | DB7: 13463.954 | DC7: 11932.496 | DD7: 13400.297 | DE7: 35314.786 | DF7: 15926.401 | DG7: 16405.623 | DH7: 29007.708 | DI7: 21910.65 | DJ7: 37700.548 | DK7: 22756.239 | DL7: 49632.912 | DM7: 14395.514 | DN7: 20249.29 | DP7: 35849.849 | DQ7: 35267.78 | DR7: 20534.973 | DS7: 28387.059 | DT7: 59392.158 | DU7: 1886.187 | DV7: 6852.378 | DW7: 2019.323 | DX7: 2459.648 | DY7: 1775.674 | EA7: 498.013 | EB7: 1227.4 | EC7: 23651.61 | ED7: 18326.455 | EE7: 83107.283 | EF7: 52878.371 | EG7: 21217.678 | EH7: 27039.458 | EI7: 13146.992 | EJ7: 46064.281 | ES7: 47496.539 | ET7: 22307.845 | EU7: 43266.658 | EV7: 15009.564 | EW7: 25118.36 | EX7: 26872.553 | EY7: 32499.891 | EZ7: 56094.025 | FA7: 29966.566 | FB7: 67358.516 | FC7: 65579.53 | FD7: 65753.803 | FE7: 37024.881 | FF7: 13153.955 | FG7: 56959.795 | FH7: 41939.822 | FI7: 27928.406 | FJ7: 34403.312 | FK7: 17832.716 | FL7: 24777.493 | FM7: 16655.7 | FN7: 17863.361 | FO7: 15004.637 | FP7: 55777.715 | FQ7: 42070.286 | FS7: 19762.803 | FT7: 11268.906 | FU7: 32173.157 | FV7: 41009.259 | FW7: 27366.422 | FX7: 50267.971 | FY7: 20726.248 | FZ7: 16181.528 | GA7: 12278.176 | GB7: 29358.592 | GC7: 21095.881 | GD7: 27731.592 | GE7: 28740.658 | GF7: 72739.899 | GG7: 33923.413 | GH7: 16191.048 | GI7: 19610.862 | GJ7: 24404.089 | GK7: 64615.784 | GL7: 32764.288 | GM7: 114400.23 | GN7: 55930.32 | GO7: 38160.712 | GP7: 34319.898 | GQ7: 17461.64 | GR7: 14612.873 | GT7: 46511.873 | GU7: 23110.182 | GV7: 14235.841 | GW7: 38294.762 | GX7: 70236.793 | GY7: 35403.602 | GZ7: 31458.66 | HB7: 23254.953 | HC7: 36214.627 | HD7: 23043.811 | HE7: 20089.488 | HF7: 157609.18 | HG7: 19767.578 | HH7: 42169.816 | HI7: 21218.465 | HJ7: 20254.493 | HK7: 49794.682 | HL7: 135.72 | HM7: 43425.085 | HN7: 69260.038 | HO7: 21909.735 | HP7: 41189.404 | HQ7: 6580207.1
A8: Gastos | B8: 1424830 | D8: 9865.879 | E8: 4713.688 | F8: 7403.344 | G8: 5414.652 | I8: 25121.691 | J8: 6722.854 | K8: 7256.201 | O8: 310.188 | P8: 4065.688 | Q8: 5359.375 | R8: 8264.593 | S8: 3561.329 | T8: 7330.502 | U8: 6102.949 | V8: 6610.181 | W8: 384.006 | X8: 11196.559 | Y8: 4028.58 | Z8: 11531.063 | AA8: 11074.405 | AB8: 4805.209 | AC8: 5421.801 | AD8: 4141.908 | AE8: 4392.319 | AF8: 5875.301 | AG8: 15884.699 | AH8: 7374.813 | AI8: 5204.971 | AJ8: 5416.732 | AK8: 9732.211 | AL8: 7890.009 | AM8: 3676.278 | AN8: 5319.129 | AO8: 5206.288 | AP8: 4625.305 | AQ8: 9951.566 | AR8: 5266.013 | AS8: 808.31 | AT8: 0 | AU8: 5047.858 | AV8: 3995.675 | AW8: 4390.999 | AX8: 11267.249 | AY8: 5043.989 | AZ8: 7609.76 | BA8: 12015.378 | BB8: 15583.996 | BC8: 14727.687 | BD8: 8269.654 | BE8: 12783.126 | BF8: 5085.302 | BG8: 21234.737 | BH8: 8744.798 | BI8: 6774.854 | BJ8: 7884.375 | BK8: 4756.569 | BL8: 3972.61 | BM8: 6808.029 | BN8: 4245.857 | BO8: 6364.7 | BP8: 4406.171 | BQ8: 3506.063 | BR8: 6071.371 | BS8: 6695.99 | BT8: 12371.273 | BU8: 5232.203 | BV8: 12667.763 | BW8: 4103.591 | BX8: 9890.252 | BY8: 19480.882 | BZ8: 4080.293 | CA8: 5310.243 | CB8: 3148.116 | CC8: 4017.063 | CD8: 4548.703 | CE8: 7739.264 | CF8: 5107.668 | CG8: 6268.238 | CH8: 1930.891 | CI8: 3115.533 | CJ8: 3480.066 | CK8: 2037.041 | CL8: 2459.308 | CM8: 5349.196 | CN8: 10092.693 | CO8: 3015.642 | CP8: 4547.339 | CQ8: 10226.648 | CR8: 3117.619 | CS8: 5297.961 | CT8: 31234.589 | CU8: 7221.807 | CV8: 7894.424 | CW8: 7243.801 | CX8: 6906.553 | CY8: 4617.671 | CZ8: 7795.629 | DA8: 5487.255 | DB8: 7347.764 | DC8: 4146.662 | DD8: 6283.246 | DE8: 10516.311 | DF8: 6883.232 | DG8: 3113.481 | DH8: 9662.989 | DI8: 4111.704 | DJ8: 9318.572 | DK8: 7453.626 | DL8: 12278.268 | DM8: 3364.301 | DN8: 2818.432 | DP8: 14291.882 | DQ8: 4788.696 | DR8: 9717.43 | DS8: 5898.692 | DT8: 10327.111 | DU8: 646.374 | DV8: 1089.902 | DW8: 601.95 | DX8: 467.574 | DY8: 771.758 | EA8: 874.746 | EB8: 336.59 | EC8: 2685.394 | ED8: 4863.25 | EE8: 17585.642 | EF8: 7948.103 | EG8: 6348.238 | EH8: 6088.646 | EI8: 4762.469 | EJ8: 5872.642 | ES8: 8033.46 | ET8: 7653.496 | EU8: 11613.352 | EV8: 3551.383 | EW8: 7815.801 | EX8: 5709.48 | EY8: 5439.069 | EZ8: 16220.757 | FA8: 10647.372 | FB8: 11155.528 | FC8: 14047.84 | FD8: 10405.618 | FE8: 4299.995 | FF8: 4214.133 | FG8: 7897.046 | FH8: 8260.51 | FI8: 10072.91 | FJ8: 8244.951 | FK8: 5275.453 | FL8: 4035.639 | FM8: 4939.129 | FN8: 5555.771 | FO8: 3190.903 | FP8: 13581.793 | FQ8: 5370.968 | FS8: 5152.982 | FT8: 4271.638 | FU8: 4427.324 | FV8: 7764.454 | FW8: 8847.696 | FX8: 8392.358 | FY8: 5010.784 | FZ8: 4185.777 | GA8: 3993.56 | GB8: 4197.663 | GC8: 4828.185 | GD8: 4002.715 | GE8: 5636.298 | GF8: 8151.631 | GG8: 4356.927 | GH8: 5406.604 | GI8: 3469.474 | GJ8: 3303.508 | GK8: 6157.911 | GL8: 17802.287 | GM8: 11795.869 | GN8: 10887.707 | GO8: 4602.47 | GP8: 11045.519 | GQ8: 8807.622 | GR8: 5059.406 | GT8: 8208.715 | GU8: 7659.603 | GV8: 4338.541 | GW8: 5153.692 | GX8: 9576.082 | GY8: 7578.916 | GZ8: 7496.207 | HB8: 4040.703 | HC8: 5598.669 | HD8: 6700.542 | HE8: 13404.27 | HF8: 12176.027 | HG8: 4864.428 | HH8: 7232.546 | HI8: 7328.282 | HJ8: 4774.729 | HK8: 9088.694 | HL8: 0 | HM8: 8470.171 | HN8: 7048.558 | HO8: 5247.549 | HP8: 5389.218 | HQ8: 1411862.5
A9: Ingresos en bolivares | B9: 4711819.3 | D9: 15353.841 | E9: 22324.722 | F9: 42151.387 | G9: 32162.211 | I9: 14498.62 | J9: 4371.0637 | K9: 35382.82 | O9: 13621.013 | P9: 14473.401 | Q9: 15150.12 | R9: 12384.42 | S9: 11290.267 | T9: 29744.153 | U9: 22349.9 | V9: 17717.493 | W9: 1079.4016 | X9: 41233.126 | Y9: 17686.951 | Z9: 28880.64 | AA9: 28062.578 | AB9: 10395.796 | AC9: 23517.646 | AD9: 8313.2578 | AE9: 14567.642 | AF9: 24410.196 | AG9: 66747.561 | AH9: 29725.609 | AI9: 8589.9372 | AJ9: 15263.332 | AK9: 27392.171 | AL9: 16151.289 | AM9: 14810.77 | AN9: 27201.271 | AO9: 17926.354 | AP9: 16305.29 | AQ9: 23225.524 | AR9: 16868.372 | AS9: 0 | AT9: 567.95748 | AU9: 22160.282 | AV9: 6894.6023 | AW9: 21574.338 | AX9: 52989.882 | AY9: 18650.024 | AZ9: 34385.264 | BA9: 13155.669 | BB9: 56254.537 | BC9: 22182.917 | BD9: 36908.133 | BE9: 18294.676 | BF9: 27408.169 | BG9: 58393.584 | BH9: 55876.535 | BI9: 49508.298 | BJ9: 50936.7 | BK9: 14105.73 | BL9: 27229.345 | BM9: 36927.909 | BN9: 21052.699 | BO9: 17511.119 | BP9: 18723.707 | BQ9: 8375.3104 | BR9: 32014.716 | BS9: 0 | BT9: 28498.374 | BU9: 16893.655 | BV9: 41472.56 | BW9: 8097.1871 | BX9: 44863.167 | BY9: 19624.176 | BZ9: 16414.118 | CA9: 16536.36 | CB9: 50962.396 | CC9: 15768.793 | CD9: 8527.4539 | CE9: 4813.8627 | CF9: 14069.196 | CG9: 10417.476 | CH9: 7306.2744 | CI9: 12018.982 | CJ9: 12486.084 | CK9: 6447.6285 | CL9: 2953.9045 | CM9: 23390.018 | CN9: 42546.14 | CO9: 17354.7 | CP9: 10449.199 | CQ9: 30386.45 | CR9: 10528.27 | CS9: 12485.153 | CT9: 43893.713 | CU9: 37555.026 | CV9: 28771.732 | CW9: 38771.712 | CX9: 13369.082 | CY9: 12003.426 | CZ9: 19265.908 | DA9: 18075.9 | DB9: 23305.294 | DC9: 6768.9301 | DD9: 4461.428 | DE9: 26187.194 | DF9: 13899.826 | DG9: 9655.3086 | DH9: 18895.736 | DI9: 16535.553 | DJ9: 26015.042 | DK9: 13838.284 | DL9: 34435.89 | DM9: 9563.2612 | DN9: 19106.825 | DP9: 23568.998 | DQ9: 25732.511 | DR9: 14127.391 | DS9: 23414.13 | DT9: 42539.451 | DU9: 1060.0735 | DV9: 5008.7604 | DW9: 904.8707 | DX9: 1426.8887 | DY9: 597.50001 | EA9: 310.52479 | EB9: 684.32036 | EC9: 21151.202 | ED9: 16357.286 | EE9: 50589.85 | EF9: 37508.998 | EG9: 14679.118 | EH9: 22553.039 | EI9: 7055.552 | EJ9: 36887.604 | ES9: 24376.924 | ET9: 17082.084 | EU9: 35403.301 | EV9: 14037.1 | EW9: 23741.014 | EX9: 29230.769 | EY9: 27111.495 | EZ9: 41167.766 | FA9: 19830.952 | FB9: 37964.913 | FC9: 48971.367 | FD9: 44292.25 | FE9: 20819.301 | FF9: 15099.444 | FG9: 41247.666 | FH9: 40786.852 | FI9: 35517.561 | FJ9: 34068.079 | FK9: 10159.404 | FL9: 14212.911 | FM9: 11859.282 | FN9: 12940.573 | FO9: 6310.7841 | FP9: 40779.074 | FQ9: 32093.973 | FS9: 13236.84 | FT9: 5202.7338 | FU9: 2712.5109 | FV9: 27302.274 | FW9: 20903.87 | FX9: 37988.732 | FY9: 17909.722 | FZ9: 9870.4649 | GA9: 10228.943 | GB9: 20735.829 | GC9: 15569.001 | GD9: 19172.45 | GE9: 20105.446 | GF9: 45742.334 | GG9: 27140.866 | GH9: 9749.8238 | GI9: 17739.319 | GJ9: 17736.641 | GK9: 56758.162 | GL9: 21433.106 | GM9: 70937.346 | GN9: 31715.485 | GO9: 27646.12 | GP9: 29300.992 | GQ9: 8322.7293 | GR9: 11695.436 | GT9: 33906.191 | GU9: 10285.604 | GV9: 12452.6 | GW9: 25208.408 | GX9: 42384.713 | GY9: 29077.669 | GZ9: 24566.596 | HB9: 15445.216 | HC9: 24486.75 | HD9: 27488.563 | HE9: 14632.935 | HF9: 162761.28 | HG9: 16962.136 | HH9: 28154.277 | HI9: 22042.119 | HJ9: 13257.721 | HK9: 44292.634 | HL9: 0 | HM9: 27793.156 | HN9: 43546.162 | HO9: 16337.196 | HP9: 31518.407 | HQ9: 4711819.3
A10: Factor ingresos en Bs | B10: 1 | D10: 0.0032585803 | E10: 0.0047380258 | F10: 0.0089458836 | G10: 0.0068258583 | I10: 0.0030770746 | J10: 0.00092768068 | K10: 0.0075093754 | O10: 0.0028908181 | P10: 0.0030717225 | Q10: 0.0032153439 | R10: 0.0026283732 | S10: 0.0023961588 | T10: 0.0063126685 | U10: 0.0047433694 | V10: 0.0037602233 | W10: 0.00022908383 | X10: 0.0087509989 | Y10: 0.0037537413 | Z10: 0.0061294032 | AA10: 0.005955784 | AB10: 0.0022063232 | AC10: 0.0049912028 | AD10: 0.0017643414 | AE10: 0.0030917233 | AF10: 0.0051806308 | AG10: 0.014165985 | AH10: 0.0063087327 | AI10: 0.0018230617 | AJ10: 0.0032393712 | AK10: 0.005813502 | AL10: 0.0034278242 | AM10: 0.0031433229 | AN10: 0.0057729868 | AO10: 0.0038045504 | AP10: 0.0034605084 | AQ10: 0.0049292052 | AR10: 0.0035800124 | AS10: 0 | AT10: 0.00012053889 | AU10: 0.0047031265 | AV10: 0.0014632569 | AW10: 0.0045787701 | AX10: 0.011246162 | AY10: 0.0039581366 | AZ10: 0.0072976619 | BA10: 0.0027920571 | BB10: 0.011939027 | BC10: 0.0047079302 | BD10: 0.0078330959 | BE10: 0.0038827203 | BF10: 0.0058168973 | BG10: 0.012393002 | BH10: 0.011858803 | BI10: 0.010507257 | BJ10: 0.01081041 | BK10: 0.0029936907 | BL10: 0.0057789451 | BM10: 0.007837293 | BN10: 0.0044680616 | BO10: 0.0037164241 | BP10: 0.0039737743 | BQ10: 0.0017775109 | BR10: 0.0067945551 | BS10: 0 | BT10: 0.006048274 | BU10: 0.0035853784 | BV10: 0.0088018146 | BW10: 0.0017184842 | BX10: 0.0095214108 | BY10: 0.004164883 | BZ10: 0.0034836051 | CA10: 0.0035095487 | CB10: 0.010815864 | CC10: 0.0033466463 | CD10: 0.0018098007 | CE10: 0.0010216569 | CF10: 0.002985937 | CG10: 0.0022109243 | CH10: 0.001550627 | CI10: 0.0025508156 | CJ10: 0.0026499496 | CK10: 0.0013683947 | CL10: 0.00062691379 | CM10: 0.0049641162 | CN10: 0.0090296629 | CO10: 0.003683227 | CP10: 0.0022176571 | CQ10: 0.0064489846 | CR10: 0.0022344383 | CS10: 0.002649752 | CT10: 0.0093156612 | CU10: 0.0079703875 | CV10: 0.0061062894 | CW10: 0.0082286075 | CX10: 0.0028373503 | CY10: 0.0025475141 | CZ10: 0.0040888469 | DA10: 0.0038362889 | DB10: 0.004946135 | DC10: 0.0014365853 | DD10: 0.00094685889 | DE10: 0.0055577671 | DF10: 0.0029499914 | DG10: 0.0020491678 | DH10: 0.0040102846 | DI10: 0.0035093777 | DJ10: 0.0055212308 | DK10: 0.0029369301 | DL10: 0.0073084063 | DM10: 0.0020296324 | DN10: 0.0040550843 | DP10: 0.0050021014 | DQ10: 0.0054612686 | DR10: 0.0029982879 | DS10: 0.0049692334 | DT10: 0.0090282432 | DU10: 0.00022498177 | DV10: 0.0010630205 | DW10: 0.00019204274 | DX10: 0.00030283179 | DY10: 0.00012680877 | EA10: 6.5903373e-05 | EB10: 0.00014523485 | EC10: 0.0044889671 | ED10: 0.0034715436 | EE10: 0.010736798 | EF10: 0.0079606189 | EG10: 0.0031153822 | EH10: 0.0047864821 | EI10: 0.0014974157 | EJ10: 0.0078287391 | ES10: 0.0051735693 | ET10: 0.0036253691 | EU10: 0.0075137221 | EV10: 0.0029791252 | EW10: 0.0050386088 | EX10: 0.0062037118 | EY10: 0.0057539335 | EZ10: 0.0087371274 | FA10: 0.0042087676 | FB10: 0.0080573789 | FC10: 0.010393303 | FD10: 0.0094002437 | FE10: 0.0044185271 | FF10: 0.0032045889 | FG10: 0.0087540848 | FH10: 0.0086562853 | FI10: 0.0075379717 | FJ10: 0.0072303449 | FK10: 0.0021561532 | FL10: 0.0030164381 | FM10: 0.0025169221 | FN10: 0.0027464069 | FO10: 0.0013393519 | FP10: 0.0086546345 | FQ10: 0.006811376 | FS10: 0.0028092842 | FT10: 0.0011041879 | FU10: 0.00057568228 | FV10: 0.005794423 | FW10: 0.0044364753 | FX10: 0.0080624339 | FY10: 0.0038010206 | FZ10: 0.0020948309 | GA10: 0.0021709116 | GB10: 0.0044008116 | GC10: 0.003304244 | GD10: 0.004069012 | GE10: 0.0042670241 | GF10: 0.0097079982 | GG10: 0.0057601671 | GH10: 0.002069227 | GI10: 0.0037648556 | GJ10: 0.0037642872 | GK10: 0.012045912 | GL10: 0.0045487962 | GM10: 0.015055192 | GN10: 0.0067310487 | GO10: 0.0058673983 | GP10: 0.0062186154 | GQ10: 0.0017663515 | GR10: 0.0024821487 | GT10: 0.007195987 | GU10: 0.0021829368 | GV10: 0.0026428432 | GW10: 0.0053500371 | GX10: 0.0089954028 | GY10: 0.0061712189 | GZ10: 0.0052138239 | HB10: 0.0032779729 | HC10: 0.005196878 | HD10: 0.0058339595 | HE10: 0.0031055807 | HF10: 0.034543193 | HG10: 0.0035999121 | HH10: 0.0059752454 | HI10: 0.0046780485 | HJ10: 0.002813716 | HK10: 0.0094003252 | HL10: 0 | HM10: 0.0058986039 | HN10: 0.0092418999 | HO10: 0.0034672798 | HP10: 0.0066892224 | HQ10: 1
A11: Gasto Aplicado por Venta | B11: 1765897.7 | D11: 6620.085 | E11: 7675.3127 | F11: 16026.392 | G11: 11342.535 | I11: 2605.4104 | J11: 1550.2397 | K11: 12612.183 | O11: 5408.2132 | P11: 5966.502 | Q11: 6090.3307 | R11: 4448.5458 | S11: 4380.166 | T11: 10702.536 | U11: 6531.3194 | V11: 6556.3181 | W11: 365.02802 | X11: 16112.552 | Y11: 5187.8685 | Z11: 9305.9033 | AA11: 16654.984 | AB11: 6586.608 | AC11: 15036.609 | AD11: 4690.708 | AE11: 7991.0786 | AF11: 9901.9835 | AG11: 22844.805 | AH11: 11511.901 | AI11: 3470.112 | AJ11: 5529.5437 | AK11: 10147.588 | AL11: 6418.6707 | AM11: 6196.0501 | AN11: 8944.1874 | AO11: 6082.7642 | AP11: 4010.7241 | AQ11: 7234.7952 | AR11: 7999.6961 | AS11: 791.99373 | AT11: 175.43419 | AU11: 6619.9629 | AV11: 2814.2731 | AW11: 8121.8909 | AX11: 21190.537 | AY11: 7590.621 | AZ11: 13450.058 | BA11: 7343.863 | BB11: 18111.271 | BC11: 6844.9671 | BD11: 13758.694 | BE11: 9320.3301 | BF11: 9373.4343 | BG11: 20941.064 | BH11: 17272.819 | BI11: 20467.467 | BJ11: 20204.032 | BK11: 4789.1693 | BL11: 9463.9548 | BM11: 15090.944 | BN11: 7763.3031 | BO11: 5476.4223 | BP11: 6780.0745 | BQ11: 3799.4348 | BR11: 12989.414 | BS11: 0.9246744 | BT11: 9488.9303 | BU11: 4583.9744 | BV11: 15379.104 | BW11: 2861.2242 | BX11: 15491.532 | BY11: 8357.7923 | BZ11: 5472.0611 | CA11: 5537.5466 | CB11: 21796.309 | CC11: 5375.4959 | CD11: 4169.1466 | CE11: 3517.1116 | CF11: 6144.0844 | CG11: 7349.9489 | CH11: 3178.3412 | CI11: 5527.0809 | CJ11: 4049.1953 | CK11: 2591.0552 | CL11: 1287.4699 | CM11: 10333.336 | CN11: 19217.361 | CO11: 5289.1934 | CP11: 4134.3409 | CQ11: 12313.291 | CR11: 3996.9556 | CS11: 6227.3827 | CT11: 19317.702 | CU11: 14180.202 | CV11: 8262.9957 | CW11: 15822.523 | CX11: 5477.4881 | CY11: 4012.2179 | CZ11: 5431.0962 | DA11: 4286.0563 | DB11: 7710.9803 | DC11: 3383.0918 | DD11: 3106.4494 | DE11: 10563.51 | DF11: 5061.3913 | DG11: 4289.242 | DH11: 8024.6264 | DI11: 5740.8752 | DJ11: 10533.762 | DK11: 5874.0492 | DL11: 13572.259 | DM11: 4091.2138 | DN11: 5652.674 | DP11: 8809.5601 | DQ11: 9048.3668 | DR11: 5057.5789 | DS11: 8368.6858 | DT11: 17438.536 | DU11: 404.37791 | DV11: 1428.4292 | DW11: 454.59137 | DX11: 614.03906 | DY11: 366.37446 | EA11: 167.72259 | EB11: 283.71976 | EC11: 6835.6859 | ED11: 4769.6563 | EE11: 20918.718 | EF11: 13944.894 | EG11: 5431.141 | EH11: 8368.0596 | EI11: 3404.5525 | EJ11: 13633.94 | ES11: 11185.731 | ET11: 6605.8794 | EU11: 12516.437 | EV11: 5002.1337 | EW11: 7345.411 | EX11: 7970.3327 | EY11: 8928.9839 | EZ11: 15204.996 | FA11: 7362.262 | FB11: 17366.122 | FC11: 17703.132 | FD11: 17275.038 | FE11: 4194.6716 | FF11: 3934.8589 | FG11: 14884.09 | FH11: 13669.118 | FI11: 9329.8719 | FJ11: 11176.907 | FK11: 5254.4675 | FL11: 6410.4117 | FM11: 4751.1589 | FN11: 5166.7778 | FO11: 3697.6632 | FP11: 15692.294 | FQ11: 11099.117 | FS11: 5295.2072 | FT11: 2751.8805 | FU11: 8213.6477 | FV11: 11376.4 | FW11: 7802.4651 | FX11: 14094.337 | FY11: 5556.9207 | FZ11: 4449.5339 | GA11: 3672.1248 | GB11: 5578.8562 | GC11: 5324.4644 | GD11: 7306.1713 | GE11: 8879.948 | GF11: 18099.623 | GG11: 9304.645 | GH11: 4505.4792 | GI11: 5898.566 | GJ11: 6798.8595 | GK11: 17129.279 | GL11: 8789.931 | GM11: 30038.722 | GN11: 13727.101 | GO11: 10521.278 | GP11: 10403.44 | GQ11: 4709.3441 | GR11: 4030.4013 | GT11: 12810.803 | GU11: 5657.0646 | GV11: 4494.0718 | GW11: 10455.674 | GX11: 18889.986 | GY11: 9632.9613 | GZ11: 8991.8553 | HB11: 6597.1772 | HC11: 10520.257 | HD11: 7310.5685 | HE11: 5006.8675 | HF11: 39417.614 | HG11: 5872.6022 | HH11: 10928.719 | HI11: 6823.5724 | HJ11: 5714.3503 | HK11: 13175.68 | HL11: 2.2077612 | HM11: 11738.788 | HN11: 18204.407 | HO11: 6362.4269 | HP11: 10631.195 | HQ11: 1766324.2
A12: Impacto sobre Ingresos Generales | B12: 1 | D12: 0.0037479444 | E12: 0.0043453588 | F12: 0.0090733015 | G12: 0.0064215473 | I12: 0.0014750465 | J12: 0.00087766427 | K12: 0.0071403554 | O12: 0.0030618462 | P12: 0.00337792 | Q12: 0.0034480253 | R12: 0.002518533 | S12: 0.0024798199 | T12: 0.0060592138 | U12: 0.0036976899 | V12: 0.0037118429 | W12: 0.00020665969 | X12: 0.0091220803 | Y12: 0.0029370986 | Z12: 0.0052685136 | AA12: 0.0094291768 | AB12: 0.0037289915 | AC12: 0.008512938 | AD12: 0.0026556324 | AE12: 0.0045241289 | AF12: 0.0056059829 | AG12: 0.012933528 | AH12: 0.0065174339 | AI12: 0.0019645951 | AJ12: 0.0031305372 | AK12: 0.0057450313 | AL12: 0.0036339142 | AM12: 0.0035078781 | AN12: 0.0050637291 | AO12: 0.0034437415 | AP12: 0.0022706613 | AQ12: 0.004095961 | AR12: 0.0045290077 | AS12: 0.00044838525 | AT12: 9.9321621e-05 | AU12: 0.0037478752 | AV12: 0.0015932936 | AW12: 0.004598188 | AX12: 0.011996969 | AY12: 0.0042974109 | AZ12: 0.0076147166 | BA12: 0.0041577095 | BB12: 0.01025365 | BC12: 0.0038752608 | BD12: 0.0077894496 | BE12: 0.0052766813 | BF12: 0.0053067461 | BG12: 0.01185573 | BH12: 0.009778963 | BI12: 0.011587605 | BJ12: 0.011438461 | BK12: 0.0027113761 | BL12: 0.0053579941 | BM12: 0.0085436995 | BN12: 0.0043951744 | BO12: 0.0031004626 | BP12: 0.003838522 | BQ12: 0.0021510404 | BR12: 0.0073539239 | BS12: 5.2350207e-07 | BT12: 0.0053721339 | BU12: 0.0025952055 | BV12: 0.0087068406 | BW12: 0.0016198748 | BX12: 0.0087704917 | BY12: 0.004731743 | BZ12: 0.0030979935 | CA12: 0.003135068 | CB12: 0.012339925 | CC12: 0.0030433234 | CD12: 0.0023603518 | CE12: 0.0019912038 | CF12: 0.0034784578 | CG12: 0.0041611549 | CH12: 0.0017994099 | CI12: 0.0031291429 | CJ12: 0.0022924417 | CK12: 0.0014669193 | CL12: 0.0007288978 | CM12: 0.0058501921 | CN12: 0.01087986 | CO12: 0.0029944634 | CP12: 0.0023406467 | CQ12: 0.0069711385 | CR12: 0.0022628663 | CS12: 0.0035256169 | CT12: 0.010936668 | CU12: 0.0080280856 | CV12: 0.0046780741 | CW12: 0.0089578814 | CX12: 0.003101066 | CY12: 0.002271507 | CZ12: 0.0030748014 | DA12: 0.0024265399 | DB12: 0.004365552 | DC12: 0.0019153289 | DD12: 0.0017587085 | DE12: 0.0059805044 | DF12: 0.0028654939 | DG12: 0.0024283435 | DH12: 0.0045431219 | DI12: 0.003250182 | DJ12: 0.0059636629 | DK12: 0.0033255781 | DL12: 0.0076839001 | DM12: 0.0023162303 | DN12: 0.0032002471 | DP12: 0.0049875101 | DQ12: 0.00512271 | DR12: 0.0028633355 | DS12: 0.0047379103 | DT12: 0.0098727828 | DU12: 0.00022893753 | DV12: 0.00080870157 | DW12: 0.00025736575 | DX12: 0.00034763666 | DY12: 0.00020742197 | EA12: 9.4955721e-05 | EB12: 0.00016062722 | EC12: 0.0038700063 | ED12: 0.0027003288 | EE12: 0.011843079 | EF12: 0.0078948664 | EG12: 0.0030748267 | EH12: 0.0047375558 | EI12: 0.0019274788 | EJ12: 0.0077188207 | ES12: 0.0063327732 | ET12: 0.0037399019 | EU12: 0.0070861489 | EV12: 0.0028319453 | EW12: 0.0041585858 | EX12: 0.0045123837 | EY12: 0.0050551217 | EZ12: 0.0086082702 | FA12: 0.004168126 | FB12: 0.009831786 | FC12: 0.010022583 | FD12: 0.0097802189 | FE12: 0.0023748027 | FF12: 0.0022277104 | FG12: 0.0084265899 | FH12: 0.0077387367 | FI12: 0.0052820834 | FJ12: 0.0063277778 | FK12: 0.0029748035 | FL12: 0.0036292384 | FM12: 0.0026898566 | FN12: 0.0029251582 | FO12: 0.0020934227 | FP12: 0.0088841523 | FQ12: 0.0062837368 | FS12: 0.0029978682 | FT12: 0.0015579702 | FU12: 0.0046501359 | FV12: 0.00644072 | FW12: 0.0044173459 | FX12: 0.007979473 | FY12: 0.0031460366 | FZ12: 0.0025190923 | GA12: 0.0020789642 | GB12: 0.0031584553 | GC12: 0.0030144321 | GD12: 0.0041363704 | GE12: 0.0050273601 | GF12: 0.010247056 | GG12: 0.0052678012 | GH12: 0.0025507657 | GI12: 0.0033394582 | GJ12: 0.0038491571 | GK12: 0.0096976978 | GL12: 0.0049763972 | GM12: 0.017006347 | GN12: 0.0077715634 | GO12: 0.0059565948 | GP12: 0.0058898814 | GQ12: 0.0026661832 | GR12: 0.0022818015 | GT12: 0.0072528039 | GU12: 0.0032027328 | GV12: 0.0025443074 | GW12: 0.0059194536 | GX12: 0.010694518 | GY12: 0.0054536767 | GZ12: 0.0050907161 | HB12: 0.0037349752 | HC12: 0.0059560169 | HD12: 0.0041388599 | HE12: 0.0028346254 | HF12: 0.022316182 | HG12: 0.0033247589 | HH12: 0.0061872668 | HI12: 0.0038631483 | HJ12: 0.003235165 | HK12: 0.0074593782 | HL12: 1.2499184e-06 | HM12: 0.006645885 | HN12: 0.010306379 | HO12: 0.0036020719 | HP12: 0.0060188242 | HQ12: 1
A13: Gasto Aplicado Total | B13: 3125482.7 | D13: 11050.402 | E13: 14117.061 | F13: 28189.081 | G13: 20622.869 | I13: 6788.9549 | J13: 2811.5004 | K13: 22821.817 | O13: 9338.5261 | P13: 10142.77 | Q13: 10461.864 | R13: 8022.0427 | S13: 7637.9476 | T13: 19285.146 | U13: 12980.333 | V13: 11668.661 | W13: 676.48697 | X13: 28010.278 | Y13: 10291.399 | Z13: 17639.348 | AA13: 24752.378 | AB13: 9586.292 | AC13: 21822.573 | AD13: 7089.48 | AE13: 12194.539 | AF13: 16945.491 | AG13: 42104.665 | AH13: 20089.16 | AI13: 5948.7193 | AJ13: 9933.7442 | AK13: 18051.538 | AL13: 11079.089 | AM13: 10469.665 | AN13: 16793.054 | AO13: 11255.374 | AP13: 8715.5794 | AQ13: 13936.469 | AR13: 12867.027 | AS13: 791.99373 | AT13: 339.31706 | AU13: 13014.263 | AV13: 4803.6953 | AW13: 14347.118 | AX13: 36480.65 | AY13: 12972.044 | AZ13: 23371.85 | BA13: 11139.902 | BB13: 34343.392 | BC13: 13245.798 | BD13: 24408.453 | BE13: 14599.218 | BF13: 17282.001 | BG13: 37790.403 | BH13: 33395.869 | BI13: 34752.977 | BJ13: 34901.703 | BK13: 8859.3463 | BL13: 17320.922 | BM13: 25746.41 | BN13: 13838.013 | BO13: 10529.217 | BP13: 12182.758 | BQ13: 6216.112 | BR13: 22227.189 | BS13: 0.9246744 | BT13: 17712.073 | BU13: 9458.601 | BV13: 27345.919 | BW13: 5197.6495 | BX13: 28436.699 | BY13: 14020.305 | BZ13: 10208.318 | CA13: 10309.076 | CB13: 36501.395 | CC13: 9925.546 | CD13: 6629.7244 | CE13: 4906.141 | CF13: 10203.719 | CG13: 10355.888 | CH13: 5286.5505 | CI13: 8995.1316 | CJ13: 7652.027 | CK13: 4451.5041 | CL13: 2139.8124 | CM13: 17082.474 | CN13: 31493.955 | CO13: 10296.853 | CP13: 7149.4342 | CQ13: 21081.234 | CR13: 7034.8644 | CS13: 9829.9458 | CT13: 31983.135 | CU13: 25016.621 | CV13: 16565.015 | CW13: 27010.014 | CX13: 9335.1069 | CY13: 7475.7798 | CZ13: 10990.231 | DA13: 9501.8171 | DB13: 14435.671 | DC13: 5336.2515 | DD13: 4393.7846 | DE13: 18119.767 | DF13: 9072.1553 | DG13: 7075.2598 | DH13: 13476.949 | DI13: 10512.172 | DJ13: 18040.345 | DK13: 9867.0553 | DL13: 23508.659 | DM13: 6850.6716 | DN13: 11165.906 | DP13: 15610.342 | DQ13: 16473.426 | DR13: 9134.0061 | DS13: 15124.781 | DT13: 29713.2 | DU13: 710.25975 | DV13: 2873.6959 | DW13: 715.68979 | DX13: 1025.7646 | DY13: 538.78176 | EA13: 257.32383 | EB13: 481.17888 | EC13: 12938.818 | ED13: 9489.5149 | EE13: 35516.307 | EF13: 24768.032 | EG13: 9666.7679 | EH13: 14875.689 | EI13: 5440.4163 | EJ13: 24277.776 | ES13: 18219.638 | ET13: 11534.877 | EU13: 22731.98 | EV13: 9052.5076 | EW13: 14195.828 | EX13: 16404.806 | EY13: 16751.946 | EZ13: 27083.864 | FA13: 13084.439 | FB13: 28320.813 | FC13: 31833.711 | FD13: 30055.468 | FE13: 10202.035 | FF13: 8291.7698 | FG13: 26786.012 | FH13: 25438.074 | FI13: 19578.385 | FJ13: 21007.176 | FK13: 8185.9411 | FL13: 10511.516 | FM13: 8173.1284 | FN13: 8900.7513 | FO13: 5518.6259 | FP13: 27459.005 | FQ13: 20359.761 | FS13: 9114.6679 | FT13: 4253.1177 | FU13: 8996.3367 | FV13: 19254.41 | FW13: 13834.23 | FX13: 25055.901 | FY13: 10724.731 | FZ13: 7297.6346 | GA13: 6623.6637 | GB13: 11562.134 | GC13: 9816.865 | GD13: 12838.339 | GE13: 14681.33 | GF13: 31298.472 | GG13: 17136.082 | GH13: 7318.7692 | GI13: 11017.207 | GJ13: 11916.728 | GK13: 33506.72 | GL13: 14974.406 | GM13: 50507.536 | GN13: 22878.534 | GO13: 18498.504 | GP13: 18858.177 | GQ13: 7110.8491 | GR13: 7405.0934 | GT13: 22594.359 | GU13: 8624.9527 | GV13: 8087.2418 | GW13: 17729.505 | GX13: 31120 | GY13: 18023.258 | GZ13: 16080.492 | HB13: 11053.86 | HC13: 17585.854 | HD13: 15242.332 | HE13: 9229.1684 | HF13: 86382.02 | HG13: 10766.989 | HH13: 19052.573 | HI13: 13183.777 | HJ13: 9539.8363 | HK13: 25956.222 | HL13: 2.2077612 | HM13: 19758.441 | HN13: 30769.556 | HO13: 11076.489 | HP13: 19725.762 | HQ13: 3125909.2
A14: Gasto Aplicado Factor de Ingresos | B14: =SUM(C14:HP14) -> 1359585 | D14: 4430.3168 | E14: 6441.7488 | F14: 12162.689 | G14: 9280.3345 | I14: 4183.5445 | J14: 1261.2607 | K14: 10209.634 | O14: 3930.3129 | P14: 4176.2678 | Q14: 4371.5333 | R14: 3573.4968 | S14: 3257.7815 | T14: 8582.6093 | U14: 6449.0139 | V14: 5112.3432 | W14: 311.45894 | X14: 11897.727 | Y14: 5103.5303 | Z14: 8333.4446 | AA14: 8097.3945 | AB14: 2999.6839 | AC14: 6785.9644 | AD14: 2398.7721 | AE14: 4203.4607 | AF14: 7043.5079 | AG14: 19259.861 | AH14: 8577.2583 | AI14: 2478.6073 | AJ14: 4404.2004 | AK14: 7903.9501 | AL14: 4660.4184 | AM14: 4273.6147 | AN14: 7848.8663 | AO14: 5172.6097 | AP14: 4704.8552 | AQ14: 6701.6735 | AR14: 4867.3311 | AS14: 0 | AT14: 163.88287 | AU14: 6394.3002 | AV14: 1989.4222 | AW14: 6225.2272 | AX14: 15290.113 | AY14: 5381.4231 | AZ14: 9921.7915 | BA14: 3796.0389 | BB14: 16232.122 | BC14: 6400.8313 | BD14: 10649.76 | BE14: 5278.8882 | BF14: 7908.5663 | BG14: 16849.339 | BH14: 16123.05 | BI14: 14285.509 | BJ14: 14697.672 | BK14: 4070.177 | BL14: 7856.9671 | BM14: 10655.466 | BN14: 6074.7094 | BO14: 5052.7945 | BP14: 5402.6839 | BQ14: 2416.6772 | BR14: 9237.7751 | BS14: 0 | BT14: 8223.1426 | BU14: 4874.6266 | BV14: 11966.815 | BW14: 2336.4253 | BX14: 12945.167 | BY14: 5662.5125 | BZ14: 4736.2573 | CA14: 4771.5298 | CB14: 14705.086 | CC14: 4550.0501 | CD14: 2460.5779 | CE14: 1389.0294 | CF14: 4059.6351 | CG14: 3005.9395 | CH14: 2108.2092 | CI14: 3468.0507 | CJ14: 3602.8317 | CK14: 1860.4489 | CL14: 852.34258 | CM14: 6749.1379 | CN14: 12276.594 | CO14: 5007.6601 | CP14: 3015.0933 | CQ14: 8767.9426 | CR14: 3037.9088 | CS14: 3602.5631 | CT14: 12665.433 | CU14: 10836.419 | CV14: 8302.0194 | CW14: 11187.491 | CX14: 3857.6188 | CY14: 3463.5619 | CZ14: 5559.1349 | DA14: 5215.7608 | DB14: 6724.6909 | DC14: 1953.1598 | DD14: 1287.3351 | DE14: 7556.2567 | DF14: 4010.764 | DG14: 2786.0179 | DH14: 5452.3227 | DI14: 4771.2972 | DJ14: 7506.5825 | DK14: 3993.006 | DL14: 9936.3995 | DM14: 2759.4578 | DN14: 5513.2318 | DP14: 6800.782 | DQ14: 7425.0588 | DR14: 4076.4272 | DS14: 6756.0952 | DT14: 12274.664 | DU14: 305.88184 | DV14: 1445.2667 | DW14: 261.09843 | DX14: 411.72555 | DY14: 172.4073 | EA14: 89.601237 | EB14: 197.45912 | EC14: 6103.1323 | ED14: 4719.8586 | EE14: 14597.589 | EF14: 10823.138 | EG14: 4235.6269 | EH14: 6507.6292 | EI14: 2035.8639 | EJ14: 10643.836 | ES14: 7033.9072 | ET14: 4928.9974 | EU14: 10215.544 | EV14: 4050.3739 | EW14: 6850.4169 | EX14: 8434.4735 | EY14: 7822.9616 | EZ14: 11878.867 | FA14: 5722.1772 | FB14: 10954.691 | FC14: 14130.579 | FD14: 12780.43 | FE14: 6007.3631 | FF14: 4356.9109 | FG14: 11901.922 | FH14: 11768.956 | FI14: 10248.513 | FJ14: 9830.2684 | FK14: 2931.4735 | FL14: 4101.1039 | FM14: 3421.9695 | FN14: 3733.9735 | FO14: 1820.9627 | FP14: 11766.711 | FQ14: 9260.6446 | FS14: 3819.4607 | FT14: 1501.2373 | FU14: 782.68898 | FV14: 7878.0105 | FW14: 6031.7653 | FX14: 10961.564 | FY14: 5167.8106 | FZ14: 2848.1007 | GA14: 2951.5389 | GB14: 5983.2774 | GC14: 4492.4005 | GD14: 5532.1677 | GE14: 5801.3819 | GF14: 13198.849 | GG14: 7831.4367 | GH14: 2813.29 | GI14: 5118.6412 | GJ14: 5117.8684 | GK14: 16377.441 | GL14: 6184.475 | GM14: 20468.814 | GN14: 9151.4328 | GO14: 7977.2266 | GP14: 8454.7362 | GQ14: 2401.5051 | GR14: 3374.6921 | GT14: 9783.556 | GU14: 2967.8881 | GV14: 3593.17 | GW14: 7273.8302 | GX14: 12230.015 | GY14: 8390.2966 | GZ14: 7088.6367 | HB14: 4456.6827 | HC14: 7065.5974 | HD14: 7931.7638 | HE14: 4222.3009 | HF14: 46964.406 | HG14: 4894.3865 | HH14: 8123.854 | HI14: 6360.2045 | HJ14: 3825.486 | HK14: 12780.541 | HL14: 0 | HM14: 8019.6534 | HN14: 12565.148 | HO14: 4714.0616 | HP14: 9094.5664 | HQ14: 1359585
A15: Total General | B15: -5099598.1 | D15: -16530.113 | E15: -23149.7 | F15: -51230.972 | G15: -37569.912 | I15: 11815.102 | J15: 765.221 | K15: -36968.138 | O15: -21472.504 | P15: -15320.971 | Q15: -17234.061 | R15: -7565.064 | S15: -12467.008 | T15: -33502.481 | U15: -18409.788 | V15: -17828.094 | W15: -1508.713 | X15: -44573.699 | Y15: -15197.119 | Z15: -25271.416 | AA15: -42727.477 | AB15: -15765.053 | AC15: -40901.817 | AD15: -11794.33 | AE15: -21881.147 | AF15: -32236.259 | AG15: -69209.456 | AH15: -34696.87 | AI15: -7826.712 | AJ15: -17501.991 | AK15: -29517.659 | AL15: -19042.615 | AM15: -16942.881 | AN15: -26328.486 | AO15: -17878.851 | AP15: -12029.405 | AQ15: -18964.175 | AR15: -25436.896 | AS15: -2703.529 | AT15: -1035.213 | AU15: -24328.324 | AV15: -6307.386 | AW15: -26912.348 | AX15: -63248.91 | AY15: -23522.857 | AZ15: -44930.758 | BA15: -11992.954 | BB15: -46899.647 | BC15: -10142.545 | BD15: -45628.572 | BE15: -20920.776 | BF15: -28902.059 | BG15: -61749.769 | BH15: -52758.391 | BI15: -52666.26 | BJ15: -57484.967 | BK15: -13241.611 | BL15: -33525.023 | BM15: -47276.453 | BN15: -25604.99 | BO15: -13967.755 | BP15: -21503.214 | BQ15: -9347.69 | BR15: -42149.214 | BS15: 20147.584 | BT15: -25327.582 | BU15: -16728.506 | BV15: -45040.946 | BW15: -6104.929 | BX15: -48673.083 | BY15: -11100.916 | BZ15: -17324.526 | CA15: -18906.165 | CB15: -68446.983 | CC15: -16958.824 | CD15: -10871.644 | CE15: -3622.183 | CF15: -18817.618 | CG15: -16621.679 | CH15: -10636.114 | CI15: -18236.063 | CJ15: -13450.396 | CK15: -7977.457 | CL15: -2704.121 | CM15: -32726.108 | CN15: -56937.348 | CO15: -17032.056 | CP15: -9733.896 | CQ15: -33331.458 | CR15: -13428.61 | CS15: -16354.121 | CT15: -42182.445 | CU15: -45499.148 | CV15: -27590.536 | CW15: -46896.558 | CX15: -13508.124 | CY15: -11911.557 | CZ15: -16849.708 | DA15: -14657.733 | DB15: -36394.716 | DC15: -9019.417 | DD15: -3362.67 | DE15: -32537.763 | DF15: -14739.957 | DG15: -12302.043 | DH15: -20862.623 | DI15: -16568.21 | DJ15: -31129.048 | DK15: -13368.694 | DL15: -38779.071 | DM15: -12592.195 | DN15: -18868.492 | DP15: -15214.877 | DQ15: -27071.798 | DR15: -7268.903 | DS15: -27800.087 | DT15: -59654.221 | DU15: -467.449 | DV15: -2654.99 | DW15: -751.262 | DX15: -1628.228 | DY15: -170.637 | EA15: 128.454 | EB15: -540.878 | EC15: -24375.772 | ED15: -12195.553 | EE15: -54499.437 | EF15: -42628.291 | EG15: -12726.783 | EH15: -28953.088 | EI15: -7348.327 | EJ15: -49210.929 | ES15: -27455.011 | ET15: -19046.54 | EU15: -37977.276 | EV15: -18549.021 | EW15: -21560.177 | EX15: -26548.492 | EY15: -28303.633 | EZ15: -40488.466 | FA15: -14005.415 | FB15: -50322.222 | FC15: -51709.115 | FD15: -52001.107 | FE15: 10205.33 | FF15: -11823.952 | FG15: -45565.658 | FH15: -51208.5 | FI15: -31215.396 | FJ15: -40271.286 | FK15: -15873.82 | FL15: -18744.608 | FM15: -13653.2 | FN15: -14912.302 | FO15: -9236.786 | FP15: -47058.914 | FQ15: -34901.18 | FS15: -14368.445 | FT15: -4875.183 | FU15: -24335.156 | FV15: -35625.837 | FW15: -21671.026 | FX15: -45903.126 | FY15: -15488.805 | FZ15: -12643.02 | GA15: -10971.125 | GB15: -7832.318 | GC15: -13577.218 | GD15: -22468.919 | GE15: -31501.848 | GF15: -53386.457 | GG15: -30749.218 | GH15: -11827.722 | GI15: -20680.109 | GJ15: -22731.97 | GK15: -56305.472 | GL15: -14644.408 | GM15: -96656.001 | GN15: -35020.969 | GO15: -35292.365 | GP15: -31815.914 | GQ15: -8668.55 | GR15: -10228.574 | GT15: -40320.554 | GU15: -11199.002 | GV15: -14766.362 | GW15: -34120.393 | GX15: -60328.674 | GY15: -28482.762 | GZ15: -27754.158 | HB15: -21647.665 | HC15: -36234.678 | HD15: -24491.495 | HE15: -3651.329 | HF15: -122647.28 | HG15: -18935.818 | HH15: -31675.924 | HI15: -22076.161 | HJ15: -17364.558 | HK15: -38864.727 | HL15: 119.341 | HM15: -35192.788 | HN15: -58746.765 | HO15: -20044.465 | HP15: -32292.383 | HQ15: -5111985.6
A16: Resultado despues de Gasto Aplicado | B16: -1974115.4 | D16: -5479.7111 | E16: -9032.6385 | F16: -23041.891 | G16: -16947.043 | I16: 18604.057 | J16: 3576.7214 | K16: -14146.321 | O16: -12133.978 | P16: -5178.2012 | Q16: -6772.1969 | R16: 456.97867 | S16: -4829.0604 | T16: -14217.335 | U16: -5429.4547 | V16: -6159.4327 | W16: -832.22603 | X16: -16563.421 | Y16: -4905.7202 | Z16: -7632.0681 | AA16: -17975.099 | AB16: -6178.761 | AC16: -19079.244 | AD16: -4704.85 | AE16: -9686.6077 | AF16: -15290.768 | AG16: -27104.791 | AH16: -14607.71 | AI16: -1877.9927 | AJ16: -7568.2468 | AK16: -11466.121 | AL16: -7963.5259 | AM16: -6473.2162 | AN16: -9535.4323 | AO16: -6623.4772 | AP16: -3313.8256 | AQ16: -5027.7063 | AR16: -12569.869 | AS16: -1911.5353 | AT16: -695.89594 | AU16: -11314.061 | AV16: -1503.6907 | AW16: -12565.23 | AX16: -26768.26 | AY16: -10550.813 | AZ16: -21558.908 | BA16: -853.05206 | BB16: -12556.255 | BC16: 3103.2534 | BD16: -21220.119 | BE16: -6321.5576 | BF16: -11620.058 | BG16: -23959.366 | BH16: -19362.522 | BI16: -17913.283 | BJ16: -22583.264 | BK16: -4382.2647 | BL16: -16204.101 | BM16: -21530.043 | BN16: -11766.977 | BO16: -3438.5383 | BP16: -9320.4556 | BQ16: -3131.578 | BR16: -19922.025 | BS16: 20148.509 | BT16: -7615.509 | BU16: -7269.905 | BV16: -17695.027 | BW16: -907.2795 | BX16: -20236.384 | BY16: 2919.3888 | BZ16: -7116.2077 | CA16: -8597.0886 | CB16: -31945.588 | CC16: -7033.278 | CD16: -4241.9196 | CE16: 1283.958 | CF16: -8613.8985 | CG16: -6265.7906 | CH16: -5349.5635 | CI16: -9240.9314 | CJ16: -5798.369 | CK16: -3525.9529 | CL16: -564.30856 | CM16: -15643.634 | CN16: -25443.393 | CO16: -6735.2025 | CP16: -2584.4618 | CQ16: -12250.224 | CR16: -6393.7456 | CS16: -6524.1752 | CT16: -10199.31 | CU16: -20482.527 | CV16: -11025.521 | CW16: -19886.544 | CX16: -4173.0171 | CY16: -4435.7772 | CZ16: -5859.4768 | DA16: -5155.9159 | DB16: -21959.045 | DC16: -3683.1655 | DD16: 1031.1146 | DE16: -14417.996 | DF16: -5667.8017 | DG16: -5226.7832 | DH16: -7385.6739 | DI16: -6056.0376 | DJ16: -13088.703 | DK16: -3501.6387 | DL16: -15270.412 | DM16: -5741.5234 | DN16: -7702.5863 | DP16: 395.46503 | DQ16: -10598.372 | DR16: 1865.1031 | DS16: -12675.306 | DT16: -29941.021 | DU16: 242.81075 | DV16: 218.70587 | DW16: -35.572205 | DX16: -602.46338 | DY16: 368.14476 | EA16: 385.77783 | EB16: -59.699122 | EC16: -11436.954 | ED16: -2706.0381 | EE16: -18983.13 | EF16: -17860.259 | EG16: -3060.0151 | EH16: -14077.399 | EI16: -1907.9107 | EJ16: -24933.153 | ES16: -9235.3729 | ET16: -7511.6632 | EU16: -15245.296 | EV16: -9496.5134 | EW16: -7364.3492 | EX16: -10143.686 | EY16: -11551.687 | EZ16: -13404.602 | FA16: -920.97576 | FB16: -22001.409 | FC16: -19875.404 | FD16: -21945.639 | FE16: 20407.365 | FF16: -3532.1822 | FG16: -18779.646 | FH16: -25770.426 | FI16: -11637.011 | FJ16: -19264.11 | FK16: -7687.8789 | FL16: -8233.0923 | FM16: -5480.0716 | FN16: -6011.5507 | FO16: -3718.1601 | FP16: -19599.909 | FQ16: -14541.419 | FS16: -5253.7771 | FT16: -622.06526 | FU16: -15338.819 | FV16: -16371.427 | FW16: -7836.7956 | FX16: -20847.225 | FY16: -4764.0737 | FZ16: -5345.3854 | GA16: -4347.4613 | GB16: 3729.8156 | GC16: -3760.353 | GD16: -9630.58 | GE16: -16820.518 | GF16: -22087.985 | GG16: -13613.136 | GH16: -4508.9528 | GI16: -9662.9017 | GJ16: -10815.242 | GK16: -22798.752 | GL16: 329.99795 | GM16: -46148.465 | GN16: -12142.435 | GO16: -16793.861 | GP16: -12957.737 | GQ16: -1557.7009 | GR16: -2823.4806 | GT16: -17726.195 | GU16: -2574.0493 | GV16: -6679.1202 | GW16: -16390.888 | GX16: -29208.674 | GY16: -10459.504 | GZ16: -11673.666 | HB16: -10593.805 | HC16: -18648.824 | HD16: -9249.1627 | HE16: 5577.8394 | HF16: -36265.258 | HG16: -8168.8292 | HH16: -12623.351 | HI16: -8892.3841 | HJ16: -7824.7217 | HK16: -12908.505 | HL16: 121.54876 | HM16: -15434.347 | HN16: -27977.209 | HO16: -8967.9765 | HP16: -12566.621 | HQ16: -1986076.4

Sheet Sr Wilson 3
C3: Centro de Costo | D3: Total Ingresos | E3: Total Costos | F3: Total Gastos | G3: Total General CC | H3: % ingreso | I3: Gasto aplicado | J3: Resultado - Gastos Dis
A4: Tienda | C4: [ ACB ] - AV LIBERTADOR CIUDAD BOLIVAR (100.0%) | D4: [ ACG ] - ACHAGUAS (100.0%) | E4: [ ACO ] - ANACO (100.0%) | F4: [ ADO ] - ALTAGRACIA DEL ORITUCO (100.0%) | G4: [ ANT ] - ANTIMANO (100.0%) | H4: [ APU ] - APURE (100.0%) | I4: [ ARO - INT ] - AEROPUERTO INTERNACIONAL (100.0%) | J4: [ ARO - NAC ] - AEROPUERTO NACIONAL (100.0%) | K4: [ AVM ] - AVENIDA MARIÃ‘O (100.0%) | L4: [ BAC ] - BUENOS AIRES CANGURO (100.0%) | M4: [ BCC ] - BISCUCUY (100.0%) | N4: [ BCD ] - BARINAS CC DORADO (100.0%) | O4: [ BCN ] - BARCELONA (100.0%) | P4: [ BCO ] - BOCONÃ“ (100.0%) | Q4: [ BJM ] - BEJUMA (100.0%) | R4: [ BNS ] - BARINAS SHOP (100.0%) | S4: [ BRC ] - BARRANCAS (100.0%) | T4: [ BTA ] - BARUTA (100.0%) | U4: [ BVC ] - BAZAR VALENCIA CANGURO (100.0%) | V4: [ BZC ] - BAZAR 4 (100.0%) | W4: [ BZD ] - BAZAR 2 (100.0%) | X4: [ BZT ] - BAZAR 3 (100.0%) | Y4: [ BZU ] - BAZAR 1 (100.0%) | Z4: [ CAG ] - CAGUA (100.0%) | AA4: [ CAT ] - CATIA (100.0%) | AB4: [ CBM ] - CABIMAS (100.0%) | AC4: [ CBQ ] - CHABASQUEN (100.0%) | AD4: [ CBR ] - CABUDARE (100.0%) | AE4: [ CBV ] - CIUDAD BOLIVAR (100.0%) | AF4: [ CCA ] - CENTRO COMERCIAL AVIADORES (100.0%) | AG4: [ CCB ] - CALLE CAMEJO BARINAS (100.0%) | AH4: [ CCO ] - CAICARA DEL ORINOCO (100.0%) | AI4: [ CCT ] - CC CIUDAD TAMANACO (100.0%) | AJ4: [ CDL ] - LA CANDELARIA (100.0%) | AK4: [ CDO ] - CEDENO (100.0%) | AL4: [ CHA ] - CHACAO (100.0%) | AM4: [ CHC ] - CHICHIRIVICHE (100.0%) | AN4: [ CHI ] - CHIVACOA (100.0%) | AO4: [ CHV ] - CHARALLAVE (100.0%) | AP4: [ CJP ] - CINCO DE JULIO (100.0%) | AQ4: [ CLB ] - CALABOZO (100.0%) | AR4: [ CLL ] - CALLAO (100.0%) | AS4: [ CLP ] - CATIA LIFE PHONE (100.0%) | AT4: [ CMC ] - CUA (100.0%) | AU4: [ CMO ] - COMERCIO (100.0%) | AV4: [ CNA ] - CUMANACOA (100.0%) | AW4: [ COD ] - COSMOS SHOP (100.0%) | AX4: [ COE ] - SAN CARLOS (100.0%) | AY4: [ COR ] - CORO (100.0%) | AZ4: [ CPN ] - CARUPANO (100.0%) | BA4: [ CRP ] - CARIPE (100.0%) | BB4: [ CRR ] - CARORA (100.0%) | BC4: [ CRT ] - CARIPITO (100.0%) | BD4: [ CSZ ] - CAJA SECA ZULIA (100.0%) | BE4: [ CTA ] - CANTAURA (100.0%) | BF4: [ CTC ] - CITY 4 (100.0%) | BG4: [ CTD ] - CITY 2 (100.0%) | BH4: [ CTL ] - CARTANAL (100.0%) | BI4: [ CTM ] - CATIA LA MAR (100.0%) | BJ4: [ CTO ] - CEMENTERIO (100.0%) | BK4: [ CTS ] - CIUDAD TAMANACO SEGUNDO (100.0%) | BL4: [ CTT ] - CITY 3 (100.0%) | BM4: [ CTU ] - CITY 1 (100.0%) | BN4: [ CUA ] - CUMANA SHOP (100.0%) | BO4: [ CUG ] - CAUCAGUA (100.0%) | BP4: [ DCA ] - DUACA (100.0%) | BQ4: [ ECJ ] - EL CUJI (100.0%) | BR4: [ ECM ] ECOMMERCE (100.0%) | BS4: [ EJD ] - EJIDO (100.0%) | BT4: [ ELZ ] - ELORZA (100.0%) | BU4: [ FAM ] - FLOR AMARILLO (100.0%) | BV4: [ FMD ] - FREEMARKET 2 (100.0%) | BW4: [ FOR - CHV ] - FORUM CHARALLAVE (100.0%) | BX4: [ FOR - GTE ] FORUM GUATIRE (100.0%) | BY4: [ FOR - ISF ] - FORUM IPSFA (100.0%) | BZ4: [ FOR - PRS ] - FORUM PARAISO (100.0%) | CA4: [ FOR - PZV ] - FORUM PLAZA VENEZUELA (100.0%) | CB4: [ FRM ] - FREEMARKET (100.0%) | CC4: [ GCA ] - GUACARA (100.0%) | CD4: [ GIA ] - GÃœIRIA (100.0%) | CE4: [ GNO ] - GUANARITO (100.0%) | CF4: [ GNR ] - GUANARE (100.0%) | CG4: [ GNT ] - GUANTA (100.0%) | CH4: [ GPT ] - GUASIPATI (100.0%) | CI4: [ GRA ] - GUARENAS (100.0%) | CJ4: [ GTE ] - GUATIRE (100.0%) | CK4: [ GTN ] - GATO NEGRO (100.0%) | CL4: [ HGT ] - HIGUEROTE (100.0%) | CM4: [ IGD ] - CALLE IGUALDAD (100.0%) | CN4: [ LBD ] - LA BANDERA (100.0%) | CO4: [ LCH ] - LECHERIA (100.0%) | CP4: [ LLN ] - LLANERO (100.0%) | CQ4: [ LMU ] - LA MARRON 1 (100.0%) | CR4: [ LPG ] - LA PARAGUA (100.0%) | CS4: [ MCQ ] - MACHIQUES (100.0%) | CT4: [ MCY ] - MARACAY (100.0%) | CU4: [ MDB ] - MINAS DE BARUTA (100.0%) | CV4: [ MEC ] - MARACAY ESTACION CENTRAL (100.0%) | CW4: [ MGT ] - MARGARITA SHOP (100.0%) | CX4: [ MGZ ] - MENE GRANDE ZULIA (100.0%) | CY4: [ MID ] - MÃ‰RIDA SHOP (100.0%) | CZ4: [ MJN ] - MOJAN (100.0%) | DA4: [ MKD ] - MACROCENTRO 2 SHOP (100.0%) | DB4: [ MKU ] - MACROCENTRO 1 (100.0%) | DC4: [ MNT ] - MONAY TRUJILLO (100.0%) | DD4: [ MOC ] - CANGURO MOVIL (100.0%) | DE4: [ MPC ] - MARKET PLACE CANGURO (100.0%) | DF4: [ MRN ] - MORON (100.0%) | DG4: [ MTC ] - MANTECAL (100.0%) | DH4: [ MTP ] - METROPOLIS (100.0%) | DI4: [ MUN ] - MATURIN SHOP (100.0%) | DJ4: [ MVT - BVT ] MOVISTAR BELLA VISTA (100.0%) | DK4: [ MVT - CCT ] - MOVISTAR CIUDAD TAMANACO (100.0%) | DL4: [ MVT - GRZ ] MOVISTAR LAS GARZAS (100.0%) | DM4: [ MVT - LNS ] MOVISTAR LOS LEONES (100.0%) | DN4: [ MVT - LVÃ‘ ] MOVISTAR LA VIÃ‘A (100.0%) | DO4: [ MVT - PCC ] - MOVISTAR PARQUE CENTRAL CANAIMA (100.0%) | DP4: [ MVT - SCB ] MOVISTAR SAN CRISTÃ“BAL (100.0%) | DQ4: [ MVT- LDC ] MOVISTAR LAS DELICIAS (100.0%) | DR4: [ NGA ] - NIRGUA (100.0%) | DS4: [ NGT ] - NAIGUATA (100.0%) | DT4: [ OCT ] - OCUMARE DEL TUY (100.0%) | DU4: [ ODA ] - CIUDAD OJEDA (100.0%) | DV4: [ OPO ] - OSPINO (100.0%) | DW4: [ ORK ] - ORINOKIA (100.0%) | DX4: [ PDB ] - PEDRAZA (100.0%) | DY4: [ PDM ] - PUNTA DE MATA (100.0%) | DZ4: [ PDV - GCA ] - PDVSA GUACARA (100.0%) | EA4: [ PDV - GUO ] - PDVSA GUARAGUO (100.0%) | EB4: [ PDV - LCP ] - PDVSA LA CAMPIÃ‘A (100.0%) | EC4: [ PDV - LGN ] - PDVSA LAGUNA (100.0%) | ED4: [ PDV - MUN ] - PDVSA MATURIN (100.0%) | EE4: [ PDV - ODA ] - PDVSA CIUDAD OJEDA (100.0%) | EF4: [ PDV - PCD ] - PDVSA PETROCEDEÃ‘O (100.0%) | EG4: [ PDV - PT ] - PDVSA PETROPIAR (100.0%) | EH4: [ PDV - STM ] - PDVSA SANTOME (100.0%) | EI4: [ PDV - ZUL ] - PDVSA ZULIA (100.0%) | EJ4: [ PFO ] - PUNTO FIJO (100.0%) | EK4: [ PLN ] - PALO NEGRO (100.0%) | EL4: [ PLS ] - PUERTO LA CRUZ SHOP (100.0%) | EM4: [ PML ] - PLAZA MAYOR LECHERIA (100.0%) | EN4: [ PPT ] - PROPATRIA (100.0%) | EO4: [ PRG ] - PARIAGUAN (100.0%) | EP4: [ PRT ] - PUERTO PIRITU (100.0%) | EQ4: [ PSA ] - ACARIGUA (100.0%) | ER4: [ PTA ] - PUERTO AYACUCHO (100.0%) | ES4: [ PTC ] - PUERTO CABELLO (100.0%) | ET4: [ PTT ] - PETARE 3 (100.0%) | EU4: [ PTU ] - PETARE 1 (100.0%) | EV4: [ QBR ] - QUIBOR (100.0%) | EW4: [ QTC ] - QUINTA CRESPO (100.0%) | EX4: [ RCO ] - RIO CHICO (100.0%) | EY4: [ SAM - CDL ] - SAMBIL CANDELARIA (100.0%) | EZ4: [ SAM - CHA ] - SAMBIL CHACAO (100.0%) | FA4: [ SAM - LAR ] - SAMBIL LARA (100.0%) | FB4: [ SAM - MGT ] - SAMBIL MARGARITA (100.0%) | FC4: [ SAM - PFO ] - SAMBIL PUNTO FIJO (100.0%) | FD4: [ SAM - VLC ] - SAMBIL VALENCIA (100.0%) | FE4: [ SAM - ZUL ] - SAMBIL ZULIA (100.0%) | FF4: [ SBB ] - SANTA BARBARA (100.0%) | FG4: [ SBC ] - SABANA CITY (100.0%) | FH4: [ SBO ] - EL SOMBRERO (100.0%) | FI4: [ SCM ] - SANÂ CASIMIRO (100.0%) | FJ4: [ SCP ] - SOCOPO (100.0%) | FK4: [ SEU ] - SANTA ELENA DE UAIREN (100.0%) | FL4: [ SFX ] - SAN FELIX (100.0%) | FM4: [ SGO ] - SABANA GRANDE OUTLET (100.0%) | FN4: [ SJM ] - SAN JUAN DE LOS MORROS (100.0%) | FO4: [ SMT ] - SABANA MENDOZA (100.0%) | FP4: [ SMZ ] - SIERRA MAESTRA (100.0%) | FQ4: [ SNR ] - SANARE (100.0%) | FR4: [ SNT ] - SABANETA (100.0%) | FS4: [ SRO ] - SAN RAFAEL DE ONOTO (100.0%) | FT4: [ STL ] - SANTA LUCIA (100.0%) | FU4: [ STR ] - SANTA RITA ARAGUA (100.0%) | FV4: [ STT ] - SANTA TERESA DEL TUY (100.0%) | FW4: [ TBD ] - TEMBLADOR (100.0%) | FX4: [ TCC ] - TUCACAS (100.0%) | FY4: [ TCD ] - TUCUPIDO (100.0%) | FZ4: [ TCO ] - TOCUYO (100.0%) | GA4: [ TCP ] - TUCUPITA (100.0%) | GB4: [ TCY ] - TOCUYITO (100.0%) | GC4: [ TED ] - LOS TEQUES DOS (100.0%) | GD4: [ TEQ ] - LOS TEQUES SHOP (100.0%) | GE4: [ TGO ] - EL TIGRITO (100.0%) | GF4: [ TGR ] - TIGRE SHOP (100.0%) | GG4: [ THA ] - TACHIRA (100.0%) | GH4: [ TJL ] - TRUJILLO (100.0%) | GI4: [ TLG ] - TERMINAL LA GUAIRA (100.0%) | GJ4: [ TMO ] - TURMERO (100.0%) | GK4: [ TMR ] - TUMEREMO (100.0%) | GL4: [ TPV ] - TERMINAL PLAZA VENEZUELA (100.0%) | GM4: [ TQO ] - TINAQUILLO (100.0%) | GN4: [ TRN ] - TUREN (100.0%) | GO4: [ TRU ] - VALERA SHOP (100.0%) | GP4: [ UNR ] - UNARE (100.0%) | GQ4: [ UPT ] - UPATA (100.0%) | GR4: [ URD ] - URDANETA SHOP (100.0%) | GS4: [ URF ] - URDANETA FIX (100.0%) | GT4: [ VAR ] - LA GUAIRA (100.0%) | GU4: [ VDC ] - VILLA DE CURA (100.0%) | GV4: [ VDP ] - VALLE DE LA PASCUA (100.0%) | GW4: [ VGA ] - LA VEGA (100.0%) | GX4: [ VIG ] - VIGIA (100.0%) | GY4: [ VLL ] - EL VALLE (100.0%) | GZ4: [ VTA ] - LA VICTORIA (100.0%) | HA4: [ YAR ] - SAN FELIPE (100.0%) | HB4: [ YTG ] - YARITAGUA (100.0%) | HC4: [ ZAR ] - ZARAZA (100.0%) | HD4: [ ADS - VAR ] - AEDOS LA GUAIRA (100.0%) | HE4: [ CCM ] - CENTRO COMERCIAL METROCENTER (100.0%) | HF4: [ EMT ] - EL MANTECO (100.0%) | HG4: [ TQT ] - LOS TEQUES TRES (100.0%) | HH4: [ GBZ ] - GRAN BAZAR 5 ZULIA (100.0%) | HI4: [ JQT ] - EL JUNQUITO (100.0%) | HJ4: [ CRN ] - CLARINES (100.0%) | HK4: [ SCC ] - CANGURO SELLCENTER (100.0%) | HL4: Total general
A5: Ingresos | C5: -16420.285 | D5: -30098.35 | E5: -79557.045 | F5: -38738.39 | G5: -31702.703 | H5: -75182.005 | I5: -5791.3039 | J5: -8062.1671 | K5: -35368 | L5: -22183.714 | M5: -25422.353 | N5: -22309.495 | O5: -56551.018 | P5: -40307.835 | Q5: -32291.73 | R5: -65768.033 | S5: -27569.72 | T5: -41365.876 | U5: -65132.924 | V5: -30724.553 | W5: -70755.446 | X5: -20665.979 | Y5: -31283.001 | Z5: -42926.093 | AA5: -84185.181 | AB5: -64801.332 | AC5: -19258.52 | AD5: -29421.965 | AE5: -52549.423 | AF5: -26154.751 | AG5: -30970.117 | AH5: -56843.329 | AI5: -21216.428 | AJ5: -35552.059 | AK5: -38397.217 | AL5: -38272.709 | AM5: -14140.096 | AN5: -29022.718 | AO5: -104753.18 | AP5: -32112.251 | AQ5: -55750.942 | AR5: -73649.145 | AS5: -74383.693 | AT5: -57989.75 | AU5: -44818.539 | AV5: -39239.768 | AW5: -83637.399 | AX5: -82749.309 | AY5: -76756.398 | AZ5: -76646.627 | BA5: -48156.326 | BB5: -67356.485 | BC5: -34912.527 | BD5: -31901.938 | BE5: -32921.082 | BF5: 0 | BG5: -12515.677 | BH5: -40548.624 | BI5: -70046.469 | BJ5: -51010.104 | BK5: -22714.647 | BL5: -75094.302 | BM5: -9841.0006 | BN5: -70337.568 | BO5: -31265.09 | BP5: -20286.496 | BQ5: -25156.368 | BR5: -547431.41 | BS5: -30973.905 | BT5: -27286.745 | BU5: -24582.882 | BV5: -24635.006 | BW5: -7822.2115 | BX5: -20661.255 | BY5: -16035.904 | BZ5: -11702.947 | CA5: -5978.4897 | CB5: -38883.731 | CC5: -69413.492 | CD5: -23414.2 | CE5: -23268.952 | CF5: -56248.979 | CG5: -14263.466 | CH5: -46591.871 | CI5: -44267.768 | CJ5: -50472.063 | CK5: -29656.507 | CL5: -59168.62 | CM5: -31155.965 | CN5: -20518.666 | CO5: -32911.513 | CP5: -24850.737 | CQ5: -25549.105 | CR5: -32899.219 | CS5: -17346.034 | CT5: -40480.253 | CU5: -21807.269 | CV5: -13190.986 | CW5: -44718.011 | CX5: -19966.899 | CY5: -54491.956 | CZ5: -31068.24 | DA5: -67791.155 | DB5: -18371.479 | DC5: -29754.704 | DD5: 0 | DE5: -37839.125 | DF5: -34949.712 | DG5: -24656.468 | DH5: -39284.31 | DI5: -100391.53 | DJ5: -2079.4348 | DK5: -4027.2475 | DL5: -1608.0683 | DM5: -3514.9796 | DN5: -2814.2406 | DO5: -8331.8913 | DP5: -2643.136 | DQ5: -798.3788 | DR5: -31745.627 | DS5: -16053.831 | DT5: -92498.368 | DU5: -76223.974 | DV5: -25637.911 | DW5: -38345.216 | DX5: -20861.682 | DY5: -74804.256 | DZ5: -2231.0521 | EA5: -814.0003 | EB5: -4837.8031 | EC5: -643.0311 | ED5: -3934.0037 | EE5: -736.1809 | EF5: -374.0006 | EG5: -1085.0012 | EH5: -2197.9108 | EI5: -1968.0009 | EJ5: -47563 | EK5: -29919.013 | EL5: -67630.386 | EM5: -26699.456 | EN5: -25551.927 | EO5: -43378.894 | EP5: -46867.981 | EQ5: -82524.161 | ER5: -54310.329 | ES5: -71568.525 | ET5: -71203.045 | EU5: -71015.927 | EV5: -37111.65 | EW5: -18886.807 | EX5: -58694.535 | EY5: -84186.18 | EZ5: -41373.43 | FA5: -53193.666 | FB5: -28368 | FC5: -30911.52 | FD5: -17469.626 | FE5: -20747.076 | FF5: -20584.982 | FG5: -65645.382 | FH5: -41536.553 | FI5: -20675.227 | FJ5: -20445.248 | FK5: -67071.741 | FL5: -50763.335 | FM5: -41272.29 | FN5: -74714.968 | FO5: -37005.531 | FP5: -16947.29 | FQ5: -20749.915 | FR5: -41064.798 | FS5: -23926.768 | FT5: -29264.056 | FU5: -27316.253 | FV5: -92246.548 | FW5: -50772.992 | FX5: -23534.191 | FY5: -23256.796 | FZ5: -21303.08 | GA5: -95669.757 | GB5: -44429.067 | GC5: -119822.16 | GD5: -58530.338 | GE5: -54798.269 | GF5: -56719.568 | GG5: -17819.397 | GH5: -21598.924 | GI5: -5146.9983 | GJ5: -61012.973 | GK5: -49369.203 | GL5: -20436.73 | GM5: -34926.468 | GN5: -62778.25 | GO5: -43929.481 | GP5: -25576.881 | GQ5: -55893.661 | GR5: -31938.685 | GS5: -25962.177 | GT5: -102599.39 | GU5: -26508.788 | GV5: -49129.255 | GW5: -35477.185 | GX5: -34962.066 | GY5: -56190.792 | GZ5: -54402.334 | HA5: -66609.666 | HB5: -27700.97 | HC5: -45155.614 | HD5: 0 | HE5: -17357.021 | HF5: -29214.655 | HG5: -71736.235 | HH5: 0 | HI5: 0 | HJ5: 0 | HK5: 0
A6: Costos | C6: 6947.4527 | D6: 14687.742 | E6: 32697.559 | F6: 15998.935 | G6: 11997.412 | H6: 34119.283 | I6: 2333.7607 | J6: 2968.2677 | K6: 16132.549 | L6: 8740.6518 | M6: 13834.797 | N6: 9401.8043 | O6: 20768.794 | P6: 19545.71 | Q6: 15114.514 | R6: 31036.039 | S6: 15663.179 | T6: 15910.026 | U6: 30460.891 | V6: 16093.052 | W6: 41079.543 | X6: 9301.5252 | Y6: 17477.489 | Z6: 15726.934 | AA6: 34699.062 | AB6: 26992.142 | AC6: 11468.388 | AD6: 9890.8362 | AE6: 22945.701 | AF6: 9630.4932 | AG6: 13907.911 | AH6: 31562.383 | AI6: 7095.0003 | AJ6: 14662.867 | AK6: 16686.886 | AL6: 16240.194 | AM6: 8624.336 | AN6: 11659.214 | AO6: 45016.028 | AP6: 11886.475 | AQ6: 21969.585 | AR6: 42411.355 | AS6: 34498.453 | AT6: 21224.968 | AU6: 21282.435 | AV6: 17009.854 | AW6: 31622.05 | AX6: 36412.643 | AY6: 38269.507 | AZ6: 34257.674 | BA6: 20436.175 | BB6: 29636.054 | BC6: 15106.176 | BD6: 14932.619 | BE6: 13286.65 | BF6: (en blanco) | BG6: 5976.4705 | BH6: 16763.154 | BI6: 28596.08 | BJ6: 24101.751 | BK6: 7425.6234 | BL6: 31597.05 | BM6: 5077.159 | BN6: 25625.144 | BO6: 13794.725 | BP6: 9168.1681 | BQ6: 8755.1662 | BR6: 257180.2 | BS6: 14470.405 | BT6: 13875.035 | BU6: 10056.756 | BV6: 11559.601 | BW6: 3393.0682 | BX6: 7693.9953 | BY6: 5921.1911 | BZ6: 4790.1671 | CA6: 2126.75 | CB6: 16796.457 | CC6: 27927.477 | CD6: 9522.8568 | CE6: 12972.288 | CF6: 26139.363 | CG6: 5673.432 | CH6: 27023.395 | CI6: 16866.494 | CJ6: 19506.678 | CK6: 10438.922 | CL6: 27567.433 | CM6: 12100.085 | CN6: 7416.3736 | CO6: 11363.818 | CP6: 9108.3727 | CQ6: 9468.4332 | CR6: 20733.548 | CS6: 11249.81 | CT6: 17417.435 | CU6: 8284.4329 | CV6: 6057.6498 | CW6: 16751.033 | CX6: 8875.8979 | CY6: 26484.497 | CZ6: 15486.05 | DA6: 28634.227 | DB6: 8383.4926 | DC6: 13288.92 | DD6: (en blanco) | DE6: 17266.154 | DF6: 15606.435 | DG6: 13402.16 | DH6: 12821.609 | DI6: 40195.569 | DJ6: 1246.8934 | DK6: 2497.6071 | DL6: 936.7021 | DM6: 1652.3591 | DN6: 1298.2914 | DO6: 4571.3865 | DP6: 1423.5313 | DQ6: 405.2312 | DR6: 15509.044 | DS6: 6854.8878 | DT6: 42796.881 | DU6: 32194.092 | DV6: 13712.533 | DW6: 13254.677 | DX6: 11241.69 | DY6: 29881.941 | DZ6: 696.5109 | EA6: 221.9037 | EB6: 1525.7727 | EC6: 128.8214 | ED6: 1426.2823 | EE6: 162.4465 | EF6: 88.3497 | EG6: 375.453 | EH6: 903.7551 | EI6: 716.539 | EJ6: 28121.859 | EK6: 11142.342 | EL6: 25396.804 | EM6: 9538.4559 | EN6: 9321.1773 | EO6: 17837.17 | EP6: 18666.518 | EQ6: 35488.581 | ER6: 27797.566 | ES6: 30904.997 | ET6: 29169.396 | EU6: 32566.435 | EV6: 14740.665 | EW6: 7043.3004 | EX6: 25346.786 | EY6: 30688.717 | EZ6: 12600.461 | FA6: 16385.001 | FB6: 9254.325 | FC6: 6697.9514 | FD6: 6704.6249 | FE6: 6896.2046 | FF6: 12560.1 | FG6: 26034.164 | FH6: 17094.964 | FI6: 8705.8202 | FJ6: 10837.288 | FK6: 42199.851 | FL6: 22156.199 | FM6: 18268.771 | FN6: 29181.403 | FO6: 15775.65 | FP6: 7397.169 | FQ6: 9568.685 | FR6: 20229.571 | FS6: 10495.845 | FT6: 11895.096 | FU6: 9612.9945 | FV6: 42560.749 | FW6: 20569.892 | FX6: 11283.175 | FY6: 9093.0145 | FZ6: 8726.9066 | GA6: 42499.916 | GB6: 18959.229 | GC6: 51932.716 | GD6: 25295.659 | GE6: 22747.492 | GF6: 22177.551 | GG6: 9203.7434 | GH6: 8384.4548 | GI6: 2134.2161 | GJ6: 25166.191 | GK6: 29655.352 | GL6: 8101.9835 | GM6: 15726.395 | GN6: 28085.552 | GO6: 16830.663 | GP6: 10429.747 | GQ6: 28569.154 | GR6: 12526.994 | GS6: 8040.6543 | GT6: 47110.348 | GU6: 10943.292 | GV6: 20626.726 | GW6: 13481.776 | GX6: 16528.559 | GY6: 21546.244 | GZ6: 23760.07 | HA6: 27337.328 | HB6: 10478.711 | HC6: 19185.103 | HD6: 36.44 | HE6: 6670.5461 | HF6: 19273.358 | HG6: 29698.252 | HH6: (en blanco) | HI6: 0 | HJ6: 0 | HK6: (en blanco)
